Workbook
Name ccc: #REF!
Name ccc: #REF!
Name cmndBase: #REF!
Name cmndBase: #REF!
Name cmndDayMonthTo: #REF!
Name cmndDayMonthTo: #REF!
Name cmndDays: #REF!
Name cmndDays: #REF!
Name cmndDocNum: #REF!
Name cmndDocNum: #REF!
Name cmndDocSer: #REF!
Name cmndDocSer: #REF!
Name cmndFIO: #REF!
Name cmndFIO: #REF!
Name cmndOrdDay: #REF!
Name cmndOrdDay: #REF!
Name cmndOrdMonth: #REF!
Name cmndOrdMonth: #REF!
Name cmndOrdNum: #REF!
Name cmndOrdNum: #REF!
Name cmndOrdYear: #REF!
Name cmndOrdYear: #REF!
Name cmndPoint: #REF!
Name cmndPoint: #REF!
Name cmndPoint1: #REF!
Name cmndPoint1: #REF!
Name cmndPos: #REF!
Name cmndPos: #REF!
Name cmndYearTo: #REF!
Name cmndYearTo: #REF!
Name cntAddition: #REF!
Name cntAddition: #REF!
Name cntDay: #REF!
Name cntDay: #REF!
Name cntMonth: #REF!
Name cntMonth: #REF!
Name cntName: #REF!
Name cntName: #REF!
Name cntNumber: #REF!
Name cntNumber: #REF!
Name cntPayer: #REF!
Name cntPayer: #REF!
Name cntPayer1: #REF!
Name cntPayer1: #REF!
Name cntPayerAddr1: #REF!
Name cntPayerAddr1: #REF!
Name cntPayerAddr2: #REF!
Name cntPayerAddr2: #REF!
Name cntPayerBank1: #REF!
Name cntPayerBank1: #REF!
Name cntPayerBank2: #REF!
Name cntPayerBank2: #REF!
Name cntPayerBank3: #REF!
Name cntPayerBank3: #REF!
Name cntPayerCount: #REF!
Name cntPayerCount: #REF!
Name cntPayerCountCor: #REF!
Name cntPayerCountCor: #REF!
Name cntPriceC: #REF!
Name cntPriceC: #REF!

Sheet Выпадение всего
A2: УГОЛЬ экспорт | G2: Справочно коэфф по направлениям:
C3: Значения | H3: Значения
A4: Вид груза | B4: Направление | C4: Сумма по полю Объем перевозок (тн) | D4: Сумма по полю объем* коэфф | E4: Сумма по полю Средний коэфф сохранения базы | G4: Названия строк | H4: Сумма по полю Объем перевозок (тн) | I4: Сумма по полю объем* коэфф | J4: Сумма по полю Средний коэфф сохранения базы
A5: антрацит (энергетический уголь) | B5: Восточное | C5: 2022773 | D5: 2022773 | E5: 1 | G5: Восточное | H5: 16935950 | I5: 16884958 | J5: 0.9969891
A6: антрацит (энергетический уголь) Итог | C6: 2022773 | D6: 2022773 | E6: 1 | G6: Северо-Западное | H6: 10287319 | I6: 10061954 | J6: 0.97809295
A7: уголь для коксования | B7: Восточное | C7: 1434447 | D7: 1434447 | E7: 1 | G7: Южное | H7: 3748943 | I7: 3727812.4 | J7: 0.99436358
B8: Северо-Западное | C8: 51530 | D8: 51530 | E8: 1 | G8: Общий итог | H8: 30972212 | I8: 30674724 | J8: 0.99039501
B9: Южное | C9: 595825 | D9: 595825 | E9: 1
A10: уголь для коксования Итог | C10: 2081802 | D10: 2081802 | E10: 1 | G10: ПАРАМЕТРЫ ИЗМЕНЕНИЯ ТАРИФА
A11: уголь энергетический (кроме антрацита) | B11: Восточное | C11: 13478730 | D11: 13427738 | E11: 0.99621682 | G11: TRUE | H11: TRUE | J11: FALSE
B12: Северо-Западное | C12: 10235789 | D12: 10010424 | E12: 0.97798266 | G12: до 50% | I12: до -50%
B13: Южное | C13: 3153118 | D13: 3131987.4 | E13: 0.9932985 | G13: ИНДЕКСАЦИЯ
A14: уголь энергетический (кроме антрацита) Итог | C14: 26867637 | D14: 26570149 | E14: 0.98892765 | I14: 45 | J14: 0.1
A15: Общий итог | C15: 30972212 | D15: 30674724 | E15: 0.99039501
G16: СКИДКА
I17: 0 | J17: =-(I17/1000) -> 0
A24: млн.тонн | B24: 2025 | D24: 2026 | H24: 2027 | L24: 2028 | P24: 2029 | T24: 2030
B25: Факт ИХ перевезено | C25: Факт (по плану погрузки) | D25: План | E25: с учетом чувствительности | F25: +/- | G25: +/- % | H25: План | I25: с учетом чувствительности | J25: +/- | K25: +/- % | L25: План | M25: с учетом чувствительности | N25: +/- | O25: +/- % | P25: План | Q25: с учетом чувствительности | R25: +/- | S25: +/- % | T25: План | U25: с учетом чувствительности | V25: +/- | W25: +/- %
A26: Всего погрузка: | B26: =B27+B28 -> 327.53617 | C26: =C27+C28 -> 324.46634 | D26: =D27+D28 -> 328.24059 | E26: =E27+E28 -> 327.05762 | F26: =E26-D26 -> -1.1829684 | G26: =F26/D26 -> -0.0036039674 | H26: =H27+H28 -> 326.22648 | I26: =I27+I28 -> 325.04866 | J26: =I26-H26 -> -1.1778266 | K26: =J26/H26 -> -0.0036104568 | L26: =L27+L28 -> 326.725 | M26: =M27+M28 -> 325.5405 | N26: =M26-L26 -> -1.184503 | O26: =N26/L26 -> -0.0036253823 | P26: =P27+P28 -> 327.511 | Q26: =Q27+Q28 -> 326.29489 | R26: =Q26-P26 -> -1.21611 | S26: =R26/P26 -> -0.0037131884 | T26: =T27+T28 -> 328.9 | U26: =U27+U28 -> 327.64686 | V26: =U26-T26 -> -1.2531352 | W26: =V26/T26 -> -0.0038100798
A27: Внутренние | B27: 148.39864 | C27: ='План погрузки'!G20 -> 147.43839 | D27: ='План погрузки'!H20 -> 143.42277 | E27: =D27 -> 143.42277 | H27: ='План погрузки'!I20 -> 143.539 | I27: =H27 -> 143.539 | L27: ='План погрузки'!J20 -> 143.525 | M27: =L27 -> 143.525 | P27: ='План погрузки'!K20 -> 143.811 | Q27: =P27 -> 143.811 | T27: ='План погрузки'!L20 -> 144.4 | U27: =T27 -> 144.4
A28: Экспорт | B28: =B33+B37+B41 -> 179.13752 | C28: =SUM(C29:C31) -> 177.02795 | D28: =SUM(D29:D31) -> 184.81782 | E28: =E33+E37+E41 -> 183.63485 | F28: =E28-D28 -> -1.1829684 | G28: =F28/D28 -> -0.0064007268 | H28: =SUM(H29:H31) -> 182.68748 | I28: =I33+I37+I41 -> 181.50966 | J28: =I28-H28 -> -1.1778266 | K28: =J28/H28 -> -0.0064472212 | L28: =SUM(L29:L31) -> 183.2 | M28: =M33+M37+M41 -> 182.0155 | N28: =M28-L28 -> -1.184503 | O28: =N28/L28 -> -0.0064656279 | P28: =SUM(P29:P31) -> 183.7 | Q28: =Q33+Q37+Q41 -> 182.48389 | R28: =Q28-P28 -> -1.21611 | S28: =R28/P28 -> -0.0066200873 | T28: =SUM(T29:T31) -> 184.5 | U28: =U33+U37+U41 -> 183.24686 | V28: =U28-T28 -> -1.2531352 | W28: =V28/T28 -> -0.006792061
A29: Восточное | B29: =B34+B38+B42 -> 118.71894 | C29: ='План погрузки'!G72 -> 118.19677 | D29: ='План погрузки'!H72 -> 119.96579 | E29: =E34+E38+E42 -> 119.65578 | F29: =E29-D29 -> -0.31001173 | G29: =F29/D29 -> -0.0025841678 | H29: ='План погрузки'!I72 -> 117.707 | I29: =I34+I38+I42 -> 117.40283 | J29: =I29-H29 -> -0.30417464 | K29: =J29/H29 -> -0.0025841678 | L29: ='План погрузки'!J72 -> 117.707 | M29: =M34+M38+M42 -> 117.40283 | N29: =M29-L29 -> -0.30417464 | O29: =N29/L29 -> -0.0025841678 | P29: ='План погрузки'!K72 -> 116.197 | Q29: =Q34+Q38+Q42 -> 115.89673 | R29: =Q29-P29 -> -0.30027255 | S29: =R29/P29 -> -0.0025841678 | T29: ='План погрузки'!L72 -> 114.707 | U29: =U34+U38+U42 -> 114.41058 | V29: =U29-T29 -> -0.29642214 | W29: =V29/T29 -> -0.0025841678
A30: Северо-Западное | B30: =B35+B39+B43 -> 39.259007 | C30: ='План погрузки'!G46 -> 38.307818 | D30: ='План погрузки'!H46 -> 37.677301 | E30: =E35+E39+E43 -> 36.951446 | F30: =E30-D30 -> -0.72585494 | G30: =F30/D30 -> -0.019265046 | H30: ='План погрузки'!I46 -> 37.677301 | I30: =I35+I39+I43 -> 36.951446 | J30: =I30-H30 -> -0.72585494 | K30: =J30/H30 -> -0.019265046 | L30: ='План погрузки'!J46 -> 37.959 | M30: =M35+M39+M43 -> 37.227718 | N30: =M30-L30 -> -0.73128188 | O30: =N30/L30 -> -0.019265046 | P30: ='План погрузки'!K46 -> 39.737 | Q30: =Q35+Q39+Q43 -> 38.971465 | R30: =Q30-P30 -> -0.76553514 | S30: =R30/P30 -> -0.019265046 | T30: ='План погрузки'!L46 -> 41.793 | U30: =U35+U39+U43 -> 40.987856 | V30: =U30-T30 -> -0.80514407 | W30: =V30/T30 -> -0.019265046
A31: Южное | B31: =B36+B40+B44 -> 21.159581 | C31: ='План погрузки'!G59 -> 20.523359 | D31: ='План погрузки'!H59 -> 27.174729 | E31: =E36+E40+E44 -> 27.027627 | F31: =E31-D31 -> -0.1471017 | G31: =F31/D31 -> -0.00541318 | H31: ='План погрузки'!I59 -> 27.303182 | I31: =I36+I40+I44 -> 27.155385 | J31: =I31-H31 -> -0.14779704 | K31: =J31/H31 -> -0.00541318 | L31: ='План погрузки'!J59 -> 27.534 | M31: =M36+M40+M44 -> 27.384954 | N31: =M31-L31 -> -0.1490465 | O31: =N31/L31 -> -0.00541318 | P31: ='План погрузки'!K59 -> 27.766 | Q31: =Q36+Q40+Q44 -> 27.615698 | R31: =Q31-P31 -> -0.15030236 | S31: =R31/P31 -> -0.00541318 | T31: ='План погрузки'!L59 -> 28 | U31: =U36+U40+U44 -> 27.848431 | V31: =U31-T31 -> -0.15156904 | W31: =V31/T31 -> -0.00541318
A32: в т.ч. Экспорт:
A33: уголь энергетический (кроме антрацита) | B33: =B34+B35+B36 -> 132.53632 | D33: =SUM(D34:D36) -> 136.86279 | E33: =SUM(E34:E36) -> 135.67982 | F33: =E33-D33 -> -1.1829684 | G33: =F33/D33 -> -0.0086434623 | H33: =SUM(H34:H36) -> 135.42364 | I33: =SUM(I34:I36) -> 134.24582 | J33: =I33-H33 -> -1.1778266 | K33: =J33/H33 -> -0.0086973485 | L33: =SUM(L34:L36) -> 135.85657 | M33: =SUM(M34:M36) -> 134.67207 | N33: =M33-L33 -> -1.184503 | O33: =N33/L33 -> -0.008718776 | P33: =SUM(P34:P36) -> 136.56828 | Q33: =SUM(Q34:Q36) -> 135.35217 | R33: =Q33-P33 -> -1.21611 | S33: =R33/P33 -> -0.0089047768 | T33: =SUM(T34:T36) -> 137.53851 | U33: =SUM(U34:U36) -> 136.28538 | V33: =U33-T33 -> -1.2531352 | W33: =V33/T33 -> -0.009111159
A34: Восточное | B34: 81.09312 | D34: =$D$29*$B$34/$B$29 -> 81.944806 | E34: =$E$11*D34 -> 81.634794 | F34: =E34-D34 -> -0.31001173 | G34: =F34/D34 -> -0.0037831773 | H34: =$H$29*$B$34/$B$29 -> 80.401899 | I34: =$E$11*H34 -> 80.097725 | J34: =I34-H34 -> -0.30417464 | K34: =J34/H34 -> -0.0037831773 | L34: =$L$29*$B$34/$B$29 -> 80.401899 | M34: =$E$11*L34 -> 80.097725 | N34: =M34-L34 -> -0.30417464 | O34: =N34/L34 -> -0.0037831773 | P34: =$P$29*$B$34/$B$29 -> 79.370467 | Q34: =$E$11*P34 -> 79.070194 | R34: =Q34-P34 -> -0.30027255 | S34: =R34/P34 -> -0.0037831773 | T34: =$T$29*$B$34/$B$29 -> 78.352695 | U34: =$E$11*T34 -> 78.056273 | V34: =U34-T34 -> -0.29642214 | W34: =V34/T34 -> -0.0037831773
A35: Северо-Западное | B35: 34.351411 | D35: =$D$30*$B$35/$B$30 -> 32.967427 | E35: =$E$12*D35 -> 32.241572 | F35: =E35-D35 -> -0.72585494 | G35: =F35/D35 -> -0.022017337 | H35: =$H$30*$B$35/$B$30 -> 32.967427 | I35: =$E$12*H35 -> 32.241572 | J35: =I35-H35 -> -0.72585494 | K35: =J35/H35 -> -0.022017337 | L35: =$L$30*$B$35/$B$30 -> 33.213912 | M35: =$E$12*L35 -> 32.48263 | N35: =M35-L35 -> -0.73128188 | O35: =N35/L35 -> -0.022017337 | P35: =$P$30*$B$35/$B$30 -> 34.769652 | Q35: =$E$12*P35 -> 34.004117 | R35: =Q35-P35 -> -0.76553514 | S35: =R35/P35 -> -0.022017337 | T35: =$T$30*$B$35/$B$30 -> 36.568641 | U35: =$E$12*T35 -> 35.763497 | V35: =U35-T35 -> -0.80514407 | W35: =V35/T35 -> -0.022017337
A36: Южное | B36: 17.091784 | D36: =$D$31*$B$36/$B$31 -> 21.950557 | E36: =$E$13*D36 -> 21.803456 | F36: =E36-D36 -> -0.1471017 | G36: =F36/D36 -> -0.0067015018 | H36: =$H$31*$B$36/$B$31 -> 22.054316 | I36: =$E$13*H36 -> 21.906519 | J36: =I36-H36 -> -0.14779704 | K36: =J36/H36 -> -0.0067015018 | L36: =$L$31*$B$36/$B$31 -> 22.240761 | M36: =$E$13*L36 -> 22.091714 | N36: =M36-L36 -> -0.1490465 | O36: =N36/L36 -> -0.0067015018 | P36: =$P$31*$B$36/$B$31 -> 22.42816 | Q36: =$E$13*P36 -> 22.277858 | R36: =Q36-P36 -> -0.15030236 | S36: =R36/P36 -> -0.0067015018 | T36: =$T$31*$B$36/$B$31 -> 22.617175 | U36: =$E$13*T36 -> 22.465606 | V36: =U36-T36 -> -0.15156904 | W36: =V36/T36 -> -0.0067015018
A37: уголь для коксования | B37: =B38+B39+B40 -> 32.077955 | D37: =SUM(D38:D40) -> 32.896365 | E37: =SUM(E38:E40) -> 32.896365 | F37: =E37-D37 -> 0 | G37: =F37/D37 -> 0 | H37: =SUM(H38:H40) -> 32.385708 | I37: =SUM(I38:I40) -> 32.385708 | J37: =I37-H37 -> 0 | K37: =J37/H37 -> 0 | L37: =SUM(L38:L40) -> 32.426464 | M37: =SUM(M38:M40) -> 32.426464 | N37: =M37-L37 -> 0 | O37: =N37/L37 -> 0 | P37: =SUM(P38:P40) -> 32.206433 | Q37: =SUM(Q38:Q40) -> 32.206433 | R37: =Q37-P37 -> 0 | S37: =R37/P37 -> 0 | T37: =SUM(T38:T40) -> 32.007851 | U37: =SUM(U38:U40) -> 32.007851 | V37: =U37-T37 -> 0 | W37: =V37/T37 -> 0
A38: Восточное | B38: 27.539394 | D38: =$D$29*$B$38/$B$29 -> 27.828628 | E38: =$E$7*D38 -> 27.828628 | F38: =E38-D38 -> 0 | G38: =F38/D38 -> 0 | H38: =$H$29*$B$38/$B$29 -> 27.304654 | I38: =$E$7*H38 -> 27.304654 | J38: =I38-H38 -> 0 | K38: =J38/H38 -> 0 | L38: =$L$29*$B$38/$B$29 -> 27.304654 | M38: =$E$7*L38 -> 27.304654 | N38: =M38-L38 -> 0 | O38: =N38/L38 -> 0 | P38: =$P$29*$B$38/$B$29 -> 26.954377 | Q38: =$E$7*P38 -> 26.954377 | R38: =Q38-P38 -> 0 | S38: =R38/P38 -> 0 | T38: =$T$29*$B$38/$B$29 -> 26.60874 | U38: =$E$7*T38 -> 26.60874 | V38: =U38-T38 -> 0 | W38: =V38/T38 -> 0
A39: Северо-Западное | B39: 2.34476 | D39: =$D$30*$B$39/$B$30 -> 2.250292 | E39: =$E$8*D39 -> 2.250292 | F39: =E39-D39 -> 0 | G39: =F39/D39 -> 0 | H39: =$H$30*$B$39/$B$30 -> 2.250292 | I39: =$E$8*H39 -> 2.250292 | J39: =I39-H39 -> 0 | K39: =J39/H39 -> 0 | L39: =$L$30*$B$39/$B$30 -> 2.2671166 | M39: =$E$8*L39 -> 2.2671166 | N39: =M39-L39 -> 0 | O39: =N39/L39 -> 0 | P39: =$P$30*$B$39/$B$30 -> 2.3733083 | Q39: =$E$8*P39 -> 2.3733083 | R39: =Q39-P39 -> 0 | S39: =R39/P39 -> 0 | T39: =$T$30*$B$39/$B$30 -> 2.4961038 | U39: =$E$8*T39 -> 2.4961038 | V39: =U39-T39 -> 0 | W39: =V39/T39 -> 0
A40: Южное | B40: 2.193801 | D40: =$D$31*$B$40/$B$31 -> 2.8174446 | E40: =$E$9*D40 -> 2.8174446 | F40: =E40-D40 -> 0 | G40: =F40/D40 -> 0 | H40: =$H$31*$B$40/$B$31 -> 2.8307625 | I40: =$E$9*H40 -> 2.8307625 | J40: =I40-H40 -> 0 | K40: =J40/H40 -> 0 | L40: =$L$31*$B$40/$B$31 -> 2.8546934 | M40: =$E$9*L40 -> 2.8546934 | N40: =M40-L40 -> 0 | O40: =N40/L40 -> 0 | P40: =$P$31*$B$40/$B$31 -> 2.8787469 | Q40: =$E$9*P40 -> 2.8787469 | R40: =Q40-P40 -> 0 | S40: =R40/P40 -> 0 | T40: =$T$31*$B$40/$B$31 -> 2.9030078 | U40: =$E$9*T40 -> 2.9030078 | V40: =U40-T40 -> 0 | W40: =V40/T40 -> 0
A41: антрацит (энергетический уголь) | B41: =B42+B43+B44 -> 14.523253 | D41: =SUM(D42:D44) -> 15.058663 | E41: =SUM(E42:E44) -> 15.058663 | F41: =E41-D41 -> 0 | G41: =F41/D41 -> 0 | H41: =SUM(H42:H44) -> 14.878132 | I41: =SUM(I42:I44) -> 14.878132 | J41: =I41-H41 -> 0 | K41: =J41/H41 -> 0 | L41: =SUM(L42:L44) -> 14.916963 | M41: =SUM(M42:M44) -> 14.916963 | N41: =M41-L41 -> 0 | O41: =N41/L41 -> 0 | P41: =SUM(P42:P44) -> 14.925288 | Q41: =SUM(Q42:Q44) -> 14.925288 | R41: =Q41-P41 -> 0 | S41: =R41/P41 -> 0 | T41: =SUM(T42:T44) -> 14.953638 | U41: =SUM(U42:U44) -> 14.953638 | V41: =U41-T41 -> 0 | W41: =V41/T41 -> 0
A42: Восточное | B42: 10.086421 | D42: =$D$29*$B$42/$B$29 -> 10.192354 | E42: =$E$5*D42 -> 10.192354 | F42: =E42-D42 -> 0 | G42: =F42/D42 -> 0 | H42: =$H$29*$B$42/$B$29 -> 10.000446 | I42: =$E$5*H42 -> 10.000446 | J42: =I42-H42 -> 0 | K42: =J42/H42 -> 0 | L42: =$L$29*$B$42/$B$29 -> 10.000446 | M42: =$E$5*L42 -> 10.000446 | N42: =M42-L42 -> 0 | O42: =N42/L42 -> 0 | P42: =$P$29*$B$42/$B$29 -> 9.8721561 | Q42: =$E$5*P42 -> 9.8721561 | R42: =Q42-P42 -> 0 | S42: =R42/P42 -> 0 | T42: =$T$29*$B$42/$B$29 -> 9.745565 | U42: =$E$5*T42 -> 9.745565 | V42: =U42-T42 -> 0 | W42: =V42/T42 -> 0
A43: Северо-Западное | B43: 2.562836 | D43: =$D$30*$B$43/$B$30 -> 2.4595819 | E43: =$E$5*D43 -> 2.4595819 | F43: =E43-D43 -> 0 | G43: =F43/D43 -> 0 | H43: =$H$30*$B$43/$B$30 -> 2.4595819 | I43: =$E$5*H43 -> 2.4595819 | J43: =I43-H43 -> 0 | K43: =J43/H43 -> 0 | L43: =$L$30*$B$43/$B$30 -> 2.4779713 | M43: =$E$5*L43 -> 2.4779713 | N43: =M43-L43 -> 0 | O43: =N43/L43 -> 0 | P43: =$P$30*$B$43/$B$30 -> 2.5940395 | Q43: =$E$5*P43 -> 2.5940395 | R43: =Q43-P43 -> 0 | S43: =R43/P43 -> 0 | T43: =$T$30*$B$43/$B$30 -> 2.7282556 | U43: =$E$5*T43 -> 2.7282556 | V43: =U43-T43 -> 0 | W43: =V43/T43 -> 0
A44: Южное | B44: 1.873996 | D44: =$D$31*$B$44/$B$31 -> 2.4067269 | E44: =$E$5*D44 -> 2.4067269 | F44: =E44-D44 -> 0 | G44: =F44/D44 -> 0 | H44: =$H$31*$B$44/$B$31 -> 2.4181033 | I44: =$E$5*H44 -> 2.4181033 | J44: =I44-H44 -> 0 | K44: =J44/H44 -> 0 | L44: =$L$31*$B$44/$B$31 -> 2.4385457 | M44: =$E$5*L44 -> 2.4385457 | N44: =M44-L44 -> 0 | O44: =N44/L44 -> 0 | P44: =$P$31*$B$44/$B$31 -> 2.4590928 | Q44: =$E$5*P44 -> 2.4590928 | R44: =Q44-P44 -> 0 | S44: =R44/P44 -> 0 | T44: =$T$31*$B$44/$B$31 -> 2.479817 | U44: =$E$5*T44 -> 2.479817 | V44: =U44-T44 -> 0 | W44: =V44/T44 -> 0

Sheet Уголь_эластика_экспорт
IS1: индексация жд тарифа | IU1: индексация заданная | IV1: =1+(IX1/1000) -> 1 | IW1: корректировка | IX1: 0
B2: параметры перевозок | X2: параметры расчета тарифа | AC2: экономика перевозок в текущих условиях | AT2: для усреднения | AU2: Коэффициент загрузки предприятия | AV2: трнаспортная с индексацией | AZ2: Изменение тарифа ОАО "РЖД" | IS2: =ROUND(IU2,2) -> 0.1 | IT2: =IF(IS2<0,"скидка","индексация") -> индексация | IU2: =IF(AND('Выпадение всего'!G11=TRUE,'Выпадение всего'!J11=FALSE),'Выпадение всего'!J14,IF(AND('Выпадение всего'!G11=FALSE,'Выпадение всего'!J11=TRUE),'Выпадение всего'!J17)) -> 0.1 | IV2: 1 | IW2: при корректировке коэфф НЕ может принимать значения >1, если у ИПЕМ он <=1, т.е. груз нечувствителен
A3: сцеп цены | B3: Код группы груза | C3: Группа груза | D3: Код груза | E3: Наим груза | F3: Вид груза | G3: Дор отпр | H3: Дор наз | I3: Станц отпр РФ | J3: Станц назн РФ | K3: Средняя дальность(км) | L3: Род вагона | M3: Вид перевозки | N3: Признак контейнерной отправки | O3: Направление | P3: ОКПО компании | Q3: Компания отправителя | R3: Холдинг отправителя | S3: Объем перевозок (тн) | T3: Грузооборот, ткм | U3: Кол-во вагонов | V3: Кол-во контейнеров | W3: Провозная плата, руб | X3: Загрузка вагона | Y3: Категория отправки | Z3: Груженый рейс, дней | AA3: Порожний рейс, дней | AB3: Погрузка-разгрузка, дней | AC3: Расходы по оплате услуг ОАО 'РЖД', руб. за тонну гружёный рейс | AD3: Расходы по оплате услуг ОАО 'РЖД', руб. за тонну порожний рейс | AE3: Расходы по оплате услуг ОАО 'РЖД', руб. за тонну общая стоимость (тарифные условия 2026 года) | AF3: Расходы по оплате услуг операторов, руб. за тонну | AG3: Расходы на перевалку, руб. за тонну | AH3: Акциз/пошлина | AI3: Себестоимость добычи/производства, руб. т. | AJ3: Стоимость 1 тонны на рынке, руб./т. | AK3: Стоимость 1 тонны на рынке, $/т. | AL3: Общие транспортные расходы, руб. за тонну | AM3: Нетбэк, руб. за тонну | AN3: Общие расходы, руб. за тонну | AO3: Маржинальность в текущих условиях | AP3: Транспортная составляющая в цене % | AQ3: Инфраструктурная составляющая в цене % | AR3: Инфраструктурная составляющая в транспортных затратах | AS3: Коэффициент сохранения базы В РАСЧЕТ | AT3: объем* коэфф | AV3: Маржинальность с индексацией | AW3: Транспортная составляющая в цене % | AX3: Инфраструктурная составляющая в цене % | AY3: Инфраструктурная составляющая в транспортных затратах | AZ3: =ROUND(BA3-0.5%,3) -> -0.5 | BA3: =ROUND(BB3-0.5%,3) -> -0.495 | BB3: =ROUND(BC3-0.5%,3) -> -0.49 | BC3: =ROUND(BD3-0.5%,3) -> -0.485 | BD3: =ROUND(BE3-0.5%,3) -> -0.48 | BE3: =ROUND(BF3-0.5%,3) -> -0.475 | BF3: =ROUND(BG3-0.5%,3) -> -0.47 | BG3: =ROUND(BH3-0.5%,3) -> -0.465 | ... CW3: =ROUND(CX3-0.5%,3) -> -0.255 | CX3: -0.25 | CY3: -0.245 | CZ3: -0.24 | DA3: -0.235 | DB3: -0.23 | DC3: -0.225 | DD3: -0.22 | DE3: -0.215 | DF3: -0.21 | DG3: -0.205 | DH3: -0.2 | DI3: -0.195 | DJ3: -0.19 | DK3: -0.185 | DL3: -0.18 | DM3: -0.175 | DN3: -0.17 | DO3: -0.165 | DP3: -0.16 | DQ3: -0.155 | DR3: -0.15 | DS3: -0.145 | DT3: -0.14 | DU3: -0.135 | DV3: -0.13 | DW3: -0.125 | DX3: -0.12 | DY3: -0.115 | DZ3: -0.11 | EA3: -0.105 | EB3: -0.1 | EC3: -0.095 | ED3: -0.09 | EE3: -0.085 | EF3: -0.08 | EG3: -0.075 | EH3: -0.07 | EI3: -0.065 | EJ3: -0.06 | EK3: -0.055 | EL3: -0.05 | EM3: -0.045 | EN3: -0.04 | EO3: -0.035 | EP3: -0.03 | EQ3: -0.025 | ER3: -0.02 | ES3: -0.015 | ET3: -0.01 | EU3: -0.005 | EV3: 0 | EW3: 0.005 | EX3: 0.01 | EY3: 0.015 | EZ3: 0.02 | FA3: 0.025 | FB3: 0.03 | FC3: 0.035 | FD3: 0.04 | FE3: 0.045 | FF3: 0.05 | FG3: 0.055 | FH3: 0.06 | FI3: 0.065 | FJ3: 0.07 | FK3: 0.075 | FL3: 0.08 | FM3: 0.085 | FN3: 0.09 | FO3: 0.095 | FP3: 0.1 | FQ3: 0.105 | FR3: 0.11 | FS3: 0.115 | FT3: 0.12 | FU3: 0.125 | FV3: 0.13 | FW3: 0.135 | FX3: 0.14 | FY3: 0.145 | FZ3: 0.15 | GA3: 0.155 | GB3: 0.16 | GC3: 0.165 | GD3: 0.17 | GE3: 0.175 | GF3: 0.18 | GG3: 0.185 | GH3: 0.19 | GI3: 0.195 | GJ3: 0.2 | GK3: 0.205 | GL3: 0.21 | GM3: 0.215 | GN3: 0.22 | GO3: 0.225 | GP3: 0.23 | GQ3: 0.235 | GR3: 0.24 | GS3: 0.245 | GT3: 0.25 | GU3: 0.255 | GV3: 0.26 | GW3: 0.265 | GX3: 0.27 | GY3: 0.275 | GZ3: 0.28 | HA3: 0.285 | HB3: 0.29 | HC3: 0.295 | HD3: 0.3 | HE3: 0.305 | HF3: 0.31 | HG3: 0.315 | HH3: 0.32 | HI3: 0.325 | HJ3: 0.33 | HK3: 0.335 | HL3: 0.34 | HM3: 0.345 | HN3: 0.35 | HO3: 0.355 | HP3: 0.36 | HQ3: 0.365 | HR3: 0.37 | HS3: 0.375 | HT3: 0.38 | HU3: 0.385 | HV3: 0.39 | HW3: 0.395 | HX3: 0.4 | HY3: 0.405 | HZ3: 0.41 | IA3: 0.415 | IB3: 0.42 | IC3: 0.425 | ID3: 0.43 | IE3: 0.435 | IF3: 0.44 | IG3: 0.445 | IH3: 0.45 | II3: 0.455 | IJ3: 0.46 | IK3: 0.465 | IL3: 0.47 | IM3: 0.475 | IN3: 0.48 | IO3: 0.485 | IP3: 0.49 | IQ3: 0.495 | IR3: 0.5 | IS3: Коэффициент сохранения базы ИПЕМ | IT3: Коэффициент сохранения базы с корректировкой | IW3: при корректировке коэфф МОЖЕТ принимать значения >1, если у ИПЕМ он <=1, т.е. груз нечувствителен
A4: уголь энергетический (кроме антрацита)ЭкспортВосточное | B4: 1 | C4: Уголь каменный | D4: 16111 | E4: УГОЛЬ Г | F4: уголь энергетический (кроме антрацита) | G4: ДВС | H4: ДВС | I4: ЧЕГДОМЫН | J4: ВАНИНО-ЭКСП | K4: 971 | L4: полувагон | M4: Экспорт | N4: неконтейнерная | O4: Восточное | P4: 54657469 | Q4: ООО "КАРБОНПРО" | R4: АО "СУЭК" | S4: 4534534 | T4: 4403034520 | U4: 60744 | W4: 3250215610 | X4: 75 | Y4: группа вагонов | Z4: 7 | AA4: 7 | AB4: 4 | AC4: 808.81 | AD4: 406.26 | AE4: =AC4+AD4 -> 1215.07 | AF4: ='Цены,перевалка,аренда'!$C$26*SUM(Уголь_эластика_экспорт!Z4+Уголь_эластика_экспорт!AA4+Уголь_эластика_экспорт!AB4)/Уголь_эластика_экспорт!X4 -> 240 | AG4: =SUMIF('Цены,перевалка,аренда'!$A$20:$A$22,Уголь_эластика_экспорт!$O4,'Цены,перевалка,аренда'!$D$20:$D$22) -> 763.055 | AI4: 5018 | AJ4: =SUMIF('Цены,перевалка,аренда'!$A$5:$A$17,Уголь_эластика_экспорт!A4,'Цены,перевалка,аренда'!$D$5:$D$17) -> 8546.216 | AK4: =AJ4/'Цены,перевалка,аренда'!$C$1 -> 112 | AL4: =AE4+AF4+AG4 -> 2218.125 | AM4: =AJ4-AL4 -> 6328.091 | AN4: =AI4+AH4+AG4+AF4+AE4 -> 7236.125 | AO4: =(AJ4-AN4)/AJ4 -> 0.15329486 | AP4: =AL4/AJ4 -> 0.25954469 | AQ4: =AE4/AJ4 -> 0.14217637 | AR4: =AE4/AL4 -> 0.54779149 | AS4: =IT4 -> 1 | AT4: =S4*AS4 -> 4534534 | AU4: 1 | AV4: =(AJ4-(AE4*(1+$IS$2)+AF4+AG4+AH4+AI4))/AJ4 -> 0.13907722 | AW4: =(AE4*(1+$IS$2)+AF4+AG4)/AJ4 -> 0.27376233 | AX4: =(AE4*(1+$IS$2))/AJ4 -> 0.15639401 | AY4: =(AE4*(1+$IS$2))/(AE4*(1+$IS$2)+AF4+AG4) -> 0.57127659 | AZ4: =MIN(IF($AU4=100%,1,1+VLOOKUP(($AJ4-$AI4-$AH4-$AG4-$AF4-$AE4*(1+AZ$3))/$AJ4,Уголь_коэфф!$A:$B,2,1)-VLOOKUP($AO4,Уголь_коэфф!$A:$B,2,1)),1+(1-$AU4)) -> 1 | BA4: =MIN(IF($AU4=100%,1,1+VLOOKUP(($AJ4-$AI4-$AH4-$AG4-$AF4-$AE4*(1+BA$3))/$AJ4,Уголь_коэфф!$A:$B,2,1)-VLOOKUP($AO4,Уголь_коэфф!$A:$B,2,1)),1+(1-$AU4)) -> 1 | BB4: =MIN(IF($AU4=100%,1,1+VLOOKUP(($AJ4-$AI4-$AH4-$AG4-$AF4-$AE4*(1+BB$3))/$AJ4,Уголь_коэфф!$A:$B,2,1)-VLOOKUP($AO4,Уголь_коэфф!$A:$B,2,1)),1+(1-$AU4)) -> 1 | BC4: =MIN(IF($AU4=100%,1,1+VLOOKUP(($AJ4-$AI4-$AH4-$AG4-$AF4-$AE4*(1+BC$3))/$AJ4,Уголь_коэфф!$A:$B,2,1)-VLOOKUP($AO4,Уголь_коэфф!$A:$B,2,1)),1+(1-$AU4)) -> 1 | BD4: =MIN(IF($AU4=100%,1,1+VLOOKUP(($AJ4-$AI4-$AH4-$AG4-$AF4-$AE4*(1+BD$3))/$AJ4,Уголь_коэфф!$A:$B,2,1)-VLOOKUP($AO4,Уголь_коэфф!$A:$B,2,1)),1+(1-$AU4)) -> 1 | BE4: =MIN(IF($AU4=100%,1,1+VLOOKUP(($AJ4-$AI4-$AH4-$AG4-$AF4-$AE4*(1+BE$3))/$AJ4,Уголь_коэфф!$A:$B,2,1)-VLOOKUP($AO4,Уголь_коэфф!$A:$B,2,1)),1+(1-$AU4)) -> 1 | BF4: =MIN(IF($AU4=100%,1,1+VLOOKUP(($AJ4-$AI4-$AH4-$AG4-$AF4-$AE4*(1+BF$3))/$AJ4,Уголь_коэфф!$A:$B,2,1)-VLOOKUP($AO4,Уголь_коэфф!$A:$B,2,1)),1+(1-$AU4)) -> 1 | BG4: =MIN(IF($AU4=100%,1,1+VLOOKUP(($AJ4-$AI4-$AH4-$AG4-$AF4-$AE4*(1+BG$3))/$AJ4,Уголь_коэфф!$A:$B,2,1)-VLOOKUP($AO4,Уголь_коэфф!$A:$B,2,1)),1+(1-$AU4)) -> 1 | ... EU4: =MIN(IF($AU4=100%,1,1+VLOOKUP(($AJ4-$AI4-$AH4-$AG4-$AF4-$AE4*(1+EU$3))/$AJ4,Уголь_коэфф!$A:$B,2,1)-VLOOKUP($AO4,Уголь_коэфф!$A:$B,2,1)),1+(1-$AU4)) -> 1 | EV4: 1 | EW4: =MIN(1,MAX(VLOOKUP(($AJ4-$AI4-$AH4-$AG4-$AF4-$AE4*(1+EW$3))/$AJ4,Уголь_коэфф!$A:$B,2,1),(EV4-0.05))) -> 1 | EX4: =MIN(1,MAX(VLOOKUP(($AJ4-$AI4-$AH4-$AG4-$AF4-$AE4*(1+EX$3))/$AJ4,Уголь_коэфф!$A:$B,2,1),(EW4-0.05))) -> 1 | EY4: =MIN(1,MAX(VLOOKUP(($AJ4-$AI4-$AH4-$AG4-$AF4-$AE4*(1+EY$3))/$AJ4,Уголь_коэфф!$A:$B,2,1),(EX4-0.05))) -> 1 | EZ4: =MIN(1,MAX(VLOOKUP(($AJ4-$AI4-$AH4-$AG4-$AF4-$AE4*(1+EZ$3))/$AJ4,Уголь_коэфф!$A:$B,2,1),(EY4-0.05))) -> 1 | FA4: =MIN(1,MAX(VLOOKUP(($AJ4-$AI4-$AH4-$AG4-$AF4-$AE4*(1+FA$3))/$AJ4,Уголь_коэфф!$A:$B,2,1),(EZ4-0.05))) -> 1 | FB4: =MIN(1,MAX(VLOOKUP(($AJ4-$AI4-$AH4-$AG4-$AF4-$AE4*(1+FB$3))/$AJ4,Уголь_коэфф!$A:$B,2,1),(FA4-0.05))) -> 1 | FC4: =MIN(1,MAX(VLOOKUP(($AJ4-$AI4-$AH4-$AG4-$AF4-$AE4*(1+FC$3))/$AJ4,Уголь_коэфф!$A:$B,2,1),(FB4-0.05))) -> 1 | FD4: =MIN(1,MAX(VLOOKUP(($AJ4-$AI4-$AH4-$AG4-$AF4-$AE4*(1+FD$3))/$AJ4,Уголь_коэфф!$A:$B,2,1),(FC4-0.05))) -> 1 | ... IR4: =MIN(1,MAX(VLOOKUP(($AJ4-$AI4-$AH4-$AG4-$AF4-$AE4*(1+IR$3))/$AJ4,Уголь_коэфф!$A:$B,2,1),(IQ4-0.05))) -> 1 | IS4: =HLOOKUP($IS$2,$AZ$3:$IR$27,ROW(IR4)-2,FALSE) -> 1 | IT4: =IF($IV$2=1,IF(AND($IT$2="индексация",IS4<1,IS4*$IV$1>1),1,IF(AND($IT$2="индексация",IS4=1),1,IF(AND($IT$2="скидка",IS4=1),1,IS4*$IV$1))),IS4*$IV$1) -> 1
A5: уголь энергетический (кроме антрацита)ЭкспортСеверо-Западное | B5: 1 | C5: Уголь каменный | D5: 16112 | E5: УГОЛЬ Д | F5: уголь энергетический (кроме антрацита) | G5: КРС | H5: ОКТ | I5: ЧЕРНОГ.КОПИ | J5: МУРМАНСК-ЭКС | K5: 5356 | L5: полувагон | M5: Экспорт | N5: неконтейнерная | O5: Северо-Западное | P5: 54657469 | Q5: ООО "КАРБОНПРО" | R5: АО "СУЭК" | S5: 2180783 | T5: 11680408007 | U5: 29661 | W5: 4360383957 | X5: 75 | Y5: маршрутная | Z5: 12 | AA5: 12 | AB5: 4 | AC5: 2152.64 | AD5: 1013.71 | AE5: =AC5+AD5 -> 3166.35 | AF5: ='Цены,перевалка,аренда'!$C$26*SUM(Уголь_эластика_экспорт!Z5+Уголь_эластика_экспорт!AA5+Уголь_эластика_экспорт!AB5)/Уголь_эластика_экспорт!X5 -> 373.33333 | AG5: =SUMIF('Цены,перевалка,аренда'!$A$20:$A$22,Уголь_эластика_экспорт!$O5,'Цены,перевалка,аренда'!$D$20:$D$22) -> 610.444 | AI5: 2020 | AJ5: =SUMIF('Цены,перевалка,аренда'!$A$5:$A$17,Уголь_эластика_экспорт!A5,'Цены,перевалка,аренда'!$D$5:$D$17) -> 6485.9675 | AK5: =AJ5/'Цены,перевалка,аренда'!$C$1 -> 85 | AL5: =AE5+AF5+AG5 -> 4150.1273 | AM5: =AJ5-AL5 -> 2335.8402 | AN5: =AI5+AH5+AG5+AF5+AE5 -> 6170.1273 | AO5: =(AJ5-AN5)/AJ5 -> 0.048695922 | AP5: =AL5/AJ5 -> 0.63986249 | AQ5: =AE5/AJ5 -> 0.48818468 | AR5: =AE5/AL5 -> 0.76295249 | AS5: =IT5 -> 1 | AT5: =S5*AS5 -> 2180783 | AU5: 1 | AV5: =(AJ5-(AE5*(1+$IS$2)+AF5+AG5+AH5+AI5))/AJ5 -> -0.00012254661 | AW5: =(AE5*(1+$IS$2)+AF5+AG5)/AJ5 -> 0.68868096 | AX5: =(AE5*(1+$IS$2))/AJ5 -> 0.53700315 | AY5: =(AE5*(1+$IS$2))/(AE5*(1+$IS$2)+AF5+AG5) -> 0.77975606 | AZ5: =MIN(IF($AU5=100%,1,1+VLOOKUP(($AJ5-$AI5-$AH5-$AG5-$AF5-$AE5*(1+AZ$3))/$AJ5,Уголь_коэфф!$A:$B,2,1)-VLOOKUP($AO5,Уголь_коэфф!$A:$B,2,1)),1+(1-$AU5)) -> 1 | BA5: =MIN(IF($AU5=100%,1,1+VLOOKUP(($AJ5-$AI5-$AH5-$AG5-$AF5-$AE5*(1+BA$3))/$AJ5,Уголь_коэфф!$A:$B,2,1)-VLOOKUP($AO5,Уголь_коэфф!$A:$B,2,1)),1+(1-$AU5)) -> 1 | BB5: =MIN(IF($AU5=100%,1,1+VLOOKUP(($AJ5-$AI5-$AH5-$AG5-$AF5-$AE5*(1+BB$3))/$AJ5,Уголь_коэфф!$A:$B,2,1)-VLOOKUP($AO5,Уголь_коэфф!$A:$B,2,1)),1+(1-$AU5)) -> 1 | BC5: =MIN(IF($AU5=100%,1,1+VLOOKUP(($AJ5-$AI5-$AH5-$AG5-$AF5-$AE5*(1+BC$3))/$AJ5,Уголь_коэфф!$A:$B,2,1)-VLOOKUP($AO5,Уголь_коэфф!$A:$B,2,1)),1+(1-$AU5)) -> 1 | BD5: =MIN(IF($AU5=100%,1,1+VLOOKUP(($AJ5-$AI5-$AH5-$AG5-$AF5-$AE5*(1+BD$3))/$AJ5,Уголь_коэфф!$A:$B,2,1)-VLOOKUP($AO5,Уголь_коэфф!$A:$B,2,1)),1+(1-$AU5)) -> 1 | BE5: =MIN(IF($AU5=100%,1,1+VLOOKUP(($AJ5-$AI5-$AH5-$AG5-$AF5-$AE5*(1+BE$3))/$AJ5,Уголь_коэфф!$A:$B,2,1)-VLOOKUP($AO5,Уголь_коэфф!$A:$B,2,1)),1+(1-$AU5)) -> 1 | BF5: =MIN(IF($AU5=100%,1,1+VLOOKUP(($AJ5-$AI5-$AH5-$AG5-$AF5-$AE5*(1+BF$3))/$AJ5,Уголь_коэфф!$A:$B,2,1)-VLOOKUP($AO5,Уголь_коэфф!$A:$B,2,1)),1+(1-$AU5)) -> 1 | BG5: =MIN(IF($AU5=100%,1,1+VLOOKUP(($AJ5-$AI5-$AH5-$AG5-$AF5-$AE5*(1+BG$3))/$AJ5,Уголь_коэфф!$A:$B,2,1)-VLOOKUP($AO5,Уголь_коэфф!$A:$B,2,1)),1+(1-$AU5)) -> 1 | ... EU5: =MIN(IF($AU5=100%,1,1+VLOOKUP(($AJ5-$AI5-$AH5-$AG5-$AF5-$AE5*(1+EU$3))/$AJ5,Уголь_коэфф!$A:$B,2,1)-VLOOKUP($AO5,Уголь_коэфф!$A:$B,2,1)),1+(1-$AU5)) -> 1 | EV5: 1 | EW5: =MIN(1,MAX(VLOOKUP(($AJ5-$AI5-$AH5-$AG5-$AF5-$AE5*(1+EW$3))/$AJ5,Уголь_коэфф!$A:$B,2,1),(EV5-0.05))) -> 1 | EX5: =MIN(1,MAX(VLOOKUP(($AJ5-$AI5-$AH5-$AG5-$AF5-$AE5*(1+EX$3))/$AJ5,Уголь_коэфф!$A:$B,2,1),(EW5-0.05))) -> 1 | EY5: =MIN(1,MAX(VLOOKUP(($AJ5-$AI5-$AH5-$AG5-$AF5-$AE5*(1+EY$3))/$AJ5,Уголь_коэфф!$A:$B,2,1),(EX5-0.05))) -> 1 | EZ5: =MIN(1,MAX(VLOOKUP(($AJ5-$AI5-$AH5-$AG5-$AF5-$AE5*(1+EZ$3))/$AJ5,Уголь_коэфф!$A:$B,2,1),(EY5-0.05))) -> 1 | FA5: =MIN(1,MAX(VLOOKUP(($AJ5-$AI5-$AH5-$AG5-$AF5-$AE5*(1+FA$3))/$AJ5,Уголь_коэфф!$A:$B,2,1),(EZ5-0.05))) -> 1 | FB5: =MIN(1,MAX(VLOOKUP(($AJ5-$AI5-$AH5-$AG5-$AF5-$AE5*(1+FB$3))/$AJ5,Уголь_коэфф!$A:$B,2,1),(FA5-0.05))) -> 1 | FC5: =MIN(1,MAX(VLOOKUP(($AJ5-$AI5-$AH5-$AG5-$AF5-$AE5*(1+FC$3))/$AJ5,Уголь_коэфф!$A:$B,2,1),(FB5-0.05))) -> 1 | FD5: =MIN(1,MAX(VLOOKUP(($AJ5-$AI5-$AH5-$AG5-$AF5-$AE5*(1+FD$3))/$AJ5,Уголь_коэфф!$A:$B,2,1),(FC5-0.05))) -> 1 | ... IR5: =MIN(1,MAX(VLOOKUP(($AJ5-$AI5-$AH5-$AG5-$AF5-$AE5*(1+IR$3))/$AJ5,Уголь_коэфф!$A:$B,2,1),(IQ5-0.05))) -> 0.908 | IS5: =HLOOKUP($IS$2,$AZ$3:$IR$27,ROW(IR5)-2,FALSE) -> 1 | IT5: =IF($IV$2=1,IF(AND($IT$2="индексация",IS5<1,IS5*$IV$1>1),1,IF(AND($IT$2="индексация",IS5=1),1,IF(AND($IT$2="скидка",IS5=1),1,IS5*$IV$1))),IS5*$IV$1) -> 1
A6: уголь энергетический (кроме антрацита)ЭкспортЮжное | B6: 1 | C6: Уголь каменный | D6: 16112 | E6: УГОЛЬ Д | F6: уголь энергетический (кроме антрацита) | G6: КРС | H6: СКВ | I6: ЧЕРНОГ.КОПИ | J6: АЗОВ-ЭКСПОРТ | K6: 4832 | L6: полувагон | M6: Экспорт | N6: неконтейнерная | O6: Южное | P6: 54657469 | Q6: ООО "КАРБОНПРО" | R6: АО "СУЭК" | S6: 399916 | T6: 1932276609 | U6: 5484 | W6: 750324310 | X6: 75 | Y6: маршрутная | Z6: 11 | AA6: 11 | AB6: 4 | AC6: 1990.61 | AD6: 928.22 | AE6: =AC6+AD6 -> 2918.83 | AF6: ='Цены,перевалка,аренда'!$C$26*SUM(Уголь_эластика_экспорт!Z6+Уголь_эластика_экспорт!AA6+Уголь_эластика_экспорт!AB6)/Уголь_эластика_экспорт!X6 -> 346.66667 | AG6: =SUMIF('Цены,перевалка,аренда'!$A$20:$A$22,Уголь_эластика_экспорт!$O6,'Цены,перевалка,аренда'!$D$20:$D$22) -> 991.9715 | AI6: 2020 | AJ6: =SUMIF('Цены,перевалка,аренда'!$A$5:$A$17,Уголь_эластика_экспорт!A6,'Цены,перевалка,аренда'!$D$5:$D$17) -> 7249.0225 | AK6: =AJ6/'Цены,перевалка,аренда'!$C$1 -> 95 | AL6: =AE6+AF6+AG6 -> 4257.4682 | AM6: =AJ6-AL6 -> 2991.5543 | AN6: =AI6+AH6+AG6+AF6+AE6 -> 6277.4682 | AO6: =(AJ6-AN6)/AJ6 -> 0.13402556 | AP6: =AL6/AJ6 -> 0.58731617 | AQ6: =AE6/AJ6 -> 0.40265153 | AR6: =AE6/AL6 -> 0.68557882 | AS6: =IT6 -> 1 | AT6: =S6*AS6 -> 399916 | AU6: 1 | AV6: =(AJ6-(AE6*(1+$IS$2)+AF6+AG6+AH6+AI6))/AJ6 -> 0.093760412 | AW6: =(AE6*(1+$IS$2)+AF6+AG6)/AJ6 -> 0.62758133 | AX6: =(AE6*(1+$IS$2))/AJ6 -> 0.44291668 | AY6: =(AE6*(1+$IS$2))/(AE6*(1+$IS$2)+AF6+AG6) -> 0.70575185 | AZ6: =MIN(IF($AU6=100%,1,1+VLOOKUP(($AJ6-$AI6-$AH6-$AG6-$AF6-$AE6*(1+AZ$3))/$AJ6,Уголь_коэфф!$A:$B,2,1)-VLOOKUP($AO6,Уголь_коэфф!$A:$B,2,1)),1+(1-$AU6)) -> 1 | BA6: =MIN(IF($AU6=100%,1,1+VLOOKUP(($AJ6-$AI6-$AH6-$AG6-$AF6-$AE6*(1+BA$3))/$AJ6,Уголь_коэфф!$A:$B,2,1)-VLOOKUP($AO6,Уголь_коэфф!$A:$B,2,1)),1+(1-$AU6)) -> 1 | BB6: =MIN(IF($AU6=100%,1,1+VLOOKUP(($AJ6-$AI6-$AH6-$AG6-$AF6-$AE6*(1+BB$3))/$AJ6,Уголь_коэфф!$A:$B,2,1)-VLOOKUP($AO6,Уголь_коэфф!$A:$B,2,1)),1+(1-$AU6)) -> 1 | BC6: =MIN(IF($AU6=100%,1,1+VLOOKUP(($AJ6-$AI6-$AH6-$AG6-$AF6-$AE6*(1+BC$3))/$AJ6,Уголь_коэфф!$A:$B,2,1)-VLOOKUP($AO6,Уголь_коэфф!$A:$B,2,1)),1+(1-$AU6)) -> 1 | BD6: =MIN(IF($AU6=100%,1,1+VLOOKUP(($AJ6-$AI6-$AH6-$AG6-$AF6-$AE6*(1+BD$3))/$AJ6,Уголь_коэфф!$A:$B,2,1)-VLOOKUP($AO6,Уголь_коэфф!$A:$B,2,1)),1+(1-$AU6)) -> 1 | BE6: =MIN(IF($AU6=100%,1,1+VLOOKUP(($AJ6-$AI6-$AH6-$AG6-$AF6-$AE6*(1+BE$3))/$AJ6,Уголь_коэфф!$A:$B,2,1)-VLOOKUP($AO6,Уголь_коэфф!$A:$B,2,1)),1+(1-$AU6)) -> 1 | BF6: =MIN(IF($AU6=100%,1,1+VLOOKUP(($AJ6-$AI6-$AH6-$AG6-$AF6-$AE6*(1+BF$3))/$AJ6,Уголь_коэфф!$A:$B,2,1)-VLOOKUP($AO6,Уголь_коэфф!$A:$B,2,1)),1+(1-$AU6)) -> 1 | BG6: =MIN(IF($AU6=100%,1,1+VLOOKUP(($AJ6-$AI6-$AH6-$AG6-$AF6-$AE6*(1+BG$3))/$AJ6,Уголь_коэфф!$A:$B,2,1)-VLOOKUP($AO6,Уголь_коэфф!$A:$B,2,1)),1+(1-$AU6)) -> 1 | ... EU6: =MIN(IF($AU6=100%,1,1+VLOOKUP(($AJ6-$AI6-$AH6-$AG6-$AF6-$AE6*(1+EU$3))/$AJ6,Уголь_коэфф!$A:$B,2,1)-VLOOKUP($AO6,Уголь_коэфф!$A:$B,2,1)),1+(1-$AU6)) -> 1 | EV6: 1 | EW6: =MIN(1,MAX(VLOOKUP(($AJ6-$AI6-$AH6-$AG6-$AF6-$AE6*(1+EW$3))/$AJ6,Уголь_коэфф!$A:$B,2,1),(EV6-0.05))) -> 1 | EX6: =MIN(1,MAX(VLOOKUP(($AJ6-$AI6-$AH6-$AG6-$AF6-$AE6*(1+EX$3))/$AJ6,Уголь_коэфф!$A:$B,2,1),(EW6-0.05))) -> 1 | EY6: =MIN(1,MAX(VLOOKUP(($AJ6-$AI6-$AH6-$AG6-$AF6-$AE6*(1+EY$3))/$AJ6,Уголь_коэфф!$A:$B,2,1),(EX6-0.05))) -> 1 | EZ6: =MIN(1,MAX(VLOOKUP(($AJ6-$AI6-$AH6-$AG6-$AF6-$AE6*(1+EZ$3))/$AJ6,Уголь_коэфф!$A:$B,2,1),(EY6-0.05))) -> 1 | FA6: =MIN(1,MAX(VLOOKUP(($AJ6-$AI6-$AH6-$AG6-$AF6-$AE6*(1+FA$3))/$AJ6,Уголь_коэфф!$A:$B,2,1),(EZ6-0.05))) -> 1 | FB6: =MIN(1,MAX(VLOOKUP(($AJ6-$AI6-$AH6-$AG6-$AF6-$AE6*(1+FB$3))/$AJ6,Уголь_коэфф!$A:$B,2,1),(FA6-0.05))) -> 1 | FC6: =MIN(1,MAX(VLOOKUP(($AJ6-$AI6-$AH6-$AG6-$AF6-$AE6*(1+FC$3))/$AJ6,Уголь_коэфф!$A:$B,2,1),(FB6-0.05))) -> 1 | FD6: =MIN(1,MAX(VLOOKUP(($AJ6-$AI6-$AH6-$AG6-$AF6-$AE6*(1+FD$3))/$AJ6,Уголь_коэфф!$A:$B,2,1),(FC6-0.05))) -> 1 | ... IR6: =MIN(1,MAX(VLOOKUP(($AJ6-$AI6-$AH6-$AG6-$AF6-$AE6*(1+IR$3))/$AJ6,Уголь_коэфф!$A:$B,2,1),(IQ6-0.05))) -> 0.975 | IS6: =HLOOKUP($IS$2,$AZ$3:$IR$27,ROW(IR6)-2,FALSE) -> 1 | IT6: =IF($IV$2=1,IF(AND($IT$2="индексация",IS6<1,IS6*$IV$1>1),1,IF(AND($IT$2="индексация",IS6=1),1,IF(AND($IT$2="скидка",IS6=1),1,IS6*$IV$1))),IS6*$IV$1) -> 1
A7: уголь энергетический (кроме антрацита)ЭкспортВосточное | B7: 1 | C7: Уголь каменный | D7: 16112 | E7: УГОЛЬ Д | F7: уголь энергетический (кроме антрацита) | G7: КРС | H7: ИФР | I7: КАМЫШТА | J7: МИХ-СЕМ-Э | K7: 4678 | L7: полувагон | M7: Экспорт | N7: неконтейнерная | O7: Восточное | P7: 1869326 | Q7: ООО "УГОЛЬ ПЛЮС" | R7: АО "Русский уголь" | S7: 200545 | T7: 938250119 | U7: 2877 | W7: 485116824 | X7: 69 | Y7: маршрутная | Z7: 14 | AA7: 14 | AB7: 4 | AC7: 2198.94 | AD7: 1008.93 | AE7: =AC7+AD7 -> 3207.87 | AF7: ='Цены,перевалка,аренда'!$C$27*SUM(Уголь_эластика_экспорт!Z7+Уголь_эластика_экспорт!AA7+Уголь_эластика_экспорт!AB7)/Уголь_эластика_экспорт!X7 -> 324.63768 | AI7: 586 | AJ7: =SUMIF('Цены,перевалка,аренда'!$A$5:$A$17,Уголь_эластика_экспорт!A7,'Цены,перевалка,аренда'!$D$5:$D$17) -> 8546.216 | AK7: =AJ7/'Цены,перевалка,аренда'!$C$1 -> 112 | AL7: =AE7+AF7+AG7 -> 3532.5077 | AM7: =AJ7-AL7 -> 5013.7083 | AN7: =AI7+AH7+AG7+AF7+AE7 -> 4118.5077 | AO7: =(AJ7-AN7)/AJ7 -> 0.51808991 | AP7: =AL7/AJ7 -> 0.41334173 | AQ7: =AE7/AJ7 -> 0.3753556 | AR7: =AE7/AL7 -> 0.90809994 | AS7: =IT7 -> 1 | AT7: =S7*AS7 -> 200545 | AU7: 1 | AV7: =(AJ7-(AE7*(1+$IS$2)+AF7+AG7+AH7+AI7))/AJ7 -> 0.48055436 | AW7: =(AE7*(1+$IS$2)+AF7+AG7)/AJ7 -> 0.45087729 | AX7: =(AE7*(1+$IS$2))/AJ7 -> 0.41289116 | AY7: =(AE7*(1+$IS$2))/(AE7*(1+$IS$2)+AF7+AG7) -> 0.91575062 | AZ7: =MIN(IF($AU7=100%,1,1+VLOOKUP(($AJ7-$AI7-$AH7-$AG7-$AF7-$AE7*(1+AZ$3))/$AJ7,Уголь_коэфф!$A:$B,2,1)-VLOOKUP($AO7,Уголь_коэфф!$A:$B,2,1)),1+(1-$AU7)) -> 1 | BA7: =MIN(IF($AU7=100%,1,1+VLOOKUP(($AJ7-$AI7-$AH7-$AG7-$AF7-$AE7*(1+BA$3))/$AJ7,Уголь_коэфф!$A:$B,2,1)-VLOOKUP($AO7,Уголь_коэфф!$A:$B,2,1)),1+(1-$AU7)) -> 1 | BB7: =MIN(IF($AU7=100%,1,1+VLOOKUP(($AJ7-$AI7-$AH7-$AG7-$AF7-$AE7*(1+BB$3))/$AJ7,Уголь_коэфф!$A:$B,2,1)-VLOOKUP($AO7,Уголь_коэфф!$A:$B,2,1)),1+(1-$AU7)) -> 1 | BC7: =MIN(IF($AU7=100%,1,1+VLOOKUP(($AJ7-$AI7-$AH7-$AG7-$AF7-$AE7*(1+BC$3))/$AJ7,Уголь_коэфф!$A:$B,2,1)-VLOOKUP($AO7,Уголь_коэфф!$A:$B,2,1)),1+(1-$AU7)) -> 1 | BD7: =MIN(IF($AU7=100%,1,1+VLOOKUP(($AJ7-$AI7-$AH7-$AG7-$AF7-$AE7*(1+BD$3))/$AJ7,Уголь_коэфф!$A:$B,2,1)-VLOOKUP($AO7,Уголь_коэфф!$A:$B,2,1)),1+(1-$AU7)) -> 1 | BE7: =MIN(IF($AU7=100%,1,1+VLOOKUP(($AJ7-$AI7-$AH7-$AG7-$AF7-$AE7*(1+BE$3))/$AJ7,Уголь_коэфф!$A:$B,2,1)-VLOOKUP($AO7,Уголь_коэфф!$A:$B,2,1)),1+(1-$AU7)) -> 1 | BF7: =MIN(IF($AU7=100%,1,1+VLOOKUP(($AJ7-$AI7-$AH7-$AG7-$AF7-$AE7*(1+BF$3))/$AJ7,Уголь_коэфф!$A:$B,2,1)-VLOOKUP($AO7,Уголь_коэфф!$A:$B,2,1)),1+(1-$AU7)) -> 1 | BG7: =MIN(IF($AU7=100%,1,1+VLOOKUP(($AJ7-$AI7-$AH7-$AG7-$AF7-$AE7*(1+BG$3))/$AJ7,Уголь_коэфф!$A:$B,2,1)-VLOOKUP($AO7,Уголь_коэфф!$A:$B,2,1)),1+(1-$AU7)) -> 1 | ... EU7: =MIN(IF($AU7=100%,1,1+VLOOKUP(($AJ7-$AI7-$AH7-$AG7-$AF7-$AE7*(1+EU$3))/$AJ7,Уголь_коэфф!$A:$B,2,1)-VLOOKUP($AO7,Уголь_коэфф!$A:$B,2,1)),1+(1-$AU7)) -> 1 | EV7: 1 | EW7: =MIN(1,MAX(VLOOKUP(($AJ7-$AI7-$AH7-$AG7-$AF7-$AE7*(1+EW$3))/$AJ7,Уголь_коэфф!$A:$B,2,1),(EV7-0.05))) -> 1 | EX7: =MIN(1,MAX(VLOOKUP(($AJ7-$AI7-$AH7-$AG7-$AF7-$AE7*(1+EX$3))/$AJ7,Уголь_коэфф!$A:$B,2,1),(EW7-0.05))) -> 1 | EY7: =MIN(1,MAX(VLOOKUP(($AJ7-$AI7-$AH7-$AG7-$AF7-$AE7*(1+EY$3))/$AJ7,Уголь_коэфф!$A:$B,2,1),(EX7-0.05))) -> 1 | EZ7: =MIN(1,MAX(VLOOKUP(($AJ7-$AI7-$AH7-$AG7-$AF7-$AE7*(1+EZ$3))/$AJ7,Уголь_коэфф!$A:$B,2,1),(EY7-0.05))) -> 1 | FA7: =MIN(1,MAX(VLOOKUP(($AJ7-$AI7-$AH7-$AG7-$AF7-$AE7*(1+FA$3))/$AJ7,Уголь_коэфф!$A:$B,2,1),(EZ7-0.05))) -> 1 | FB7: =MIN(1,MAX(VLOOKUP(($AJ7-$AI7-$AH7-$AG7-$AF7-$AE7*(1+FB$3))/$AJ7,Уголь_коэфф!$A:$B,2,1),(FA7-0.05))) -> 1 | FC7: =MIN(1,MAX(VLOOKUP(($AJ7-$AI7-$AH7-$AG7-$AF7-$AE7*(1+FC$3))/$AJ7,Уголь_коэфф!$A:$B,2,1),(FB7-0.05))) -> 1 | FD7: =MIN(1,MAX(VLOOKUP(($AJ7-$AI7-$AH7-$AG7-$AF7-$AE7*(1+FD$3))/$AJ7,Уголь_коэфф!$A:$B,2,1),(FC7-0.05))) -> 1 | ... IR7: =MIN(1,MAX(VLOOKUP(($AJ7-$AI7-$AH7-$AG7-$AF7-$AE7*(1+IR$3))/$AJ7,Уголь_коэфф!$A:$B,2,1),(IQ7-0.05))) -> 1 | IS7: =HLOOKUP($IS$2,$AZ$3:$IR$27,ROW(IR7)-2,FALSE) -> 1 | IT7: =IF($IV$2=1,IF(AND($IT$2="индексация",IS7<1,IS7*$IV$1>1),1,IF(AND($IT$2="индексация",IS7=1),1,IF(AND($IT$2="скидка",IS7=1),1,IS7*$IV$1))),IS7*$IV$1) -> 1
A8: уголь энергетический (кроме антрацита)ЭкспортСеверо-Западное | B8: 1 | C8: Уголь каменный | D8: 16111 | E8: УГОЛЬ Г | F8: уголь энергетический (кроме антрацита) | G8: КРС | H8: ОКТ | I8: КРАВЧЕНКО | J8: ЛУЖСКАЯ-ЭКСП | K8: 4972 | L8: полувагон | M8: Экспорт | N8: неконтейнерная | O8: Северо-Западное | P8: 78465421 | Q8: АО "РУССКИЙ УГОЛЬ" | R8: АО "Русский уголь" | S8: 55119 | T8: 274033646 | U8: 786 | W8: 109968398 | X8: 69 | Y8: маршрутная | Z8: 12 | AA8: 12 | AB8: 4 | AC8: 2243.1 | AD8: 1024.44 | AE8: =AC8+AD8 -> 3267.54 | AF8: ='Цены,перевалка,аренда'!$C$27*SUM(Уголь_эластика_экспорт!Z8+Уголь_эластика_экспорт!AA8+Уголь_эластика_экспорт!AB8)/Уголь_эластика_экспорт!X8 -> 284.05797 | AG8: =SUMIF('Цены,перевалка,аренда'!$A$20:$A$22,Уголь_эластика_экспорт!$O8,'Цены,перевалка,аренда'!$D$20:$D$22) -> 610.444 | AI8: 586 | AJ8: =SUMIF('Цены,перевалка,аренда'!$A$5:$A$17,Уголь_эластика_экспорт!A8,'Цены,перевалка,аренда'!$D$5:$D$17) -> 6485.9675 | AK8: =AJ8/'Цены,перевалка,аренда'!$C$1 -> 85 | AL8: =AE8+AF8+AG8 -> 4162.042 | AM8: =AJ8-AL8 -> 2323.9255 | AN8: =AI8+AH8+AG8+AF8+AE8 -> 4748.042 | AO8: =(AJ8-AN8)/AJ8 -> 0.26795162 | AP8: =AL8/AJ8 -> 0.64169948 | AQ8: =AE8/AJ8 -> 0.50378606 | AR8: =AE8/AL8 -> 0.78508098 | AS8: =IT8 -> 1 | AT8: =S8*AS8 -> 55119 | AU8: 1 | AV8: =(AJ8-(AE8*(1+$IS$2)+AF8+AG8+AH8+AI8))/AJ8 -> 0.21757302 | AW8: =(AE8*(1+$IS$2)+AF8+AG8)/AJ8 -> 0.69207809 | AX8: =(AE8*(1+$IS$2))/AJ8 -> 0.55416466 | AY8: =(AE8*(1+$IS$2))/(AE8*(1+$IS$2)+AF8+AG8) -> 0.80072563 | AZ8: =MIN(IF($AU8=100%,1,1+VLOOKUP(($AJ8-$AI8-$AH8-$AG8-$AF8-$AE8*(1+AZ$3))/$AJ8,Уголь_коэфф!$A:$B,2,1)-VLOOKUP($AO8,Уголь_коэфф!$A:$B,2,1)),1+(1-$AU8)) -> 1 | BA8: =MIN(IF($AU8=100%,1,1+VLOOKUP(($AJ8-$AI8-$AH8-$AG8-$AF8-$AE8*(1+BA$3))/$AJ8,Уголь_коэфф!$A:$B,2,1)-VLOOKUP($AO8,Уголь_коэфф!$A:$B,2,1)),1+(1-$AU8)) -> 1 | BB8: =MIN(IF($AU8=100%,1,1+VLOOKUP(($AJ8-$AI8-$AH8-$AG8-$AF8-$AE8*(1+BB$3))/$AJ8,Уголь_коэфф!$A:$B,2,1)-VLOOKUP($AO8,Уголь_коэфф!$A:$B,2,1)),1+(1-$AU8)) -> 1 | BC8: =MIN(IF($AU8=100%,1,1+VLOOKUP(($AJ8-$AI8-$AH8-$AG8-$AF8-$AE8*(1+BC$3))/$AJ8,Уголь_коэфф!$A:$B,2,1)-VLOOKUP($AO8,Уголь_коэфф!$A:$B,2,1)),1+(1-$AU8)) -> 1 | BD8: =MIN(IF($AU8=100%,1,1+VLOOKUP(($AJ8-$AI8-$AH8-$AG8-$AF8-$AE8*(1+BD$3))/$AJ8,Уголь_коэфф!$A:$B,2,1)-VLOOKUP($AO8,Уголь_коэфф!$A:$B,2,1)),1+(1-$AU8)) -> 1 | BE8: =MIN(IF($AU8=100%,1,1+VLOOKUP(($AJ8-$AI8-$AH8-$AG8-$AF8-$AE8*(1+BE$3))/$AJ8,Уголь_коэфф!$A:$B,2,1)-VLOOKUP($AO8,Уголь_коэфф!$A:$B,2,1)),1+(1-$AU8)) -> 1 | BF8: =MIN(IF($AU8=100%,1,1+VLOOKUP(($AJ8-$AI8-$AH8-$AG8-$AF8-$AE8*(1+BF$3))/$AJ8,Уголь_коэфф!$A:$B,2,1)-VLOOKUP($AO8,Уголь_коэфф!$A:$B,2,1)),1+(1-$AU8)) -> 1 | BG8: =MIN(IF($AU8=100%,1,1+VLOOKUP(($AJ8-$AI8-$AH8-$AG8-$AF8-$AE8*(1+BG$3))/$AJ8,Уголь_коэфф!$A:$B,2,1)-VLOOKUP($AO8,Уголь_коэфф!$A:$B,2,1)),1+(1-$AU8)) -> 1 | ... EU8: =MIN(IF($AU8=100%,1,1+VLOOKUP(($AJ8-$AI8-$AH8-$AG8-$AF8-$AE8*(1+EU$3))/$AJ8,Уголь_коэфф!$A:$B,2,1)-VLOOKUP($AO8,Уголь_коэфф!$A:$B,2,1)),1+(1-$AU8)) -> 1 | EV8: 1 | EW8: =MIN(1,MAX(VLOOKUP(($AJ8-$AI8-$AH8-$AG8-$AF8-$AE8*(1+EW$3))/$AJ8,Уголь_коэфф!$A:$B,2,1),(EV8-0.05))) -> 1 | EX8: =MIN(1,MAX(VLOOKUP(($AJ8-$AI8-$AH8-$AG8-$AF8-$AE8*(1+EX$3))/$AJ8,Уголь_коэфф!$A:$B,2,1),(EW8-0.05))) -> 1 | EY8: =MIN(1,MAX(VLOOKUP(($AJ8-$AI8-$AH8-$AG8-$AF8-$AE8*(1+EY$3))/$AJ8,Уголь_коэфф!$A:$B,2,1),(EX8-0.05))) -> 1 | EZ8: =MIN(1,MAX(VLOOKUP(($AJ8-$AI8-$AH8-$AG8-$AF8-$AE8*(1+EZ$3))/$AJ8,Уголь_коэфф!$A:$B,2,1),(EY8-0.05))) -> 1 | FA8: =MIN(1,MAX(VLOOKUP(($AJ8-$AI8-$AH8-$AG8-$AF8-$AE8*(1+FA$3))/$AJ8,Уголь_коэфф!$A:$B,2,1),(EZ8-0.05))) -> 1 | FB8: =MIN(1,MAX(VLOOKUP(($AJ8-$AI8-$AH8-$AG8-$AF8-$AE8*(1+FB$3))/$AJ8,Уголь_коэфф!$A:$B,2,1),(FA8-0.05))) -> 1 | FC8: =MIN(1,MAX(VLOOKUP(($AJ8-$AI8-$AH8-$AG8-$AF8-$AE8*(1+FC$3))/$AJ8,Уголь_коэфф!$A:$B,2,1),(FB8-0.05))) -> 1 | FD8: =MIN(1,MAX(VLOOKUP(($AJ8-$AI8-$AH8-$AG8-$AF8-$AE8*(1+FD$3))/$AJ8,Уголь_коэфф!$A:$B,2,1),(FC8-0.05))) -> 1 | ... IR8: =MIN(1,MAX(VLOOKUP(($AJ8-$AI8-$AH8-$AG8-$AF8-$AE8*(1+IR$3))/$AJ8,Уголь_коэфф!$A:$B,2,1),(IQ8-0.05))) -> 1 | IS8: =HLOOKUP($IS$2,$AZ$3:$IR$27,ROW(IR8)-2,FALSE) -> 1 | IT8: =IF($IV$2=1,IF(AND($IT$2="индексация",IS8<1,IS8*$IV$1>1),1,IF(AND($IT$2="индексация",IS8=1),1,IF(AND($IT$2="скидка",IS8=1),1,IS8*$IV$1))),IS8*$IV$1) -> 1
A9: уголь энергетический (кроме антрацита)ЭкспортЮжное | B9: 1 | C9: Уголь каменный | D9: 16111 | E9: УГОЛЬ Г | F9: уголь энергетический (кроме антрацита) | G9: КРС | H9: СКВ | I9: КРАВЧЕНКО | J9: ВЫШСТБЛ-ЭКС | K9: 5362 | L9: полувагон | M9: Экспорт | N9: неконтейнерная | O9: Южное | P9: 78465421 | Q9: АО "РУССКИЙ УГОЛЬ" | R9: АО "Русский уголь" | S9: 744502 | T9: 3991785157 | U9: 10404 | W9: 1516719886 | X9: 69 | Y9: маршрутная | Z9: 12 | AA9: 12 | AB9: 4 | AC9: 2334.86 | AD9: 1086.34 | AE9: =AC9+AD9 -> 3421.2 | AF9: ='Цены,перевалка,аренда'!$C$27*SUM(Уголь_эластика_экспорт!Z9+Уголь_эластика_экспорт!AA9+Уголь_эластика_экспорт!AB9)/Уголь_эластика_экспорт!X9 -> 284.05797 | AG9: =SUMIF('Цены,перевалка,аренда'!$A$20:$A$22,Уголь_эластика_экспорт!$O9,'Цены,перевалка,аренда'!$D$20:$D$22) -> 991.9715 | AI9: 586 | AJ9: =SUMIF('Цены,перевалка,аренда'!$A$5:$A$17,Уголь_эластика_экспорт!A9,'Цены,перевалка,аренда'!$D$5:$D$17) -> 7249.0225 | AK9: =AJ9/'Цены,перевалка,аренда'!$C$1 -> 95 | AL9: =AE9+AF9+AG9 -> 4697.2295 | AM9: =AJ9-AL9 -> 2551.793 | AN9: =AI9+AH9+AG9+AF9+AE9 -> 5283.2295 | AO9: =(AJ9-AN9)/AJ9 -> 0.27118043 | AP9: =AL9/AJ9 -> 0.64798109 | AQ9: =AE9/AJ9 -> 0.47195329 | AR9: =AE9/AL9 -> 0.72834423 | AS9: =IT9 -> 1 | AT9: =S9*AS9 -> 744502 | AU9: 1 | AV9: =(AJ9-(AE9*(1+$IS$2)+AF9+AG9+AH9+AI9))/AJ9 -> 0.2239851 | AW9: =(AE9*(1+$IS$2)+AF9+AG9)/AJ9 -> 0.69517641 | AX9: =(AE9*(1+$IS$2))/AJ9 -> 0.51914862 | AY9: =(AE9*(1+$IS$2))/(AE9*(1+$IS$2)+AF9+AG9) -> 0.74678687 | AZ9: =MIN(IF($AU9=100%,1,1+VLOOKUP(($AJ9-$AI9-$AH9-$AG9-$AF9-$AE9*(1+AZ$3))/$AJ9,Уголь_коэфф!$A:$B,2,1)-VLOOKUP($AO9,Уголь_коэфф!$A:$B,2,1)),1+(1-$AU9)) -> 1 | BA9: =MIN(IF($AU9=100%,1,1+VLOOKUP(($AJ9-$AI9-$AH9-$AG9-$AF9-$AE9*(1+BA$3))/$AJ9,Уголь_коэфф!$A:$B,2,1)-VLOOKUP($AO9,Уголь_коэфф!$A:$B,2,1)),1+(1-$AU9)) -> 1 | BB9: =MIN(IF($AU9=100%,1,1+VLOOKUP(($AJ9-$AI9-$AH9-$AG9-$AF9-$AE9*(1+BB$3))/$AJ9,Уголь_коэфф!$A:$B,2,1)-VLOOKUP($AO9,Уголь_коэфф!$A:$B,2,1)),1+(1-$AU9)) -> 1 | BC9: =MIN(IF($AU9=100%,1,1+VLOOKUP(($AJ9-$AI9-$AH9-$AG9-$AF9-$AE9*(1+BC$3))/$AJ9,Уголь_коэфф!$A:$B,2,1)-VLOOKUP($AO9,Уголь_коэфф!$A:$B,2,1)),1+(1-$AU9)) -> 1 | BD9: =MIN(IF($AU9=100%,1,1+VLOOKUP(($AJ9-$AI9-$AH9-$AG9-$AF9-$AE9*(1+BD$3))/$AJ9,Уголь_коэфф!$A:$B,2,1)-VLOOKUP($AO9,Уголь_коэфф!$A:$B,2,1)),1+(1-$AU9)) -> 1 | BE9: =MIN(IF($AU9=100%,1,1+VLOOKUP(($AJ9-$AI9-$AH9-$AG9-$AF9-$AE9*(1+BE$3))/$AJ9,Уголь_коэфф!$A:$B,2,1)-VLOOKUP($AO9,Уголь_коэфф!$A:$B,2,1)),1+(1-$AU9)) -> 1 | BF9: =MIN(IF($AU9=100%,1,1+VLOOKUP(($AJ9-$AI9-$AH9-$AG9-$AF9-$AE9*(1+BF$3))/$AJ9,Уголь_коэфф!$A:$B,2,1)-VLOOKUP($AO9,Уголь_коэфф!$A:$B,2,1)),1+(1-$AU9)) -> 1 | BG9: =MIN(IF($AU9=100%,1,1+VLOOKUP(($AJ9-$AI9-$AH9-$AG9-$AF9-$AE9*(1+BG$3))/$AJ9,Уголь_коэфф!$A:$B,2,1)-VLOOKUP($AO9,Уголь_коэфф!$A:$B,2,1)),1+(1-$AU9)) -> 1 | ... EU9: =MIN(IF($AU9=100%,1,1+VLOOKUP(($AJ9-$AI9-$AH9-$AG9-$AF9-$AE9*(1+EU$3))/$AJ9,Уголь_коэфф!$A:$B,2,1)-VLOOKUP($AO9,Уголь_коэфф!$A:$B,2,1)),1+(1-$AU9)) -> 1 | EV9: 1 | EW9: =MIN(1,MAX(VLOOKUP(($AJ9-$AI9-$AH9-$AG9-$AF9-$AE9*(1+EW$3))/$AJ9,Уголь_коэфф!$A:$B,2,1),(EV9-0.05))) -> 1 | EX9: =MIN(1,MAX(VLOOKUP(($AJ9-$AI9-$AH9-$AG9-$AF9-$AE9*(1+EX$3))/$AJ9,Уголь_коэфф!$A:$B,2,1),(EW9-0.05))) -> 1 | EY9: =MIN(1,MAX(VLOOKUP(($AJ9-$AI9-$AH9-$AG9-$AF9-$AE9*(1+EY$3))/$AJ9,Уголь_коэфф!$A:$B,2,1),(EX9-0.05))) -> 1 | EZ9: =MIN(1,MAX(VLOOKUP(($AJ9-$AI9-$AH9-$AG9-$AF9-$AE9*(1+EZ$3))/$AJ9,Уголь_коэфф!$A:$B,2,1),(EY9-0.05))) -> 1 | FA9: =MIN(1,MAX(VLOOKUP(($AJ9-$AI9-$AH9-$AG9-$AF9-$AE9*(1+FA$3))/$AJ9,Уголь_коэфф!$A:$B,2,1),(EZ9-0.05))) -> 1 | FB9: =MIN(1,MAX(VLOOKUP(($AJ9-$AI9-$AH9-$AG9-$AF9-$AE9*(1+FB$3))/$AJ9,Уголь_коэфф!$A:$B,2,1),(FA9-0.05))) -> 1 | FC9: =MIN(1,MAX(VLOOKUP(($AJ9-$AI9-$AH9-$AG9-$AF9-$AE9*(1+FC$3))/$AJ9,Уголь_коэфф!$A:$B,2,1),(FB9-0.05))) -> 1 | FD9: =MIN(1,MAX(VLOOKUP(($AJ9-$AI9-$AH9-$AG9-$AF9-$AE9*(1+FD$3))/$AJ9,Уголь_коэфф!$A:$B,2,1),(FC9-0.05))) -> 1 | ... IR9: =MIN(1,MAX(VLOOKUP(($AJ9-$AI9-$AH9-$AG9-$AF9-$AE9*(1+IR$3))/$AJ9,Уголь_коэфф!$A:$B,2,1),(IQ9-0.05))) -> 1 | IS9: =HLOOKUP($IS$2,$AZ$3:$IR$27,ROW(IR9)-2,FALSE) -> 1 | IT9: =IF($IV$2=1,IF(AND($IT$2="индексация",IS9<1,IS9*$IV$1>1),1,IF(AND($IT$2="индексация",IS9=1),1,IF(AND($IT$2="скидка",IS9=1),1,IS9*$IV$1))),IS9*$IV$1) -> 1
A10: уголь энергетический (кроме антрацита)ЭкспортВосточное | B10: 1 | C10: Уголь каменный | D10: 16118 | E10: УГОЛЬ Т | F10: уголь энергетический (кроме антрацита) | G10: ЗСБ | H10: ДВС | I10: САРБАЛА | J10: НАХОДКА-В-ЭК | K10: 5976 | L10: полувагон | M10: Экспорт | N10: неконтейнерная | O10: Восточное | P10: 82365518 | Q10: АО "АТРИУМ" | R10: ООО "УГМК-Холдинг" | S10: 1782028 | T10: 10648684516 | U10: 23883 | W10: 3937998980 | X10: 75 | Y10: маршрутная | Z10: 13 | AA10: 14 | AB10: 4 | AC10: 2442.47 | AD10: 1120.57 | AE10: =AC10+AD10 -> 3563.04 | AF10: ='Цены,перевалка,аренда'!$C$26*SUM(Уголь_эластика_экспорт!Z10+Уголь_эластика_экспорт!AA10+Уголь_эластика_экспорт!AB10)/Уголь_эластика_экспорт!X10 -> 413.33333 | AG10: =SUMIF('Цены,перевалка,аренда'!$A$20:$A$22,Уголь_эластика_экспорт!$O10,'Цены,перевалка,аренда'!$D$20:$D$22) -> 763.055 | AI10: 2736 | AJ10: =SUMIF('Цены,перевалка,аренда'!$A$5:$A$17,Уголь_эластика_экспорт!A10,'Цены,перевалка,аренда'!$D$5:$D$17) -> 8546.216 | AK10: =AJ10/'Цены,перевалка,аренда'!$C$1 -> 112 | AL10: =AE10+AF10+AG10 -> 4739.4283 | AM10: =AJ10-AL10 -> 3806.7877 | AN10: =AI10+AH10+AG10+AF10+AE10 -> 7475.4283 | AO10: =(AJ10-AN10)/AJ10 -> 0.12529378 | AP10: =AL10/AJ10 -> 0.55456454 | AQ10: =AE10/AJ10 -> 0.41691434 | AR10: =AE10/AL10 -> 0.75178687 | AS10: =IT10 -> 1 | AT10: =S10*AS10 -> 1782028 | AU10: 0.9 | AV10: =(AJ10-(AE10*(1+$IS$2)+AF10+AG10+AH10+AI10))/AJ10 -> 0.083602341 | AW10: =(AE10*(1+$IS$2)+AF10+AG10)/AJ10 -> 0.59625597 | AX10: =(AE10*(1+$IS$2))/AJ10 -> 0.45860577 | AY10: =(AE10*(1+$IS$2))/(AE10*(1+$IS$2)+AF10+AG10) -> 0.76914244 | AZ10: =MIN(IF($AU10=100%,1,1+VLOOKUP(($AJ10-$AI10-$AH10-$AG10-$AF10-$AE10*(1+AZ$3))/$AJ10,Уголь_коэфф!$A:$B,2,1)-VLOOKUP($AO10,Уголь_коэфф!$A:$B,2,1)),1+(1-$AU10)) -> 1.1 | BA10: =MIN(IF($AU10=100%,1,1+VLOOKUP(($AJ10-$AI10-$AH10-$AG10-$AF10-$AE10*(1+BA$3))/$AJ10,Уголь_коэфф!$A:$B,2,1)-VLOOKUP($AO10,Уголь_коэфф!$A:$B,2,1)),1+(1-$AU10)) -> 1.1 | BB10: =MIN(IF($AU10=100%,1,1+VLOOKUP(($AJ10-$AI10-$AH10-$AG10-$AF10-$AE10*(1+BB$3))/$AJ10,Уголь_коэфф!$A:$B,2,1)-VLOOKUP($AO10,Уголь_коэфф!$A:$B,2,1)),1+(1-$AU10)) -> 1.1 | BC10: =MIN(IF($AU10=100%,1,1+VLOOKUP(($AJ10-$AI10-$AH10-$AG10-$AF10-$AE10*(1+BC$3))/$AJ10,Уголь_коэфф!$A:$B,2,1)-VLOOKUP($AO10,Уголь_коэфф!$A:$B,2,1)),1+(1-$AU10)) -> 1.1 | BD10: =MIN(IF($AU10=100%,1,1+VLOOKUP(($AJ10-$AI10-$AH10-$AG10-$AF10-$AE10*(1+BD$3))/$AJ10,Уголь_коэфф!$A:$B,2,1)-VLOOKUP($AO10,Уголь_коэфф!$A:$B,2,1)),1+(1-$AU10)) -> 1.1 | BE10: =MIN(IF($AU10=100%,1,1+VLOOKUP(($AJ10-$AI10-$AH10-$AG10-$AF10-$AE10*(1+BE$3))/$AJ10,Уголь_коэфф!$A:$B,2,1)-VLOOKUP($AO10,Уголь_коэфф!$A:$B,2,1)),1+(1-$AU10)) -> 1.1 | BF10: =MIN(IF($AU10=100%,1,1+VLOOKUP(($AJ10-$AI10-$AH10-$AG10-$AF10-$AE10*(1+BF$3))/$AJ10,Уголь_коэфф!$A:$B,2,1)-VLOOKUP($AO10,Уголь_коэфф!$A:$B,2,1)),1+(1-$AU10)) -> 1.1 | BG10: =MIN(IF($AU10=100%,1,1+VLOOKUP(($AJ10-$AI10-$AH10-$AG10-$AF10-$AE10*(1+BG$3))/$AJ10,Уголь_коэфф!$A:$B,2,1)-VLOOKUP($AO10,Уголь_коэфф!$A:$B,2,1)),1+(1-$AU10)) -> 1.1 | ... EU10: =MIN(IF($AU10=100%,1,1+VLOOKUP(($AJ10-$AI10-$AH10-$AG10-$AF10-$AE10*(1+EU$3))/$AJ10,Уголь_коэфф!$A:$B,2,1)-VLOOKUP($AO10,Уголь_коэфф!$A:$B,2,1)),1+(1-$AU10)) -> 1 | EV10: 1 | EW10: =MIN(1,MAX(VLOOKUP(($AJ10-$AI10-$AH10-$AG10-$AF10-$AE10*(1+EW$3))/$AJ10,Уголь_коэфф!$A:$B,2,1),(EV10-0.05))) -> 1 | EX10: =MIN(1,MAX(VLOOKUP(($AJ10-$AI10-$AH10-$AG10-$AF10-$AE10*(1+EX$3))/$AJ10,Уголь_коэфф!$A:$B,2,1),(EW10-0.05))) -> 1 | EY10: =MIN(1,MAX(VLOOKUP(($AJ10-$AI10-$AH10-$AG10-$AF10-$AE10*(1+EY$3))/$AJ10,Уголь_коэфф!$A:$B,2,1),(EX10-0.05))) -> 1 | EZ10: =MIN(1,MAX(VLOOKUP(($AJ10-$AI10-$AH10-$AG10-$AF10-$AE10*(1+EZ$3))/$AJ10,Уголь_коэфф!$A:$B,2,1),(EY10-0.05))) -> 1 | FA10: =MIN(1,MAX(VLOOKUP(($AJ10-$AI10-$AH10-$AG10-$AF10-$AE10*(1+FA$3))/$AJ10,Уголь_коэфф!$A:$B,2,1),(EZ10-0.05))) -> 1 | FB10: =MIN(1,MAX(VLOOKUP(($AJ10-$AI10-$AH10-$AG10-$AF10-$AE10*(1+FB$3))/$AJ10,Уголь_коэфф!$A:$B,2,1),(FA10-0.05))) -> 1 | FC10: =MIN(1,MAX(VLOOKUP(($AJ10-$AI10-$AH10-$AG10-$AF10-$AE10*(1+FC$3))/$AJ10,Уголь_коэфф!$A:$B,2,1),(FB10-0.05))) -> 1 | FD10: =MIN(1,MAX(VLOOKUP(($AJ10-$AI10-$AH10-$AG10-$AF10-$AE10*(1+FD$3))/$AJ10,Уголь_коэфф!$A:$B,2,1),(FC10-0.05))) -> 1 | ... IR10: =MIN(1,MAX(VLOOKUP(($AJ10-$AI10-$AH10-$AG10-$AF10-$AE10*(1+IR$3))/$AJ10,Уголь_коэфф!$A:$B,2,1),(IQ10-0.05))) -> 0.965 | IS10: =HLOOKUP($IS$2,$AZ$3:$IR$27,ROW(IR10)-2,FALSE) -> 1 | IT10: =IF($IV$2=1,IF(AND($IT$2="индексация",IS10<1,IS10*$IV$1>1),1,IF(AND($IT$2="индексация",IS10=1),1,IF(AND($IT$2="скидка",IS10=1),1,IS10*$IV$1))),IS10*$IV$1) -> 1
A11: уголь энергетический (кроме антрацита)ЭкспортСеверо-Западное | B11: 1 | C11: Уголь каменный | D11: 16117 | E11: УГОЛЬ СС | F11: уголь энергетический (кроме антрацита) | G11: ЗСБ | H11: ОКТ | I11: БОЧАТЫ | J11: ЛУЖСКАЯ-ЭКСП | K11: 4156 | L11: полувагон | M11: Экспорт | N11: неконтейнерная | O11: Северо-Западное | P11: 82365518 | Q11: АО "АТРИУМ" | R11: ООО "УГМК-Холдинг" | S11: 1822456 | T11: 7574874184 | U11: 25338 | W11: 3281208376 | X11: 69 | Y11: маршрутная | Z11: 11 | AA11: 12 | AB11: 4 | AC11: 2082.23 | AD11: 928.76 | AE11: =AC11+AD11 -> 3010.99 | AF11: ='Цены,перевалка,аренда'!$C$27*SUM(Уголь_эластика_экспорт!Z11+Уголь_эластика_экспорт!AA11+Уголь_эластика_экспорт!AB11)/Уголь_эластика_экспорт!X11 -> 273.91304 | AG11: =SUMIF('Цены,перевалка,аренда'!$A$20:$A$22,Уголь_эластика_экспорт!$O11,'Цены,перевалка,аренда'!$D$20:$D$22) -> 610.444 | AI11: 2736 | AJ11: =SUMIF('Цены,перевалка,аренда'!$A$5:$A$17,Уголь_эластика_экспорт!A11,'Цены,перевалка,аренда'!$D$5:$D$17) -> 6485.9675 | AK11: =AJ11/'Цены,перевалка,аренда'!$C$1 -> 85 | AL11: =AE11+AF11+AG11 -> 3895.347 | AM11: =AJ11-AL11 -> 2590.6205 | AN11: =AI11+AH11+AG11+AF11+AE11 -> 6631.347 | AO11: =(AJ11-AN11)/AJ11 -> -0.022414473 | AP11: =AL11/AJ11 -> 0.60058072 | AQ11: =AE11/AJ11 -> 0.46423144 | AR11: =AE11/AL11 -> 0.77297092 | AS11: =IT11 -> 0.975 | AT11: =S11*AS11 -> 1776894.6 | AU11: 0.9 | AV11: =(AJ11-(AE11*(1+$IS$2)+AF11+AG11+AH11+AI11))/AJ11 -> -0.068837617 | AW11: =(AE11*(1+$IS$2)+AF11+AG11)/AJ11 -> 0.64700387 | AX11: =(AE11*(1+$IS$2))/AJ11 -> 0.51065458 | AY11: =(AE11*(1+$IS$2))/(AE11*(1+$IS$2)+AF11+AG11) -> 0.78926048 | AZ11: =MIN(IF($AU11=100%,1,1+VLOOKUP(($AJ11-$AI11-$AH11-$AG11-$AF11-$AE11*(1+AZ$3))/$AJ11,Уголь_коэфф!$A:$B,2,1)-VLOOKUP($AO11,Уголь_коэфф!$A:$B,2,1)),1+(1-$AU11)) -> 1.097 | BA11: =MIN(IF($AU11=100%,1,1+VLOOKUP(($AJ11-$AI11-$AH11-$AG11-$AF11-$AE11*(1+BA$3))/$AJ11,Уголь_коэфф!$A:$B,2,1)-VLOOKUP($AO11,Уголь_коэфф!$A:$B,2,1)),1+(1-$AU11)) -> 1.097 | BB11: =MIN(IF($AU11=100%,1,1+VLOOKUP(($AJ11-$AI11-$AH11-$AG11-$AF11-$AE11*(1+BB$3))/$AJ11,Уголь_коэфф!$A:$B,2,1)-VLOOKUP($AO11,Уголь_коэфф!$A:$B,2,1)),1+(1-$AU11)) -> 1.097 | BC11: =MIN(IF($AU11=100%,1,1+VLOOKUP(($AJ11-$AI11-$AH11-$AG11-$AF11-$AE11*(1+BC$3))/$AJ11,Уголь_коэфф!$A:$B,2,1)-VLOOKUP($AO11,Уголь_коэфф!$A:$B,2,1)),1+(1-$AU11)) -> 1.097 | BD11: =MIN(IF($AU11=100%,1,1+VLOOKUP(($AJ11-$AI11-$AH11-$AG11-$AF11-$AE11*(1+BD$3))/$AJ11,Уголь_коэфф!$A:$B,2,1)-VLOOKUP($AO11,Уголь_коэфф!$A:$B,2,1)),1+(1-$AU11)) -> 1.097 | BE11: =MIN(IF($AU11=100%,1,1+VLOOKUP(($AJ11-$AI11-$AH11-$AG11-$AF11-$AE11*(1+BE$3))/$AJ11,Уголь_коэфф!$A:$B,2,1)-VLOOKUP($AO11,Уголь_коэфф!$A:$B,2,1)),1+(1-$AU11)) -> 1.091 | BF11: =MIN(IF($AU11=100%,1,1+VLOOKUP(($AJ11-$AI11-$AH11-$AG11-$AF11-$AE11*(1+BF$3))/$AJ11,Уголь_коэфф!$A:$B,2,1)-VLOOKUP($AO11,Уголь_коэфф!$A:$B,2,1)),1+(1-$AU11)) -> 1.091 | BG11: =MIN(IF($AU11=100%,1,1+VLOOKUP(($AJ11-$AI11-$AH11-$AG11-$AF11-$AE11*(1+BG$3))/$AJ11,Уголь_коэфф!$A:$B,2,1)-VLOOKUP($AO11,Уголь_коэфф!$A:$B,2,1)),1+(1-$AU11)) -> 1.091 | ... EU11: =MIN(IF($AU11=100%,1,1+VLOOKUP(($AJ11-$AI11-$AH11-$AG11-$AF11-$AE11*(1+EU$3))/$AJ11,Уголь_коэфф!$A:$B,2,1)-VLOOKUP($AO11,Уголь_коэфф!$A:$B,2,1)),1+(1-$AU11)) -> 1 | EV11: 1 | EW11: =MIN(1,MAX(VLOOKUP(($AJ11-$AI11-$AH11-$AG11-$AF11-$AE11*(1+EW$3))/$AJ11,Уголь_коэфф!$A:$B,2,1),(EV11-0.05))) -> 0.995 | EX11: =MIN(1,MAX(VLOOKUP(($AJ11-$AI11-$AH11-$AG11-$AF11-$AE11*(1+EX$3))/$AJ11,Уголь_коэфф!$A:$B,2,1),(EW11-0.05))) -> 0.995 | EY11: =MIN(1,MAX(VLOOKUP(($AJ11-$AI11-$AH11-$AG11-$AF11-$AE11*(1+EY$3))/$AJ11,Уголь_коэфф!$A:$B,2,1),(EX11-0.05))) -> 0.995 | EZ11: =MIN(1,MAX(VLOOKUP(($AJ11-$AI11-$AH11-$AG11-$AF11-$AE11*(1+EZ$3))/$AJ11,Уголь_коэфф!$A:$B,2,1),(EY11-0.05))) -> 0.99 | FA11: =MIN(1,MAX(VLOOKUP(($AJ11-$AI11-$AH11-$AG11-$AF11-$AE11*(1+FA$3))/$AJ11,Уголь_коэфф!$A:$B,2,1),(EZ11-0.05))) -> 0.99 | FB11: =MIN(1,MAX(VLOOKUP(($AJ11-$AI11-$AH11-$AG11-$AF11-$AE11*(1+FB$3))/$AJ11,Уголь_коэфф!$A:$B,2,1),(FA11-0.05))) -> 0.99 | FC11: =MIN(1,MAX(VLOOKUP(($AJ11-$AI11-$AH11-$AG11-$AF11-$AE11*(1+FC$3))/$AJ11,Уголь_коэфф!$A:$B,2,1),(FB11-0.05))) -> 0.99 | FD11: =MIN(1,MAX(VLOOKUP(($AJ11-$AI11-$AH11-$AG11-$AF11-$AE11*(1+FD$3))/$AJ11,Уголь_коэфф!$A:$B,2,1),(FC11-0.05))) -> 0.985 | ... IR11: =MIN(1,MAX(VLOOKUP(($AJ11-$AI11-$AH11-$AG11-$AF11-$AE11*(1+IR$3))/$AJ11,Уголь_коэфф!$A:$B,2,1),(IQ11-0.05))) -> 0.872 | IS11: =HLOOKUP($IS$2,$AZ$3:$IR$27,ROW(IR11)-2,FALSE) -> 0.975 | IT11: =IF($IV$2=1,IF(AND($IT$2="индексация",IS11<1,IS11*$IV$1>1),1,IF(AND($IT$2="индексация",IS11=1),1,IF(AND($IT$2="скидка",IS11=1),1,IS11*$IV$1))),IS11*$IV$1) -> 0.975
A12: уголь энергетический (кроме антрацита)ЭкспортЮжное | B12: 1 | C12: Уголь каменный | D12: 16112 | E12: УГОЛЬ Д | F12: уголь энергетический (кроме антрацита) | G12: ЗСБ | H12: СКВ | I12: ЕРУНАКОВО | J12: ТУАПСЕ-СОР-Э | K12: 4637 | L12: полувагон | M12: Экспорт | N12: неконтейнерная | O12: Южное | P12: 82365518 | Q12: АО "АТРИУМ" | R12: ООО "УГМК-Холдинг" | S12: 1389317 | T12: 6442749019 | U12: 19610 | W12: 2689139106 | X12: 69 | Y12: маршрутная | Z12: 11 | AA12: 12 | AB12: 4 | AC12: 2198.94 | AD12: 1008.93 | AE12: =AC12+AD12 -> 3207.87 | AF12: ='Цены,перевалка,аренда'!$C$27*SUM(Уголь_эластика_экспорт!Z12+Уголь_эластика_экспорт!AA12+Уголь_эластика_экспорт!AB12)/Уголь_эластика_экспорт!X12 -> 273.91304 | AG12: =SUMIF('Цены,перевалка,аренда'!$A$20:$A$22,Уголь_эластика_экспорт!$O12,'Цены,перевалка,аренда'!$D$20:$D$22) -> 991.9715 | AI12: 2736 | AJ12: =SUMIF('Цены,перевалка,аренда'!$A$5:$A$17,Уголь_эластика_экспорт!A12,'Цены,перевалка,аренда'!$D$5:$D$17) -> 7249.0225 | AK12: =AJ12/'Цены,перевалка,аренда'!$C$1 -> 95 | AL12: =AE12+AF12+AG12 -> 4473.7545 | AM12: =AJ12-AL12 -> 2775.268 | AN12: =AI12+AH12+AG12+AF12+AE12 -> 7209.7545 | AO12: =(AJ12-AN12)/AJ12 -> 0.0054170002 | AP12: =AL12/AJ12 -> 0.6171528 | AQ12: =AE12/AJ12 -> 0.44252449 | AR12: =AE12/AL12 -> 0.71704202 | AS12: =IT12 -> 0.99 | AT12: =S12*AS12 -> 1375423.8 | AU12: 0.9 | AV12: =(AJ12-(AE12*(1+$IS$2)+AF12+AG12+AH12+AI12))/AJ12 -> -0.038835449 | AW12: =(AE12*(1+$IS$2)+AF12+AG12)/AJ12 -> 0.66140525 | AX12: =(AE12*(1+$IS$2))/AJ12 -> 0.48677694 | AY12: =(AE12*(1+$IS$2))/(AE12*(1+$IS$2)+AF12+AG12) -> 0.73597381 | AZ12: =MIN(IF($AU12=100%,1,1+VLOOKUP(($AJ12-$AI12-$AH12-$AG12-$AF12-$AE12*(1+AZ$3))/$AJ12,Уголь_коэфф!$A:$B,2,1)-VLOOKUP($AO12,Уголь_коэфф!$A:$B,2,1)),1+(1-$AU12)) -> 1.1 | BA12: =MIN(IF($AU12=100%,1,1+VLOOKUP(($AJ12-$AI12-$AH12-$AG12-$AF12-$AE12*(1+BA$3))/$AJ12,Уголь_коэфф!$A:$B,2,1)-VLOOKUP($AO12,Уголь_коэфф!$A:$B,2,1)),1+(1-$AU12)) -> 1.1 | BB12: =MIN(IF($AU12=100%,1,1+VLOOKUP(($AJ12-$AI12-$AH12-$AG12-$AF12-$AE12*(1+BB$3))/$AJ12,Уголь_коэфф!$A:$B,2,1)-VLOOKUP($AO12,Уголь_коэфф!$A:$B,2,1)),1+(1-$AU12)) -> 1.1 | BC12: =MIN(IF($AU12=100%,1,1+VLOOKUP(($AJ12-$AI12-$AH12-$AG12-$AF12-$AE12*(1+BC$3))/$AJ12,Уголь_коэфф!$A:$B,2,1)-VLOOKUP($AO12,Уголь_коэфф!$A:$B,2,1)),1+(1-$AU12)) -> 1.1 | BD12: =MIN(IF($AU12=100%,1,1+VLOOKUP(($AJ12-$AI12-$AH12-$AG12-$AF12-$AE12*(1+BD$3))/$AJ12,Уголь_коэфф!$A:$B,2,1)-VLOOKUP($AO12,Уголь_коэфф!$A:$B,2,1)),1+(1-$AU12)) -> 1.098 | BE12: =MIN(IF($AU12=100%,1,1+VLOOKUP(($AJ12-$AI12-$AH12-$AG12-$AF12-$AE12*(1+BE$3))/$AJ12,Уголь_коэфф!$A:$B,2,1)-VLOOKUP($AO12,Уголь_коэфф!$A:$B,2,1)),1+(1-$AU12)) -> 1.098 | BF12: =MIN(IF($AU12=100%,1,1+VLOOKUP(($AJ12-$AI12-$AH12-$AG12-$AF12-$AE12*(1+BF$3))/$AJ12,Уголь_коэфф!$A:$B,2,1)-VLOOKUP($AO12,Уголь_коэфф!$A:$B,2,1)),1+(1-$AU12)) -> 1.098 | BG12: =MIN(IF($AU12=100%,1,1+VLOOKUP(($AJ12-$AI12-$AH12-$AG12-$AF12-$AE12*(1+BG$3))/$AJ12,Уголь_коэфф!$A:$B,2,1)-VLOOKUP($AO12,Уголь_коэфф!$A:$B,2,1)),1+(1-$AU12)) -> 1.098 | ... EU12: =MIN(IF($AU12=100%,1,1+VLOOKUP(($AJ12-$AI12-$AH12-$AG12-$AF12-$AE12*(1+EU$3))/$AJ12,Уголь_коэфф!$A:$B,2,1)-VLOOKUP($AO12,Уголь_коэфф!$A:$B,2,1)),1+(1-$AU12)) -> 1 | EV12: 1 | EW12: =MIN(1,MAX(VLOOKUP(($AJ12-$AI12-$AH12-$AG12-$AF12-$AE12*(1+EW$3))/$AJ12,Уголь_коэфф!$A:$B,2,1),(EV12-0.05))) -> 1 | EX12: =MIN(1,MAX(VLOOKUP(($AJ12-$AI12-$AH12-$AG12-$AF12-$AE12*(1+EX$3))/$AJ12,Уголь_коэфф!$A:$B,2,1),(EW12-0.05))) -> 1 | EY12: =MIN(1,MAX(VLOOKUP(($AJ12-$AI12-$AH12-$AG12-$AF12-$AE12*(1+EY$3))/$AJ12,Уголь_коэфф!$A:$B,2,1),(EX12-0.05))) -> 1 | EZ12: =MIN(1,MAX(VLOOKUP(($AJ12-$AI12-$AH12-$AG12-$AF12-$AE12*(1+EZ$3))/$AJ12,Уголь_коэфф!$A:$B,2,1),(EY12-0.05))) -> 1 | FA12: =MIN(1,MAX(VLOOKUP(($AJ12-$AI12-$AH12-$AG12-$AF12-$AE12*(1+FA$3))/$AJ12,Уголь_коэфф!$A:$B,2,1),(EZ12-0.05))) -> 1 | FB12: =MIN(1,MAX(VLOOKUP(($AJ12-$AI12-$AH12-$AG12-$AF12-$AE12*(1+FB$3))/$AJ12,Уголь_коэфф!$A:$B,2,1),(FA12-0.05))) -> 1 | FC12: =MIN(1,MAX(VLOOKUP(($AJ12-$AI12-$AH12-$AG12-$AF12-$AE12*(1+FC$3))/$AJ12,Уголь_коэфф!$A:$B,2,1),(FB12-0.05))) -> 1 | FD12: =MIN(1,MAX(VLOOKUP(($AJ12-$AI12-$AH12-$AG12-$AF12-$AE12*(1+FD$3))/$AJ12,Уголь_коэфф!$A:$B,2,1),(FC12-0.05))) -> 1 | ... IR12: =MIN(1,MAX(VLOOKUP(($AJ12-$AI12-$AH12-$AG12-$AF12-$AE12*(1+IR$3))/$AJ12,Уголь_коэфф!$A:$B,2,1),(IQ12-0.05))) -> 0.896 | IS12: =HLOOKUP($IS$2,$AZ$3:$IR$27,ROW(IR12)-2,FALSE) -> 0.99 | IT12: =IF($IV$2=1,IF(AND($IT$2="индексация",IS12<1,IS12*$IV$1>1),1,IF(AND($IT$2="индексация",IS12=1),1,IF(AND($IT$2="скидка",IS12=1),1,IS12*$IV$1))),IS12*$IV$1) -> 0.99
A13: уголь энергетический (кроме антрацита)ЭкспортВосточное | B13: 1 | C13: Уголь каменный | D13: 16111 | E13: УГОЛЬ Г | F13: уголь энергетический (кроме антрацита) | G13: ДВС | H13: ДВС | I13: УЛАК | J13: СТРЕЛКОВАЯ-Э | K13: 2421 | L13: полувагон | M13: Экспорт | N13: неконтейнерная | O13: Восточное | P13: 50029397 | Q13: АО "НОВЫЙ МИР" | R13: ООО "УК "Эльга" | S13: 3770445 | T13: 9130041724 | U13: 50798 | W13: 4501908298 | X13: 75 | Y13: маршрутная | Z13: 6 | AA13: 6 | AB13: 4 | AC13: 1199.87 | AD13: 560.68 | AE13: =AC13+AD13 -> 1760.55 | AF13: ='Цены,перевалка,аренда'!$C$26*SUM(Уголь_эластика_экспорт!Z13+Уголь_эластика_экспорт!AA13+Уголь_эластика_экспорт!AB13)/Уголь_эластика_экспорт!X13 -> 213.33333 | AG13: =SUMIF('Цены,перевалка,аренда'!$A$20:$A$22,Уголь_эластика_экспорт!$O13,'Цены,перевалка,аренда'!$D$20:$D$22) -> 763.055 | AI13: 3240 | AJ13: =SUMIF('Цены,перевалка,аренда'!$A$5:$A$17,Уголь_эластика_экспорт!A13,'Цены,перевалка,аренда'!$D$5:$D$17) -> 8546.216 | AK13: =AJ13/'Цены,перевалка,аренда'!$C$1 -> 112 | AL13: =AE13+AF13+AG13 -> 2736.9383 | AM13: =AJ13-AL13 -> 5809.2777 | AN13: =AI13+AH13+AG13+AF13+AE13 -> 5976.9383 | AO13: =(AJ13-AN13)/AJ13 -> 0.30063336 | AP13: =AL13/AJ13 -> 0.32025148 | AQ13: =AE13/AJ13 -> 0.20600345 | AR13: =AE13/AL13 -> 0.64325527 | AS13: =IT13 -> 1 | AT13: =S13*AS13 -> 3770445 | AU13: =35/40 -> 0.875 | AV13: =(AJ13-(AE13*(1+$IS$2)+AF13+AG13+AH13+AI13))/AJ13 -> 0.28003302 | AW13: =(AE13*(1+$IS$2)+AF13+AG13)/AJ13 -> 0.34085183 | AX13: =(AE13*(1+$IS$2))/AJ13 -> 0.2266038 | AY13: =(AE13*(1+$IS$2))/(AE13*(1+$IS$2)+AF13+AG13) -> 0.66481615 | AZ13: =MIN(IF($AU13=100%,1,1+VLOOKUP(($AJ13-$AI13-$AH13-$AG13-$AF13-$AE13*(1+AZ$3))/$AJ13,Уголь_коэфф!$A:$B,2,1)-VLOOKUP($AO13,Уголь_коэфф!$A:$B,2,1)),1+(1-$AU13)) -> 1.068 | BA13: =MIN(IF($AU13=100%,1,1+VLOOKUP(($AJ13-$AI13-$AH13-$AG13-$AF13-$AE13*(1+BA$3))/$AJ13,Уголь_коэфф!$A:$B,2,1)-VLOOKUP($AO13,Уголь_коэфф!$A:$B,2,1)),1+(1-$AU13)) -> 1.068 | BB13: =MIN(IF($AU13=100%,1,1+VLOOKUP(($AJ13-$AI13-$AH13-$AG13-$AF13-$AE13*(1+BB$3))/$AJ13,Уголь_коэфф!$A:$B,2,1)-VLOOKUP($AO13,Уголь_коэфф!$A:$B,2,1)),1+(1-$AU13)) -> 1.068 | BC13: =MIN(IF($AU13=100%,1,1+VLOOKUP(($AJ13-$AI13-$AH13-$AG13-$AF13-$AE13*(1+BC$3))/$AJ13,Уголь_коэфф!$A:$B,2,1)-VLOOKUP($AO13,Уголь_коэфф!$A:$B,2,1)),1+(1-$AU13)) -> 1.068 | BD13: =MIN(IF($AU13=100%,1,1+VLOOKUP(($AJ13-$AI13-$AH13-$AG13-$AF13-$AE13*(1+BD$3))/$AJ13,Уголь_коэфф!$A:$B,2,1)-VLOOKUP($AO13,Уголь_коэфф!$A:$B,2,1)),1+(1-$AU13)) -> 1.061 | BE13: =MIN(IF($AU13=100%,1,1+VLOOKUP(($AJ13-$AI13-$AH13-$AG13-$AF13-$AE13*(1+BE$3))/$AJ13,Уголь_коэфф!$A:$B,2,1)-VLOOKUP($AO13,Уголь_коэфф!$A:$B,2,1)),1+(1-$AU13)) -> 1.061 | BF13: =MIN(IF($AU13=100%,1,1+VLOOKUP(($AJ13-$AI13-$AH13-$AG13-$AF13-$AE13*(1+BF$3))/$AJ13,Уголь_коэфф!$A:$B,2,1)-VLOOKUP($AO13,Уголь_коэфф!$A:$B,2,1)),1+(1-$AU13)) -> 1.061 | BG13: =MIN(IF($AU13=100%,1,1+VLOOKUP(($AJ13-$AI13-$AH13-$AG13-$AF13-$AE13*(1+BG$3))/$AJ13,Уголь_коэфф!$A:$B,2,1)-VLOOKUP($AO13,Уголь_коэфф!$A:$B,2,1)),1+(1-$AU13)) -> 1.061 | ... EU13: =MIN(IF($AU13=100%,1,1+VLOOKUP(($AJ13-$AI13-$AH13-$AG13-$AF13-$AE13*(1+EU$3))/$AJ13,Уголь_коэфф!$A:$B,2,1)-VLOOKUP($AO13,Уголь_коэфф!$A:$B,2,1)),1+(1-$AU13)) -> 1 | EV13: 1 | EW13: =MIN(1,MAX(VLOOKUP(($AJ13-$AI13-$AH13-$AG13-$AF13-$AE13*(1+EW$3))/$AJ13,Уголь_коэфф!$A:$B,2,1),(EV13-0.05))) -> 1 | EX13: =MIN(1,MAX(VLOOKUP(($AJ13-$AI13-$AH13-$AG13-$AF13-$AE13*(1+EX$3))/$AJ13,Уголь_коэфф!$A:$B,2,1),(EW13-0.05))) -> 1 | EY13: =MIN(1,MAX(VLOOKUP(($AJ13-$AI13-$AH13-$AG13-$AF13-$AE13*(1+EY$3))/$AJ13,Уголь_коэфф!$A:$B,2,1),(EX13-0.05))) -> 1 | EZ13: =MIN(1,MAX(VLOOKUP(($AJ13-$AI13-$AH13-$AG13-$AF13-$AE13*(1+EZ$3))/$AJ13,Уголь_коэфф!$A:$B,2,1),(EY13-0.05))) -> 1 | FA13: =MIN(1,MAX(VLOOKUP(($AJ13-$AI13-$AH13-$AG13-$AF13-$AE13*(1+FA$3))/$AJ13,Уголь_коэфф!$A:$B,2,1),(EZ13-0.05))) -> 1 | FB13: =MIN(1,MAX(VLOOKUP(($AJ13-$AI13-$AH13-$AG13-$AF13-$AE13*(1+FB$3))/$AJ13,Уголь_коэфф!$A:$B,2,1),(FA13-0.05))) -> 1 | FC13: =MIN(1,MAX(VLOOKUP(($AJ13-$AI13-$AH13-$AG13-$AF13-$AE13*(1+FC$3))/$AJ13,Уголь_коэфф!$A:$B,2,1),(FB13-0.05))) -> 1 | FD13: =MIN(1,MAX(VLOOKUP(($AJ13-$AI13-$AH13-$AG13-$AF13-$AE13*(1+FD$3))/$AJ13,Уголь_коэфф!$A:$B,2,1),(FC13-0.05))) -> 1 | ... IR13: =MIN(1,MAX(VLOOKUP(($AJ13-$AI13-$AH13-$AG13-$AF13-$AE13*(1+IR$3))/$AJ13,Уголь_коэфф!$A:$B,2,1),(IQ13-0.05))) -> 1 | IS13: =HLOOKUP($IS$2,$AZ$3:$IR$27,ROW(IR13)-2,FALSE) -> 1 | IT13: =IF($IV$2=1,IF(AND($IT$2="индексация",IS13<1,IS13*$IV$1>1),1,IF(AND($IT$2="индексация",IS13=1),1,IF(AND($IT$2="скидка",IS13=1),1,IS13*$IV$1))),IS13*$IV$1) -> 1
A14: уголь для коксованияЭкспортВосточное | B14: 1 | C14: Уголь каменный | D14: 16104 | E14: КОНЦЕНТР УГОЛЬН | F14: уголь для коксования | G14: ЗСБ | H14: ДВС | I14: МЕЖДУРЕЧЕНСК | J14: НАХОДКА-ЭКС | K14: 5820 | L14: полувагон | M14: Экспорт | N14: неконтейнерная | O14: Восточное | P14: 57775656 | Q14: ООО "КУБЕЙРА ТРЕЙДИНГ" | R14: ООО "ЕвразХолдинг" | S14: 1434447 | T14: 8349124223 | U14: 19225 | W14: 3205086675 | X14: 75 | Y14: маршрутная | Z14: 13 | AA14: 14 | AB14: 4 | AC14: 2483.44 | AD14: 1092.09 | AE14: =AC14+AD14 -> 3575.53 | AF14: ='Цены,перевалка,аренда'!$C$26*SUM(Уголь_эластика_экспорт!Z14+Уголь_эластика_экспорт!AA14+Уголь_эластика_экспорт!AB14)/Уголь_эластика_экспорт!X14 -> 413.33333 | AG14: =SUMIF('Цены,перевалка,аренда'!$A$20:$A$22,Уголь_эластика_экспорт!$O14,'Цены,перевалка,аренда'!$D$20:$D$22) -> 763.055 | AI14: 3876 | AJ14: =SUMIF('Цены,перевалка,аренда'!$A$5:$A$17,Уголь_эластика_экспорт!A14,'Цены,перевалка,аренда'!$D$5:$D$17) -> 10911.686 | AK14: =AJ14/'Цены,перевалка,аренда'!$C$1 -> 143 | AL14: =AE14+AF14+AG14 -> 4751.9183 | AM14: =AJ14-AL14 -> 6159.7682 | AN14: =AI14+AH14+AG14+AF14+AE14 -> 8627.9183 | AO14: =(AJ14-AN14)/AJ14 -> 0.20929562 | AP14: =AL14/AJ14 -> 0.4354889 | AQ14: =AE14/AJ14 -> 0.32767895 | AR14: =AE14/AL14 -> 0.75243928 | AS14: =IT14 -> 1 | AT14: =S14*AS14 -> 1434447 | AU14: 1 | AV14: =(AJ14-(AE14*(1+$IS$2)+AF14+AG14+AH14+AI14))/AJ14 -> 0.17652772 | AW14: =(AE14*(1+$IS$2)+AF14+AG14)/AJ14 -> 0.46825679 | AX14: =(AE14*(1+$IS$2))/AJ14 -> 0.36044685 | AY14: =(AE14*(1+$IS$2))/(AE14*(1+$IS$2)+AF14+AG14) -> 0.7697632 | AZ14: =MIN(IF($AU14=100%,1,1+VLOOKUP(($AJ14-$AI14-$AH14-$AG14-$AF14-$AE14*(1+AZ$3))/$AJ14,Уголь_коэфф!$A:$B,2,1)-VLOOKUP($AO14,Уголь_коэфф!$A:$B,2,1)),1+(1-$AU14)) -> 1 | BA14: =MIN(IF($AU14=100%,1,1+VLOOKUP(($AJ14-$AI14-$AH14-$AG14-$AF14-$AE14*(1+BA$3))/$AJ14,Уголь_коэфф!$A:$B,2,1)-VLOOKUP($AO14,Уголь_коэфф!$A:$B,2,1)),1+(1-$AU14)) -> 1 | BB14: =MIN(IF($AU14=100%,1,1+VLOOKUP(($AJ14-$AI14-$AH14-$AG14-$AF14-$AE14*(1+BB$3))/$AJ14,Уголь_коэфф!$A:$B,2,1)-VLOOKUP($AO14,Уголь_коэфф!$A:$B,2,1)),1+(1-$AU14)) -> 1 | BC14: =MIN(IF($AU14=100%,1,1+VLOOKUP(($AJ14-$AI14-$AH14-$AG14-$AF14-$AE14*(1+BC$3))/$AJ14,Уголь_коэфф!$A:$B,2,1)-VLOOKUP($AO14,Уголь_коэфф!$A:$B,2,1)),1+(1-$AU14)) -> 1 | BD14: =MIN(IF($AU14=100%,1,1+VLOOKUP(($AJ14-$AI14-$AH14-$AG14-$AF14-$AE14*(1+BD$3))/$AJ14,Уголь_коэфф!$A:$B,2,1)-VLOOKUP($AO14,Уголь_коэфф!$A:$B,2,1)),1+(1-$AU14)) -> 1 | BE14: =MIN(IF($AU14=100%,1,1+VLOOKUP(($AJ14-$AI14-$AH14-$AG14-$AF14-$AE14*(1+BE$3))/$AJ14,Уголь_коэфф!$A:$B,2,1)-VLOOKUP($AO14,Уголь_коэфф!$A:$B,2,1)),1+(1-$AU14)) -> 1 | BF14: =MIN(IF($AU14=100%,1,1+VLOOKUP(($AJ14-$AI14-$AH14-$AG14-$AF14-$AE14*(1+BF$3))/$AJ14,Уголь_коэфф!$A:$B,2,1)-VLOOKUP($AO14,Уголь_коэфф!$A:$B,2,1)),1+(1-$AU14)) -> 1 | BG14: =MIN(IF($AU14=100%,1,1+VLOOKUP(($AJ14-$AI14-$AH14-$AG14-$AF14-$AE14*(1+BG$3))/$AJ14,Уголь_коэфф!$A:$B,2,1)-VLOOKUP($AO14,Уголь_коэфф!$A:$B,2,1)),1+(1-$AU14)) -> 1 | ... EU14: =MIN(IF($AU14=100%,1,1+VLOOKUP(($AJ14-$AI14-$AH14-$AG14-$AF14-$AE14*(1+EU$3))/$AJ14,Уголь_коэфф!$A:$B,2,1)-VLOOKUP($AO14,Уголь_коэфф!$A:$B,2,1)),1+(1-$AU14)) -> 1 | EV14: 1 | EW14: =MIN(1,MAX(VLOOKUP(($AJ14-$AI14-$AH14-$AG14-$AF14-$AE14*(1+EW$3))/$AJ14,Уголь_коэфф!$A:$B,2,1),(EV14-0.05))) -> 1 | EX14: =MIN(1,MAX(VLOOKUP(($AJ14-$AI14-$AH14-$AG14-$AF14-$AE14*(1+EX$3))/$AJ14,Уголь_коэфф!$A:$B,2,1),(EW14-0.05))) -> 1 | EY14: =MIN(1,MAX(VLOOKUP(($AJ14-$AI14-$AH14-$AG14-$AF14-$AE14*(1+EY$3))/$AJ14,Уголь_коэфф!$A:$B,2,1),(EX14-0.05))) -> 1 | EZ14: =MIN(1,MAX(VLOOKUP(($AJ14-$AI14-$AH14-$AG14-$AF14-$AE14*(1+EZ$3))/$AJ14,Уголь_коэфф!$A:$B,2,1),(EY14-0.05))) -> 1 | FA14: =MIN(1,MAX(VLOOKUP(($AJ14-$AI14-$AH14-$AG14-$AF14-$AE14*(1+FA$3))/$AJ14,Уголь_коэфф!$A:$B,2,1),(EZ14-0.05))) -> 1 | FB14: =MIN(1,MAX(VLOOKUP(($AJ14-$AI14-$AH14-$AG14-$AF14-$AE14*(1+FB$3))/$AJ14,Уголь_коэфф!$A:$B,2,1),(FA14-0.05))) -> 1 | FC14: =MIN(1,MAX(VLOOKUP(($AJ14-$AI14-$AH14-$AG14-$AF14-$AE14*(1+FC$3))/$AJ14,Уголь_коэфф!$A:$B,2,1),(FB14-0.05))) -> 1 | FD14: =MIN(1,MAX(VLOOKUP(($AJ14-$AI14-$AH14-$AG14-$AF14-$AE14*(1+FD$3))/$AJ14,Уголь_коэфф!$A:$B,2,1),(FC14-0.05))) -> 1 | ... IR14: =MIN(1,MAX(VLOOKUP(($AJ14-$AI14-$AH14-$AG14-$AF14-$AE14*(1+IR$3))/$AJ14,Уголь_коэфф!$A:$B,2,1),(IQ14-0.05))) -> 1 | IS14: =HLOOKUP($IS$2,$AZ$3:$IR$27,ROW(IR14)-2,FALSE) -> 1 | IT14: =IF($IV$2=1,IF(AND($IT$2="индексация",IS14<1,IS14*$IV$1>1),1,IF(AND($IT$2="индексация",IS14=1),1,IF(AND($IT$2="скидка",IS14=1),1,IS14*$IV$1))),IS14*$IV$1) -> 1
A15: уголь для коксованияЭкспортСеверо-Западное | B15: 1 | C15: Уголь каменный | D15: 16104 | E15: КОНЦЕНТР УГОЛЬН | F15: уголь для коксования | G15: ЗСБ | H15: ОКТ | I15: ОБНОРСКАЯ | J15: ЛУЖСКАЯ-ЭКСП | K15: 4245 | L15: полувагон | M15: Экспорт | N15: неконтейнерная | O15: Северо-Западное | P15: 57775656 | Q15: ООО "КУБЕЙРА ТРЕЙДИНГ" | R15: ООО "ЕвразХолдинг" | S15: 51530 | T15: 218745519 | U15: 725 | W15: 99074483 | X15: 69 | Y15: маршрутная | Z15: 11 | AA15: 12 | AB15: 4 | AC15: 2093.25 | AD15: 945.01 | AE15: =AC15+AD15 -> 3038.26 | AF15: ='Цены,перевалка,аренда'!$C$27*SUM(Уголь_эластика_экспорт!Z15+Уголь_эластика_экспорт!AA15+Уголь_эластика_экспорт!AB15)/Уголь_эластика_экспорт!X15 -> 273.91304 | AG15: =SUMIF('Цены,перевалка,аренда'!$A$20:$A$22,Уголь_эластика_экспорт!$O15,'Цены,перевалка,аренда'!$D$20:$D$22) -> 610.444 | AI15: 3876 | AJ15: =SUMIF('Цены,перевалка,аренда'!$A$5:$A$17,Уголь_эластика_экспорт!A15,'Цены,перевалка,аренда'!$D$5:$D$17) -> 8431.7577 | AK15: =AJ15/'Цены,перевалка,аренда'!$C$1 -> 110.5 | AL15: =AE15+AF15+AG15 -> 3922.617 | AM15: =AJ15-AL15 -> 4509.1407 | AN15: =AI15+AH15+AG15+AF15+AE15 -> 7798.617 | AO15: =(AJ15-AN15)/AJ15 -> 0.075090002 | AP15: =AL15/AJ15 -> 0.46521937 | AQ15: =AE15/AJ15 -> 0.3603353 | AR15: =AE15/AL15 -> 0.77454923 | AS15: =IT15 -> 1 | AT15: =S15*AS15 -> 51530 | AU15: 1 | AV15: =(AJ15-(AE15*(1+$IS$2)+AF15+AG15+AH15+AI15))/AJ15 -> 0.039056472 | AW15: =(AE15*(1+$IS$2)+AF15+AG15)/AJ15 -> 0.5012529 | AX15: =(AE15*(1+$IS$2))/AJ15 -> 0.39636884 | AY15: =(AE15*(1+$IS$2))/(AE15*(1+$IS$2)+AF15+AG15) -> 0.79075619 | AZ15: =MIN(IF($AU15=100%,1,1+VLOOKUP(($AJ15-$AI15-$AH15-$AG15-$AF15-$AE15*(1+AZ$3))/$AJ15,Уголь_коэфф!$A:$B,2,1)-VLOOKUP($AO15,Уголь_коэфф!$A:$B,2,1)),1+(1-$AU15)) -> 1 | BA15: =MIN(IF($AU15=100%,1,1+VLOOKUP(($AJ15-$AI15-$AH15-$AG15-$AF15-$AE15*(1+BA$3))/$AJ15,Уголь_коэфф!$A:$B,2,1)-VLOOKUP($AO15,Уголь_коэфф!$A:$B,2,1)),1+(1-$AU15)) -> 1 | BB15: =MIN(IF($AU15=100%,1,1+VLOOKUP(($AJ15-$AI15-$AH15-$AG15-$AF15-$AE15*(1+BB$3))/$AJ15,Уголь_коэфф!$A:$B,2,1)-VLOOKUP($AO15,Уголь_коэфф!$A:$B,2,1)),1+(1-$AU15)) -> 1 | BC15: =MIN(IF($AU15=100%,1,1+VLOOKUP(($AJ15-$AI15-$AH15-$AG15-$AF15-$AE15*(1+BC$3))/$AJ15,Уголь_коэфф!$A:$B,2,1)-VLOOKUP($AO15,Уголь_коэфф!$A:$B,2,1)),1+(1-$AU15)) -> 1 | BD15: =MIN(IF($AU15=100%,1,1+VLOOKUP(($AJ15-$AI15-$AH15-$AG15-$AF15-$AE15*(1+BD$3))/$AJ15,Уголь_коэфф!$A:$B,2,1)-VLOOKUP($AO15,Уголь_коэфф!$A:$B,2,1)),1+(1-$AU15)) -> 1 | BE15: =MIN(IF($AU15=100%,1,1+VLOOKUP(($AJ15-$AI15-$AH15-$AG15-$AF15-$AE15*(1+BE$3))/$AJ15,Уголь_коэфф!$A:$B,2,1)-VLOOKUP($AO15,Уголь_коэфф!$A:$B,2,1)),1+(1-$AU15)) -> 1 | BF15: =MIN(IF($AU15=100%,1,1+VLOOKUP(($AJ15-$AI15-$AH15-$AG15-$AF15-$AE15*(1+BF$3))/$AJ15,Уголь_коэфф!$A:$B,2,1)-VLOOKUP($AO15,Уголь_коэфф!$A:$B,2,1)),1+(1-$AU15)) -> 1 | BG15: =MIN(IF($AU15=100%,1,1+VLOOKUP(($AJ15-$AI15-$AH15-$AG15-$AF15-$AE15*(1+BG$3))/$AJ15,Уголь_коэфф!$A:$B,2,1)-VLOOKUP($AO15,Уголь_коэфф!$A:$B,2,1)),1+(1-$AU15)) -> 1 | ... EU15: =MIN(IF($AU15=100%,1,1+VLOOKUP(($AJ15-$AI15-$AH15-$AG15-$AF15-$AE15*(1+EU$3))/$AJ15,Уголь_коэфф!$A:$B,2,1)-VLOOKUP($AO15,Уголь_коэфф!$A:$B,2,1)),1+(1-$AU15)) -> 1 | EV15: 1 | EW15: =MIN(1,MAX(VLOOKUP(($AJ15-$AI15-$AH15-$AG15-$AF15-$AE15*(1+EW$3))/$AJ15,Уголь_коэфф!$A:$B,2,1),(EV15-0.05))) -> 1 | EX15: =MIN(1,MAX(VLOOKUP(($AJ15-$AI15-$AH15-$AG15-$AF15-$AE15*(1+EX$3))/$AJ15,Уголь_коэфф!$A:$B,2,1),(EW15-0.05))) -> 1 | EY15: =MIN(1,MAX(VLOOKUP(($AJ15-$AI15-$AH15-$AG15-$AF15-$AE15*(1+EY$3))/$AJ15,Уголь_коэфф!$A:$B,2,1),(EX15-0.05))) -> 1 | EZ15: =MIN(1,MAX(VLOOKUP(($AJ15-$AI15-$AH15-$AG15-$AF15-$AE15*(1+EZ$3))/$AJ15,Уголь_коэфф!$A:$B,2,1),(EY15-0.05))) -> 1 | FA15: =MIN(1,MAX(VLOOKUP(($AJ15-$AI15-$AH15-$AG15-$AF15-$AE15*(1+FA$3))/$AJ15,Уголь_коэфф!$A:$B,2,1),(EZ15-0.05))) -> 1 | FB15: =MIN(1,MAX(VLOOKUP(($AJ15-$AI15-$AH15-$AG15-$AF15-$AE15*(1+FB$3))/$AJ15,Уголь_коэфф!$A:$B,2,1),(FA15-0.05))) -> 1 | FC15: =MIN(1,MAX(VLOOKUP(($AJ15-$AI15-$AH15-$AG15-$AF15-$AE15*(1+FC$3))/$AJ15,Уголь_коэфф!$A:$B,2,1),(FB15-0.05))) -> 1 | FD15: =MIN(1,MAX(VLOOKUP(($AJ15-$AI15-$AH15-$AG15-$AF15-$AE15*(1+FD$3))/$AJ15,Уголь_коэфф!$A:$B,2,1),(FC15-0.05))) -> 1 | ... IR15: =MIN(1,MAX(VLOOKUP(($AJ15-$AI15-$AH15-$AG15-$AF15-$AE15*(1+IR$3))/$AJ15,Уголь_коэфф!$A:$B,2,1),(IQ15-0.05))) -> 0.955 | IS15: =HLOOKUP($IS$2,$AZ$3:$IR$27,ROW(IR15)-2,FALSE) -> 1 | IT15: =IF($IV$2=1,IF(AND($IT$2="индексация",IS15<1,IS15*$IV$1>1),1,IF(AND($IT$2="индексация",IS15=1),1,IF(AND($IT$2="скидка",IS15=1),1,IS15*$IV$1))),IS15*$IV$1) -> 1
A16: уголь для коксованияЭкспортЮжное | B16: 1 | C16: Уголь каменный | D16: 16104 | E16: КОНЦЕНТР УГОЛЬН | F16: уголь для коксования | G16: ЗСБ | H16: СКВ | I16: МЕЖДУРЕЧЕНСК | J16: ВЫШСТБЛ-ЭКС | K16: 4677 | L16: полувагон | M16: Экспорт | N16: неконтейнерная | O16: Южное | P16: 57775656 | Q16: ООО "КУБЕЙРА ТРЕЙДИНГ" | R16: ООО "ЕвразХолдинг" | S16: 595825 | T16: 2786924496 | U16: 8202 | W16: 1167689593 | X16: 75 | Y16: маршрутная | Z16: 11 | AA16: 12 | AB16: 4 | AC16: 2090.15 | AD16: 928.21 | AE16: =AC16+AD16 -> 3018.36 | AF16: ='Цены,перевалка,аренда'!$C$26*SUM(Уголь_эластика_экспорт!Z16+Уголь_эластика_экспорт!AA16+Уголь_эластика_экспорт!AB16)/Уголь_эластика_экспорт!X16 -> 360 | AG16: =SUMIF('Цены,перевалка,аренда'!$A$20:$A$22,Уголь_эластика_экспорт!$O16,'Цены,перевалка,аренда'!$D$20:$D$22) -> 991.9715 | AI16: 3876 | AJ16: =SUMIF('Цены,перевалка,аренда'!$A$5:$A$17,Уголь_эластика_экспорт!A16,'Цены,перевалка,аренда'!$D$5:$D$17) -> 9080.3545 | AK16: =AJ16/'Цены,перевалка,аренда'!$C$1 -> 119 | AL16: =AE16+AF16+AG16 -> 4370.3315 | AM16: =AJ16-AL16 -> 4710.023 | AN16: =AI16+AH16+AG16+AF16+AE16 -> 8246.3315 | AO16: =(AJ16-AN16)/AJ16 -> 0.091849167 | AP16: =AL16/AJ16 -> 0.48129525 | AQ16: =AE16/AJ16 -> 0.33240552 | AR16: =AE16/AL16 -> 0.69064784 | AS16: =IT16 -> 1 | AT16: =S16*AS16 -> 595825 | AU16: 1 | AV16: =(AJ16-(AE16*(1+$IS$2)+AF16+AG16+AH16+AI16))/AJ16 -> 0.058608615 | AW16: =(AE16*(1+$IS$2)+AF16+AG16)/AJ16 -> 0.5145358 | AX16: =(AE16*(1+$IS$2))/AJ16 -> 0.36564608 | AY16: =(AE16*(1+$IS$2))/(AE16*(1+$IS$2)+AF16+AG16) -> 0.71063291 | AZ16: =MIN(IF($AU16=100%,1,1+VLOOKUP(($AJ16-$AI16-$AH16-$AG16-$AF16-$AE16*(1+AZ$3))/$AJ16,Уголь_коэфф!$A:$B,2,1)-VLOOKUP($AO16,Уголь_коэфф!$A:$B,2,1)),1+(1-$AU16)) -> 1 | BA16: =MIN(IF($AU16=100%,1,1+VLOOKUP(($AJ16-$AI16-$AH16-$AG16-$AF16-$AE16*(1+BA$3))/$AJ16,Уголь_коэфф!$A:$B,2,1)-VLOOKUP($AO16,Уголь_коэфф!$A:$B,2,1)),1+(1-$AU16)) -> 1 | BB16: =MIN(IF($AU16=100%,1,1+VLOOKUP(($AJ16-$AI16-$AH16-$AG16-$AF16-$AE16*(1+BB$3))/$AJ16,Уголь_коэфф!$A:$B,2,1)-VLOOKUP($AO16,Уголь_коэфф!$A:$B,2,1)),1+(1-$AU16)) -> 1 | BC16: =MIN(IF($AU16=100%,1,1+VLOOKUP(($AJ16-$AI16-$AH16-$AG16-$AF16-$AE16*(1+BC$3))/$AJ16,Уголь_коэфф!$A:$B,2,1)-VLOOKUP($AO16,Уголь_коэфф!$A:$B,2,1)),1+(1-$AU16)) -> 1 | BD16: =MIN(IF($AU16=100%,1,1+VLOOKUP(($AJ16-$AI16-$AH16-$AG16-$AF16-$AE16*(1+BD$3))/$AJ16,Уголь_коэфф!$A:$B,2,1)-VLOOKUP($AO16,Уголь_коэфф!$A:$B,2,1)),1+(1-$AU16)) -> 1 | BE16: =MIN(IF($AU16=100%,1,1+VLOOKUP(($AJ16-$AI16-$AH16-$AG16-$AF16-$AE16*(1+BE$3))/$AJ16,Уголь_коэфф!$A:$B,2,1)-VLOOKUP($AO16,Уголь_коэфф!$A:$B,2,1)),1+(1-$AU16)) -> 1 | BF16: =MIN(IF($AU16=100%,1,1+VLOOKUP(($AJ16-$AI16-$AH16-$AG16-$AF16-$AE16*(1+BF$3))/$AJ16,Уголь_коэфф!$A:$B,2,1)-VLOOKUP($AO16,Уголь_коэфф!$A:$B,2,1)),1+(1-$AU16)) -> 1 | BG16: =MIN(IF($AU16=100%,1,1+VLOOKUP(($AJ16-$AI16-$AH16-$AG16-$AF16-$AE16*(1+BG$3))/$AJ16,Уголь_коэфф!$A:$B,2,1)-VLOOKUP($AO16,Уголь_коэфф!$A:$B,2,1)),1+(1-$AU16)) -> 1 | ... EU16: =MIN(IF($AU16=100%,1,1+VLOOKUP(($AJ16-$AI16-$AH16-$AG16-$AF16-$AE16*(1+EU$3))/$AJ16,Уголь_коэфф!$A:$B,2,1)-VLOOKUP($AO16,Уголь_коэфф!$A:$B,2,1)),1+(1-$AU16)) -> 1 | EV16: 1 | EW16: =MIN(1,MAX(VLOOKUP(($AJ16-$AI16-$AH16-$AG16-$AF16-$AE16*(1+EW$3))/$AJ16,Уголь_коэфф!$A:$B,2,1),(EV16-0.05))) -> 1 | EX16: =MIN(1,MAX(VLOOKUP(($AJ16-$AI16-$AH16-$AG16-$AF16-$AE16*(1+EX$3))/$AJ16,Уголь_коэфф!$A:$B,2,1),(EW16-0.05))) -> 1 | EY16: =MIN(1,MAX(VLOOKUP(($AJ16-$AI16-$AH16-$AG16-$AF16-$AE16*(1+EY$3))/$AJ16,Уголь_коэфф!$A:$B,2,1),(EX16-0.05))) -> 1 | EZ16: =MIN(1,MAX(VLOOKUP(($AJ16-$AI16-$AH16-$AG16-$AF16-$AE16*(1+EZ$3))/$AJ16,Уголь_коэфф!$A:$B,2,1),(EY16-0.05))) -> 1 | FA16: =MIN(1,MAX(VLOOKUP(($AJ16-$AI16-$AH16-$AG16-$AF16-$AE16*(1+FA$3))/$AJ16,Уголь_коэфф!$A:$B,2,1),(EZ16-0.05))) -> 1 | FB16: =MIN(1,MAX(VLOOKUP(($AJ16-$AI16-$AH16-$AG16-$AF16-$AE16*(1+FB$3))/$AJ16,Уголь_коэфф!$A:$B,2,1),(FA16-0.05))) -> 1 | FC16: =MIN(1,MAX(VLOOKUP(($AJ16-$AI16-$AH16-$AG16-$AF16-$AE16*(1+FC$3))/$AJ16,Уголь_коэфф!$A:$B,2,1),(FB16-0.05))) -> 1 | FD16: =MIN(1,MAX(VLOOKUP(($AJ16-$AI16-$AH16-$AG16-$AF16-$AE16*(1+FD$3))/$AJ16,Уголь_коэфф!$A:$B,2,1),(FC16-0.05))) -> 1 | ... IR16: =MIN(1,MAX(VLOOKUP(($AJ16-$AI16-$AH16-$AG16-$AF16-$AE16*(1+IR$3))/$AJ16,Уголь_коэфф!$A:$B,2,1),(IQ16-0.05))) -> 0.97 | IS16: =HLOOKUP($IS$2,$AZ$3:$IR$27,ROW(IR16)-2,FALSE) -> 1 | IT16: =IF($IV$2=1,IF(AND($IT$2="индексация",IS16<1,IS16*$IV$1>1),1,IF(AND($IT$2="индексация",IS16=1),1,IF(AND($IT$2="скидка",IS16=1),1,IS16*$IV$1))),IS16*$IV$1) -> 1
A17: антрацит (энергетический уголь)ЭкспортВосточное | B17: 1 | C17: Уголь каменный | D17: 16101 | E17: АНТРАЦИТ | F17: антрацит (энергетический уголь) | G17: ЗСБ | H17: ДВС | I17: ЕВСИНО | J17: СМОЛЯНИНОВ-Э | K17: 6011 | L17: полувагон | M17: Экспорт | N17: неконтейнерная | O17: Восточное | P17: 53037061 | Q17: ООО "СИБСЛК" | R17: ООО "Башкирский промышленный холдинг" | S17: 2022773 | T17: 12158690787 | U17: 27327 | W17: 4731039707 | X17: 75 | Y17: маршрутная | Z17: 13 | AA17: 13 | AB17: 4 | AC17: 2564.59 | AD17: 1120.57 | AE17: =AC17+AD17 -> 3685.16 | AF17: ='Цены,перевалка,аренда'!$C$26*SUM(Уголь_эластика_экспорт!Z17+Уголь_эластика_экспорт!AA17+Уголь_эластика_экспорт!AB17)/Уголь_эластика_экспорт!X17 -> 400 | AG17: =SUMIF('Цены,перевалка,аренда'!$A$20:$A$22,Уголь_эластика_экспорт!$O17,'Цены,перевалка,аренда'!$D$20:$D$22) -> 763.055 | AI17: 2771 | AJ17: =SUMIF('Цены,перевалка,аренда'!$A$5:$A$17,Уголь_эластика_экспорт!A17,'Цены,перевалка,аренда'!$D$5:$D$17) -> 10072.326 | AK17: =AJ17/'Цены,перевалка,аренда'!$C$1 -> 132 | AL17: =AE17+AF17+AG17 -> 4848.215 | AM17: =AJ17-AL17 -> 5224.111 | AN17: =AI17+AH17+AG17+AF17+AE17 -> 7619.215 | AO17: =(AJ17-AN17)/AJ17 -> 0.2435496 | AP17: =AL17/AJ17 -> 0.48134016 | AQ17: =AE17/AJ17 -> 0.36586981 | AR17: =AE17/AL17 -> 0.76010655 | AS17: =IT17 -> 1 | AT17: =S17*AS17 -> 2022773 | AU17: =12.8/13.4 -> 0.95522388 | AV17: =(AJ17-(AE17*(1+$IS$2)+AF17+AG17+AH17+AI17))/AJ17 -> 0.20696262 | AW17: =(AE17*(1+$IS$2)+AF17+AG17)/AJ17 -> 0.51792714 | AX17: =(AE17*(1+$IS$2))/AJ17 -> 0.40245679 | AY17: =(AE17*(1+$IS$2))/(AE17*(1+$IS$2)+AF17+AG17) -> 0.77705291 | AZ17: =MIN(IF($AU17=100%,1,1+VLOOKUP(($AJ17-$AI17-$AH17-$AG17-$AF17-$AE17*(1+AZ$3))/$AJ17,Уголь_коэфф!$A:$B,2,1)-VLOOKUP($AO17,Уголь_коэфф!$A:$B,2,1)),1+(1-$AU17)) -> 1.0447761 | BA17: =MIN(IF($AU17=100%,1,1+VLOOKUP(($AJ17-$AI17-$AH17-$AG17-$AF17-$AE17*(1+BA$3))/$AJ17,Уголь_коэфф!$A:$B,2,1)-VLOOKUP($AO17,Уголь_коэфф!$A:$B,2,1)),1+(1-$AU17)) -> 1.0447761 | BB17: =MIN(IF($AU17=100%,1,1+VLOOKUP(($AJ17-$AI17-$AH17-$AG17-$AF17-$AE17*(1+BB$3))/$AJ17,Уголь_коэфф!$A:$B,2,1)-VLOOKUP($AO17,Уголь_коэфф!$A:$B,2,1)),1+(1-$AU17)) -> 1.0447761 | BC17: =MIN(IF($AU17=100%,1,1+VLOOKUP(($AJ17-$AI17-$AH17-$AG17-$AF17-$AE17*(1+BC$3))/$AJ17,Уголь_коэфф!$A:$B,2,1)-VLOOKUP($AO17,Уголь_коэфф!$A:$B,2,1)),1+(1-$AU17)) -> 1.0447761 | BD17: =MIN(IF($AU17=100%,1,1+VLOOKUP(($AJ17-$AI17-$AH17-$AG17-$AF17-$AE17*(1+BD$3))/$AJ17,Уголь_коэфф!$A:$B,2,1)-VLOOKUP($AO17,Уголь_коэфф!$A:$B,2,1)),1+(1-$AU17)) -> 1.0447761 | BE17: =MIN(IF($AU17=100%,1,1+VLOOKUP(($AJ17-$AI17-$AH17-$AG17-$AF17-$AE17*(1+BE$3))/$AJ17,Уголь_коэфф!$A:$B,2,1)-VLOOKUP($AO17,Уголь_коэфф!$A:$B,2,1)),1+(1-$AU17)) -> 1.0447761 | BF17: =MIN(IF($AU17=100%,1,1+VLOOKUP(($AJ17-$AI17-$AH17-$AG17-$AF17-$AE17*(1+BF$3))/$AJ17,Уголь_коэфф!$A:$B,2,1)-VLOOKUP($AO17,Уголь_коэфф!$A:$B,2,1)),1+(1-$AU17)) -> 1.0447761 | BG17: =MIN(IF($AU17=100%,1,1+VLOOKUP(($AJ17-$AI17-$AH17-$AG17-$AF17-$AE17*(1+BG$3))/$AJ17,Уголь_коэфф!$A:$B,2,1)-VLOOKUP($AO17,Уголь_коэфф!$A:$B,2,1)),1+(1-$AU17)) -> 1.0447761 | ... EU17: =MIN(IF($AU17=100%,1,1+VLOOKUP(($AJ17-$AI17-$AH17-$AG17-$AF17-$AE17*(1+EU$3))/$AJ17,Уголь_коэфф!$A:$B,2,1)-VLOOKUP($AO17,Уголь_коэфф!$A:$B,2,1)),1+(1-$AU17)) -> 1 | EV17: 1 | EW17: =MIN(1,MAX(VLOOKUP(($AJ17-$AI17-$AH17-$AG17-$AF17-$AE17*(1+EW$3))/$AJ17,Уголь_коэфф!$A:$B,2,1),(EV17-0.05))) -> 1 | EX17: =MIN(1,MAX(VLOOKUP(($AJ17-$AI17-$AH17-$AG17-$AF17-$AE17*(1+EX$3))/$AJ17,Уголь_коэфф!$A:$B,2,1),(EW17-0.05))) -> 1 | EY17: =MIN(1,MAX(VLOOKUP(($AJ17-$AI17-$AH17-$AG17-$AF17-$AE17*(1+EY$3))/$AJ17,Уголь_коэфф!$A:$B,2,1),(EX17-0.05))) -> 1 | EZ17: =MIN(1,MAX(VLOOKUP(($AJ17-$AI17-$AH17-$AG17-$AF17-$AE17*(1+EZ$3))/$AJ17,Уголь_коэфф!$A:$B,2,1),(EY17-0.05))) -> 1 | FA17: =MIN(1,MAX(VLOOKUP(($AJ17-$AI17-$AH17-$AG17-$AF17-$AE17*(1+FA$3))/$AJ17,Уголь_коэфф!$A:$B,2,1),(EZ17-0.05))) -> 1 | FB17: =MIN(1,MAX(VLOOKUP(($AJ17-$AI17-$AH17-$AG17-$AF17-$AE17*(1+FB$3))/$AJ17,Уголь_коэфф!$A:$B,2,1),(FA17-0.05))) -> 1 | FC17: =MIN(1,MAX(VLOOKUP(($AJ17-$AI17-$AH17-$AG17-$AF17-$AE17*(1+FC$3))/$AJ17,Уголь_коэфф!$A:$B,2,1),(FB17-0.05))) -> 1 | FD17: =MIN(1,MAX(VLOOKUP(($AJ17-$AI17-$AH17-$AG17-$AF17-$AE17*(1+FD$3))/$AJ17,Уголь_коэфф!$A:$B,2,1),(FC17-0.05))) -> 1 | ... IR17: =MIN(1,MAX(VLOOKUP(($AJ17-$AI17-$AH17-$AG17-$AF17-$AE17*(1+IR$3))/$AJ17,Уголь_коэфф!$A:$B,2,1),(IQ17-0.05))) -> 1 | IS17: =HLOOKUP($IS$2,$AZ$3:$IR$27,ROW(IR17)-2,FALSE) -> 1 | IT17: =IF($IV$2=1,IF(AND($IT$2="индексация",IS17<1,IS17*$IV$1>1),1,IF(AND($IT$2="индексация",IS17=1),1,IF(AND($IT$2="скидка",IS17=1),1,IS17*$IV$1))),IS17*$IV$1) -> 1
A18: уголь энергетический (кроме антрацита)ЭкспортСеверо-Западное | B18: 1 | C18: Уголь каменный | D18: 16118 | E18: УГОЛЬ Т | F18: уголь энергетический (кроме антрацита) | G18: ЗСБ | H18: ОКТ | I18: МЫСКИ | J18: ЛУЖСКАЯ-ЭКСП | K18: 4305 | L18: полувагон | M18: Экспорт | N18: неконтейнерная | O18: Северо-Западное | P18: 53037061 | Q18: ООО "СИБСЛК" | R18: ООО "Башкирский промышленный холдинг" | S18: 1764884 | T18: 7596988312 | U18: 25207 | W18: 3294467080 | X18: 69 | Y18: маршрутная | Z18: 11 | AA18: 12 | AB18: 4 | AC18: 2093.25 | AD18: 945.01 | AE18: =AC18+AD18 -> 3038.26 | AF18: ='Цены,перевалка,аренда'!$C$27*SUM(Уголь_эластика_экспорт!Z18+Уголь_эластика_экспорт!AA18+Уголь_эластика_экспорт!AB18)/Уголь_эластика_экспорт!X18 -> 273.91304 | AG18: =SUMIF('Цены,перевалка,аренда'!$A$20:$A$22,Уголь_эластика_экспорт!$O18,'Цены,перевалка,аренда'!$D$20:$D$22) -> 610.444 | AI18: 2800 | AJ18: =SUMIF('Цены,перевалка,аренда'!$A$5:$A$17,Уголь_эластика_экспорт!A18,'Цены,перевалка,аренда'!$D$5:$D$17) -> 6485.9675 | AK18: =AJ18/'Цены,перевалка,аренда'!$C$1 -> 85 | AL18: =AE18+AF18+AG18 -> 3922.617 | AM18: =AJ18-AL18 -> 2563.3505 | AN18: =AI18+AH18+AG18+AF18+AE18 -> 6722.617 | AO18: =(AJ18-AN18)/AJ18 -> -0.036486391 | AP18: =AL18/AJ18 -> 0.60478518 | AQ18: =AE18/AJ18 -> 0.4684359 | AR18: =AE18/AL18 -> 0.77454923 | AS18: =IT18 -> 0.965 | AT18: =S18*AS18 -> 1703113.1 | AU18: =12.8/13.4 -> 0.95522388 | AV18: =(AJ18-(AE18*(1+$IS$2)+AF18+AG18+AH18+AI18))/AJ18 -> -0.08332998 | AW18: =(AE18*(1+$IS$2)+AF18+AG18)/AJ18 -> 0.65162877 | AX18: =(AE18*(1+$IS$2))/AJ18 -> 0.51527949 | AY18: =(AE18*(1+$IS$2))/(AE18*(1+$IS$2)+AF18+AG18) -> 0.79075619 | AZ18: =MIN(IF($AU18=100%,1,1+VLOOKUP(($AJ18-$AI18-$AH18-$AG18-$AF18-$AE18*(1+AZ$3))/$AJ18,Уголь_коэфф!$A:$B,2,1)-VLOOKUP($AO18,Уголь_коэфф!$A:$B,2,1)),1+(1-$AU18)) -> 1.0447761 | BA18: =MIN(IF($AU18=100%,1,1+VLOOKUP(($AJ18-$AI18-$AH18-$AG18-$AF18-$AE18*(1+BA$3))/$AJ18,Уголь_коэфф!$A:$B,2,1)-VLOOKUP($AO18,Уголь_коэфф!$A:$B,2,1)),1+(1-$AU18)) -> 1.0447761 | BB18: =MIN(IF($AU18=100%,1,1+VLOOKUP(($AJ18-$AI18-$AH18-$AG18-$AF18-$AE18*(1+BB$3))/$AJ18,Уголь_коэфф!$A:$B,2,1)-VLOOKUP($AO18,Уголь_коэфф!$A:$B,2,1)),1+(1-$AU18)) -> 1.0447761 | BC18: =MIN(IF($AU18=100%,1,1+VLOOKUP(($AJ18-$AI18-$AH18-$AG18-$AF18-$AE18*(1+BC$3))/$AJ18,Уголь_коэфф!$A:$B,2,1)-VLOOKUP($AO18,Уголь_коэфф!$A:$B,2,1)),1+(1-$AU18)) -> 1.0447761 | BD18: =MIN(IF($AU18=100%,1,1+VLOOKUP(($AJ18-$AI18-$AH18-$AG18-$AF18-$AE18*(1+BD$3))/$AJ18,Уголь_коэфф!$A:$B,2,1)-VLOOKUP($AO18,Уголь_коэфф!$A:$B,2,1)),1+(1-$AU18)) -> 1.0447761 | BE18: =MIN(IF($AU18=100%,1,1+VLOOKUP(($AJ18-$AI18-$AH18-$AG18-$AF18-$AE18*(1+BE$3))/$AJ18,Уголь_коэфф!$A:$B,2,1)-VLOOKUP($AO18,Уголь_коэфф!$A:$B,2,1)),1+(1-$AU18)) -> 1.0447761 | BF18: =MIN(IF($AU18=100%,1,1+VLOOKUP(($AJ18-$AI18-$AH18-$AG18-$AF18-$AE18*(1+BF$3))/$AJ18,Уголь_коэфф!$A:$B,2,1)-VLOOKUP($AO18,Уголь_коэфф!$A:$B,2,1)),1+(1-$AU18)) -> 1.0447761 | BG18: =MIN(IF($AU18=100%,1,1+VLOOKUP(($AJ18-$AI18-$AH18-$AG18-$AF18-$AE18*(1+BG$3))/$AJ18,Уголь_коэфф!$A:$B,2,1)-VLOOKUP($AO18,Уголь_коэфф!$A:$B,2,1)),1+(1-$AU18)) -> 1.0447761 | ... EU18: =MIN(IF($AU18=100%,1,1+VLOOKUP(($AJ18-$AI18-$AH18-$AG18-$AF18-$AE18*(1+EU$3))/$AJ18,Уголь_коэфф!$A:$B,2,1)-VLOOKUP($AO18,Уголь_коэфф!$A:$B,2,1)),1+(1-$AU18)) -> 1 | EV18: 1 | EW18: =MIN(1,MAX(VLOOKUP(($AJ18-$AI18-$AH18-$AG18-$AF18-$AE18*(1+EW$3))/$AJ18,Уголь_коэфф!$A:$B,2,1),(EV18-0.05))) -> 0.99 | EX18: =MIN(1,MAX(VLOOKUP(($AJ18-$AI18-$AH18-$AG18-$AF18-$AE18*(1+EX$3))/$AJ18,Уголь_коэфф!$A:$B,2,1),(EW18-0.05))) -> 0.985 | EY18: =MIN(1,MAX(VLOOKUP(($AJ18-$AI18-$AH18-$AG18-$AF18-$AE18*(1+EY$3))/$AJ18,Уголь_коэфф!$A:$B,2,1),(EX18-0.05))) -> 0.985 | EZ18: =MIN(1,MAX(VLOOKUP(($AJ18-$AI18-$AH18-$AG18-$AF18-$AE18*(1+EZ$3))/$AJ18,Уголь_коэфф!$A:$B,2,1),(EY18-0.05))) -> 0.985 | FA18: =MIN(1,MAX(VLOOKUP(($AJ18-$AI18-$AH18-$AG18-$AF18-$AE18*(1+FA$3))/$AJ18,Уголь_коэфф!$A:$B,2,1),(EZ18-0.05))) -> 0.985 | FB18: =MIN(1,MAX(VLOOKUP(($AJ18-$AI18-$AH18-$AG18-$AF18-$AE18*(1+FB$3))/$AJ18,Уголь_коэфф!$A:$B,2,1),(FA18-0.05))) -> 0.98 | FC18: =MIN(1,MAX(VLOOKUP(($AJ18-$AI18-$AH18-$AG18-$AF18-$AE18*(1+FC$3))/$AJ18,Уголь_коэфф!$A:$B,2,1),(FB18-0.05))) -> 0.98 | FD18: =MIN(1,MAX(VLOOKUP(($AJ18-$AI18-$AH18-$AG18-$AF18-$AE18*(1+FD$3))/$AJ18,Уголь_коэфф!$A:$B,2,1),(FC18-0.05))) -> 0.98 | ... IR18: =MIN(1,MAX(VLOOKUP(($AJ18-$AI18-$AH18-$AG18-$AF18-$AE18*(1+IR$3))/$AJ18,Уголь_коэфф!$A:$B,2,1),(IQ18-0.05))) -> 0.86 | IS18: =HLOOKUP($IS$2,$AZ$3:$IR$27,ROW(IR18)-2,FALSE) -> 0.965 | IT18: =IF($IV$2=1,IF(AND($IT$2="индексация",IS18<1,IS18*$IV$1>1),1,IF(AND($IT$2="индексация",IS18=1),1,IF(AND($IT$2="скидка",IS18=1),1,IS18*$IV$1))),IS18*$IV$1) -> 0.965
A19: уголь энергетический (кроме антрацита)ЭкспортЮжное | B19: 1 | C19: Уголь каменный | D19: 16118 | E19: УГОЛЬ Т | F19: уголь энергетический (кроме антрацита) | G19: ЗСБ | H19: СКВ | I19: МЫСКИ | J19: ВЕСЕЛОЕ-ЭКСП | K19: 4838 | L19: полувагон | M19: Экспорт | N19: неконтейнерная | O19: Южное | P19: 53037061 | Q19: ООО "СИБСЛК" | R19: ООО "Башкирский промышленный холдинг" | S19: 76356 | T19: 369416028 | U19: 1098 | W19: 153835830 | X19: 69 | Y19: маршрутная | Z19: 11 | AA19: 12 | AB19: 4 | AC19: 2247.13 | AD19: 1039.88 | AE19: =AC19+AD19 -> 3287.01 | AF19: ='Цены,перевалка,аренда'!$C$27*SUM(Уголь_эластика_экспорт!Z19+Уголь_эластика_экспорт!AA19+Уголь_эластика_экспорт!AB19)/Уголь_эластика_экспорт!X19 -> 273.91304 | AG19: =SUMIF('Цены,перевалка,аренда'!$A$20:$A$22,Уголь_эластика_экспорт!$O19,'Цены,перевалка,аренда'!$D$20:$D$22) -> 991.9715 | AI19: 2800 | AJ19: =SUMIF('Цены,перевалка,аренда'!$A$5:$A$17,Уголь_эластика_экспорт!A19,'Цены,перевалка,аренда'!$D$5:$D$17) -> 7249.0225 | AK19: =AJ19/'Цены,перевалка,аренда'!$C$1 -> 95 | AL19: =AE19+AF19+AG19 -> 4552.8945 | AM19: =AJ19-AL19 -> 2696.128 | AN19: =AI19+AH19+AG19+AF19+AE19 -> 7352.8945 | AO19: =(AJ19-AN19)/AJ19 -> -0.01432911 | AP19: =AL19/AJ19 -> 0.62807014 | AQ19: =AE19/AJ19 -> 0.45344183 | AR19: =AE19/AL19 -> 0.7219605 | AS19: =IT19 -> 0.98 | AT19: =S19*AS19 -> 74828.88 | AU19: =12.8/13.4 -> 0.95522388 | AV19: =(AJ19-(AE19*(1+$IS$2)+AF19+AG19+AH19+AI19))/AJ19 -> -0.059673293 | AW19: =(AE19*(1+$IS$2)+AF19+AG19)/AJ19 -> 0.67341432 | AX19: =(AE19*(1+$IS$2))/AJ19 -> 0.49878601 | AY19: =(AE19*(1+$IS$2))/(AE19*(1+$IS$2)+AF19+AG19) -> 0.74068222 | AZ19: =MIN(IF($AU19=100%,1,1+VLOOKUP(($AJ19-$AI19-$AH19-$AG19-$AF19-$AE19*(1+AZ$3))/$AJ19,Уголь_коэфф!$A:$B,2,1)-VLOOKUP($AO19,Уголь_коэфф!$A:$B,2,1)),1+(1-$AU19)) -> 1.0447761 | BA19: =MIN(IF($AU19=100%,1,1+VLOOKUP(($AJ19-$AI19-$AH19-$AG19-$AF19-$AE19*(1+BA$3))/$AJ19,Уголь_коэфф!$A:$B,2,1)-VLOOKUP($AO19,Уголь_коэфф!$A:$B,2,1)),1+(1-$AU19)) -> 1.0447761 | BB19: =MIN(IF($AU19=100%,1,1+VLOOKUP(($AJ19-$AI19-$AH19-$AG19-$AF19-$AE19*(1+BB$3))/$AJ19,Уголь_коэфф!$A:$B,2,1)-VLOOKUP($AO19,Уголь_коэфф!$A:$B,2,1)),1+(1-$AU19)) -> 1.0447761 | BC19: =MIN(IF($AU19=100%,1,1+VLOOKUP(($AJ19-$AI19-$AH19-$AG19-$AF19-$AE19*(1+BC$3))/$AJ19,Уголь_коэфф!$A:$B,2,1)-VLOOKUP($AO19,Уголь_коэфф!$A:$B,2,1)),1+(1-$AU19)) -> 1.0447761 | BD19: =MIN(IF($AU19=100%,1,1+VLOOKUP(($AJ19-$AI19-$AH19-$AG19-$AF19-$AE19*(1+BD$3))/$AJ19,Уголь_коэфф!$A:$B,2,1)-VLOOKUP($AO19,Уголь_коэфф!$A:$B,2,1)),1+(1-$AU19)) -> 1.0447761 | BE19: =MIN(IF($AU19=100%,1,1+VLOOKUP(($AJ19-$AI19-$AH19-$AG19-$AF19-$AE19*(1+BE$3))/$AJ19,Уголь_коэфф!$A:$B,2,1)-VLOOKUP($AO19,Уголь_коэфф!$A:$B,2,1)),1+(1-$AU19)) -> 1.0447761 | BF19: =MIN(IF($AU19=100%,1,1+VLOOKUP(($AJ19-$AI19-$AH19-$AG19-$AF19-$AE19*(1+BF$3))/$AJ19,Уголь_коэфф!$A:$B,2,1)-VLOOKUP($AO19,Уголь_коэфф!$A:$B,2,1)),1+(1-$AU19)) -> 1.0447761 | BG19: =MIN(IF($AU19=100%,1,1+VLOOKUP(($AJ19-$AI19-$AH19-$AG19-$AF19-$AE19*(1+BG$3))/$AJ19,Уголь_коэфф!$A:$B,2,1)-VLOOKUP($AO19,Уголь_коэфф!$A:$B,2,1)),1+(1-$AU19)) -> 1.0447761 | ... EU19: =MIN(IF($AU19=100%,1,1+VLOOKUP(($AJ19-$AI19-$AH19-$AG19-$AF19-$AE19*(1+EU$3))/$AJ19,Уголь_коэфф!$A:$B,2,1)-VLOOKUP($AO19,Уголь_коэфф!$A:$B,2,1)),1+(1-$AU19)) -> 1 | EV19: 1 | EW19: =MIN(1,MAX(VLOOKUP(($AJ19-$AI19-$AH19-$AG19-$AF19-$AE19*(1+EW$3))/$AJ19,Уголь_коэфф!$A:$B,2,1),(EV19-0.05))) -> 1 | EX19: =MIN(1,MAX(VLOOKUP(($AJ19-$AI19-$AH19-$AG19-$AF19-$AE19*(1+EX$3))/$AJ19,Уголь_коэфф!$A:$B,2,1),(EW19-0.05))) -> 1 | EY19: =MIN(1,MAX(VLOOKUP(($AJ19-$AI19-$AH19-$AG19-$AF19-$AE19*(1+EY$3))/$AJ19,Уголь_коэфф!$A:$B,2,1),(EX19-0.05))) -> 0.995 | EZ19: =MIN(1,MAX(VLOOKUP(($AJ19-$AI19-$AH19-$AG19-$AF19-$AE19*(1+EZ$3))/$AJ19,Уголь_коэфф!$A:$B,2,1),(EY19-0.05))) -> 0.995 | FA19: =MIN(1,MAX(VLOOKUP(($AJ19-$AI19-$AH19-$AG19-$AF19-$AE19*(1+FA$3))/$AJ19,Уголь_коэфф!$A:$B,2,1),(EZ19-0.05))) -> 0.995 | FB19: =MIN(1,MAX(VLOOKUP(($AJ19-$AI19-$AH19-$AG19-$AF19-$AE19*(1+FB$3))/$AJ19,Уголь_коэфф!$A:$B,2,1),(FA19-0.05))) -> 0.995 | FC19: =MIN(1,MAX(VLOOKUP(($AJ19-$AI19-$AH19-$AG19-$AF19-$AE19*(1+FC$3))/$AJ19,Уголь_коэфф!$A:$B,2,1),(FB19-0.05))) -> 0.99 | FD19: =MIN(1,MAX(VLOOKUP(($AJ19-$AI19-$AH19-$AG19-$AF19-$AE19*(1+FD$3))/$AJ19,Уголь_коэфф!$A:$B,2,1),(FC19-0.05))) -> 0.99 | ... IR19: =MIN(1,MAX(VLOOKUP(($AJ19-$AI19-$AH19-$AG19-$AF19-$AE19*(1+IR$3))/$AJ19,Уголь_коэфф!$A:$B,2,1),(IQ19-0.05))) -> 0.878 | IS19: =HLOOKUP($IS$2,$AZ$3:$IR$27,ROW(IR19)-2,FALSE) -> 0.98 | IT19: =IF($IV$2=1,IF(AND($IT$2="индексация",IS19<1,IS19*$IV$1>1),1,IF(AND($IT$2="индексация",IS19=1),1,IF(AND($IT$2="скидка",IS19=1),1,IS19*$IV$1))),IS19*$IV$1) -> 0.98
A20: уголь энергетический (кроме антрацита)ЭкспортВосточное | B20: 1 | C20: Уголь каменный | D20: 16112 | E20: УГОЛЬ Д | F20: уголь энергетический (кроме антрацита) | G20: ВСБ | H20: ИФР | I20: КАСЬЯНОВКА | J20: МИХ-СЕМ-Э | K20: 3414 | L20: полувагон | M20: Экспорт | N20: неконтейнерная | O20: Восточное | P20: 55565060 | Q20: ООО "ЭН+ УГОЛЬ" | R20: ООО "Компания "Востсибуголь" | S20: 49324 | T20: 168392405 | U20: 709 | W20: 108707726 | X20: 69 | Y20: группа вагонов | Z20: 14 | AA20: 14 | AB20: 4 | AC20: 1941.75 | AD20: 866.41 | AE20: =AC20+AD20 -> 2808.16 | AF20: ='Цены,перевалка,аренда'!$C$27*SUM(Уголь_эластика_экспорт!Z20+Уголь_эластика_экспорт!AA20+Уголь_эластика_экспорт!AB20)/Уголь_эластика_экспорт!X20 -> 324.63768 | AI20: 1637 | AJ20: =SUMIF('Цены,перевалка,аренда'!$A$5:$A$17,Уголь_эластика_экспорт!A20,'Цены,перевалка,аренда'!$D$5:$D$17) -> 8546.216 | AK20: =AJ20/'Цены,перевалка,аренда'!$C$1 -> 112 | AL20: =AE20+AF20+AG20 -> 3132.7977 | AM20: =AJ20-AL20 -> 5413.4183 | AN20: =AI20+AH20+AG20+AF20+AE20 -> 4769.7977 | AO20: =(AJ20-AN20)/AJ20 -> 0.44188192 | AP20: =AL20/AJ20 -> 0.36657132 | AQ20: =AE20/AJ20 -> 0.32858519 | AR20: =AE20/AL20 -> 0.89637451 | AS20: =IT20 -> 1 | AT20: =S20*AS20 -> 49324 | AU20: =16/17 -> 0.94117647 | AV20: =(AJ20-(AE20*(1+$IS$2)+AF20+AG20+AH20+AI20))/AJ20 -> 0.4090234 | AW20: =(AE20*(1+$IS$2)+AF20+AG20)/AJ20 -> 0.39942984 | AX20: =(AE20*(1+$IS$2))/AJ20 -> 0.36144371 | AY20: =(AE20*(1+$IS$2))/(AE20*(1+$IS$2)+AF20+AG20) -> 0.90489912 | AZ20: =MIN(IF($AU20=100%,1,1+VLOOKUP(($AJ20-$AI20-$AH20-$AG20-$AF20-$AE20*(1+AZ$3))/$AJ20,Уголь_коэфф!$A:$B,2,1)-VLOOKUP($AO20,Уголь_коэфф!$A:$B,2,1)),1+(1-$AU20)) -> 1.056 | BA20: =MIN(IF($AU20=100%,1,1+VLOOKUP(($AJ20-$AI20-$AH20-$AG20-$AF20-$AE20*(1+BA$3))/$AJ20,Уголь_коэфф!$A:$B,2,1)-VLOOKUP($AO20,Уголь_коэфф!$A:$B,2,1)),1+(1-$AU20)) -> 1.056 | BB20: =MIN(IF($AU20=100%,1,1+VLOOKUP(($AJ20-$AI20-$AH20-$AG20-$AF20-$AE20*(1+BB$3))/$AJ20,Уголь_коэфф!$A:$B,2,1)-VLOOKUP($AO20,Уголь_коэфф!$A:$B,2,1)),1+(1-$AU20)) -> 1.056 | BC20: =MIN(IF($AU20=100%,1,1+VLOOKUP(($AJ20-$AI20-$AH20-$AG20-$AF20-$AE20*(1+BC$3))/$AJ20,Уголь_коэфф!$A:$B,2,1)-VLOOKUP($AO20,Уголь_коэфф!$A:$B,2,1)),1+(1-$AU20)) -> 1.056 | BD20: =MIN(IF($AU20=100%,1,1+VLOOKUP(($AJ20-$AI20-$AH20-$AG20-$AF20-$AE20*(1+BD$3))/$AJ20,Уголь_коэфф!$A:$B,2,1)-VLOOKUP($AO20,Уголь_коэфф!$A:$B,2,1)),1+(1-$AU20)) -> 1.056 | BE20: =MIN(IF($AU20=100%,1,1+VLOOKUP(($AJ20-$AI20-$AH20-$AG20-$AF20-$AE20*(1+BE$3))/$AJ20,Уголь_коэфф!$A:$B,2,1)-VLOOKUP($AO20,Уголь_коэфф!$A:$B,2,1)),1+(1-$AU20)) -> 1.056 | BF20: =MIN(IF($AU20=100%,1,1+VLOOKUP(($AJ20-$AI20-$AH20-$AG20-$AF20-$AE20*(1+BF$3))/$AJ20,Уголь_коэфф!$A:$B,2,1)-VLOOKUP($AO20,Уголь_коэфф!$A:$B,2,1)),1+(1-$AU20)) -> 1.056 | BG20: =MIN(IF($AU20=100%,1,1+VLOOKUP(($AJ20-$AI20-$AH20-$AG20-$AF20-$AE20*(1+BG$3))/$AJ20,Уголь_коэфф!$A:$B,2,1)-VLOOKUP($AO20,Уголь_коэфф!$A:$B,2,1)),1+(1-$AU20)) -> 1.056 | ... EU20: =MIN(IF($AU20=100%,1,1+VLOOKUP(($AJ20-$AI20-$AH20-$AG20-$AF20-$AE20*(1+EU$3))/$AJ20,Уголь_коэфф!$A:$B,2,1)-VLOOKUP($AO20,Уголь_коэфф!$A:$B,2,1)),1+(1-$AU20)) -> 1 | EV20: 1 | EW20: =MIN(1,MAX(VLOOKUP(($AJ20-$AI20-$AH20-$AG20-$AF20-$AE20*(1+EW$3))/$AJ20,Уголь_коэфф!$A:$B,2,1),(EV20-0.05))) -> 1 | EX20: =MIN(1,MAX(VLOOKUP(($AJ20-$AI20-$AH20-$AG20-$AF20-$AE20*(1+EX$3))/$AJ20,Уголь_коэфф!$A:$B,2,1),(EW20-0.05))) -> 1 | EY20: =MIN(1,MAX(VLOOKUP(($AJ20-$AI20-$AH20-$AG20-$AF20-$AE20*(1+EY$3))/$AJ20,Уголь_коэфф!$A:$B,2,1),(EX20-0.05))) -> 1 | EZ20: =MIN(1,MAX(VLOOKUP(($AJ20-$AI20-$AH20-$AG20-$AF20-$AE20*(1+EZ$3))/$AJ20,Уголь_коэфф!$A:$B,2,1),(EY20-0.05))) -> 1 | FA20: =MIN(1,MAX(VLOOKUP(($AJ20-$AI20-$AH20-$AG20-$AF20-$AE20*(1+FA$3))/$AJ20,Уголь_коэфф!$A:$B,2,1),(EZ20-0.05))) -> 1 | FB20: =MIN(1,MAX(VLOOKUP(($AJ20-$AI20-$AH20-$AG20-$AF20-$AE20*(1+FB$3))/$AJ20,Уголь_коэфф!$A:$B,2,1),(FA20-0.05))) -> 1 | FC20: =MIN(1,MAX(VLOOKUP(($AJ20-$AI20-$AH20-$AG20-$AF20-$AE20*(1+FC$3))/$AJ20,Уголь_коэфф!$A:$B,2,1),(FB20-0.05))) -> 1 | FD20: =MIN(1,MAX(VLOOKUP(($AJ20-$AI20-$AH20-$AG20-$AF20-$AE20*(1+FD$3))/$AJ20,Уголь_коэфф!$A:$B,2,1),(FC20-0.05))) -> 1 | ... IR20: =MIN(1,MAX(VLOOKUP(($AJ20-$AI20-$AH20-$AG20-$AF20-$AE20*(1+IR$3))/$AJ20,Уголь_коэфф!$A:$B,2,1),(IQ20-0.05))) -> 1 | IS20: =HLOOKUP($IS$2,$AZ$3:$IR$27,ROW(IR20)-2,FALSE) -> 1 | IT20: =IF($IV$2=1,IF(AND($IT$2="индексация",IS20<1,IS20*$IV$1>1),1,IF(AND($IT$2="индексация",IS20=1),1,IF(AND($IT$2="скидка",IS20=1),1,IS20*$IV$1))),IS20*$IV$1) -> 1
A21: уголь энергетический (кроме антрацита)ЭкспортВосточное | B21: 1 | C21: Уголь каменный | D21: 16118 | E21: УГОЛЬ Т | F21: уголь энергетический (кроме антрацита) | G21: ЗСБ | H21: ДВС | I21: СПИЧЕНКОВО | J21: ДЮАНКА-Э | K21: 5804 | L21: полувагон | M21: Экспорт | N21: неконтейнерная | O21: Восточное | P21: 160212 | Q21: АО "ЦЕНТРАЛЬНОЕ" | R21: АО "Стройсервис" | S21: 1133165 | T21: 6576368768 | U21: 15452 | W21: 2258203125 | X21: 75 | Y21: маршрутная | Z21: 12 | AA21: 13 | AB21: 4 | AC21: 2152.64 | AD21: 1013.71 | AE21: =AC21+AD21 -> 3166.35 | AF21: ='Цены,перевалка,аренда'!$C$26*SUM(Уголь_эластика_экспорт!Z21+Уголь_эластика_экспорт!AA21+Уголь_эластика_экспорт!AB21)/Уголь_эластика_экспорт!X21 -> 386.66667 | AG21: =SUMIF('Цены,перевалка,аренда'!$A$20:$A$22,Уголь_эластика_экспорт!$O21,'Цены,перевалка,аренда'!$D$20:$D$22) -> 763.055 | AI21: 4817 | AJ21: =SUMIF('Цены,перевалка,аренда'!$A$5:$A$17,Уголь_эластика_экспорт!A21,'Цены,перевалка,аренда'!$D$5:$D$17) -> 8546.216 | AK21: =AJ21/'Цены,перевалка,аренда'!$C$1 -> 112 | AL21: =AE21+AF21+AG21 -> 4316.0717 | AM21: =AJ21-AL21 -> 4230.1443 | AN21: =AI21+AH21+AG21+AF21+AE21 -> 9133.0717 | AO21: =(AJ21-AN21)/AJ21 -> -0.06866848 | AP21: =AL21/AJ21 -> 0.50502722 | AQ21: =AE21/AJ21 -> 0.37049731 | AR21: =AE21/AL21 -> 0.73361849 | AS21: =IT21 -> 0.955 | AT21: =S21*AS21 -> 1082172.6 | AU21: =15/17 -> 0.88235294 | AV21: =(AJ21-(AE21*(1+$IS$2)+AF21+AG21+AH21+AI21))/AJ21 -> -0.10571821 | AW21: =(AE21*(1+$IS$2)+AF21+AG21)/AJ21 -> 0.54207695 | AX21: =(AE21*(1+$IS$2))/AJ21 -> 0.40754704 | AY21: =(AE21*(1+$IS$2))/(AE21*(1+$IS$2)+AF21+AG21) -> 0.75182507 | AZ21: =MIN(IF($AU21=100%,1,1+VLOOKUP(($AJ21-$AI21-$AH21-$AG21-$AF21-$AE21*(1+AZ$3))/$AJ21,Уголь_коэфф!$A:$B,2,1)-VLOOKUP($AO21,Уголь_коэфф!$A:$B,2,1)),1+(1-$AU21)) -> 1.07 | BA21: =MIN(IF($AU21=100%,1,1+VLOOKUP(($AJ21-$AI21-$AH21-$AG21-$AF21-$AE21*(1+BA$3))/$AJ21,Уголь_коэфф!$A:$B,2,1)-VLOOKUP($AO21,Уголь_коэфф!$A:$B,2,1)),1+(1-$AU21)) -> 1.07 | BB21: =MIN(IF($AU21=100%,1,1+VLOOKUP(($AJ21-$AI21-$AH21-$AG21-$AF21-$AE21*(1+BB$3))/$AJ21,Уголь_коэфф!$A:$B,2,1)-VLOOKUP($AO21,Уголь_коэфф!$A:$B,2,1)),1+(1-$AU21)) -> 1.07 | BC21: =MIN(IF($AU21=100%,1,1+VLOOKUP(($AJ21-$AI21-$AH21-$AG21-$AF21-$AE21*(1+BC$3))/$AJ21,Уголь_коэфф!$A:$B,2,1)-VLOOKUP($AO21,Уголь_коэфф!$A:$B,2,1)),1+(1-$AU21)) -> 1.07 | BD21: =MIN(IF($AU21=100%,1,1+VLOOKUP(($AJ21-$AI21-$AH21-$AG21-$AF21-$AE21*(1+BD$3))/$AJ21,Уголь_коэфф!$A:$B,2,1)-VLOOKUP($AO21,Уголь_коэфф!$A:$B,2,1)),1+(1-$AU21)) -> 1.065 | BE21: =MIN(IF($AU21=100%,1,1+VLOOKUP(($AJ21-$AI21-$AH21-$AG21-$AF21-$AE21*(1+BE$3))/$AJ21,Уголь_коэфф!$A:$B,2,1)-VLOOKUP($AO21,Уголь_коэфф!$A:$B,2,1)),1+(1-$AU21)) -> 1.065 | BF21: =MIN(IF($AU21=100%,1,1+VLOOKUP(($AJ21-$AI21-$AH21-$AG21-$AF21-$AE21*(1+BF$3))/$AJ21,Уголь_коэфф!$A:$B,2,1)-VLOOKUP($AO21,Уголь_коэфф!$A:$B,2,1)),1+(1-$AU21)) -> 1.065 | BG21: =MIN(IF($AU21=100%,1,1+VLOOKUP(($AJ21-$AI21-$AH21-$AG21-$AF21-$AE21*(1+BG$3))/$AJ21,Уголь_коэфф!$A:$B,2,1)-VLOOKUP($AO21,Уголь_коэфф!$A:$B,2,1)),1+(1-$AU21)) -> 1.065 | ... EU21: =MIN(IF($AU21=100%,1,1+VLOOKUP(($AJ21-$AI21-$AH21-$AG21-$AF21-$AE21*(1+EU$3))/$AJ21,Уголь_коэфф!$A:$B,2,1)-VLOOKUP($AO21,Уголь_коэфф!$A:$B,2,1)),1+(1-$AU21)) -> 1 | EV21: 1 | EW21: =MIN(1,MAX(VLOOKUP(($AJ21-$AI21-$AH21-$AG21-$AF21-$AE21*(1+EW$3))/$AJ21,Уголь_коэфф!$A:$B,2,1),(EV21-0.05))) -> 0.97 | EX21: =MIN(1,MAX(VLOOKUP(($AJ21-$AI21-$AH21-$AG21-$AF21-$AE21*(1+EX$3))/$AJ21,Уголь_коэфф!$A:$B,2,1),(EW21-0.05))) -> 0.97 | EY21: =MIN(1,MAX(VLOOKUP(($AJ21-$AI21-$AH21-$AG21-$AF21-$AE21*(1+EY$3))/$AJ21,Уголь_коэфф!$A:$B,2,1),(EX21-0.05))) -> 0.97 | EZ21: =MIN(1,MAX(VLOOKUP(($AJ21-$AI21-$AH21-$AG21-$AF21-$AE21*(1+EZ$3))/$AJ21,Уголь_коэфф!$A:$B,2,1),(EY21-0.05))) -> 0.97 | FA21: =MIN(1,MAX(VLOOKUP(($AJ21-$AI21-$AH21-$AG21-$AF21-$AE21*(1+FA$3))/$AJ21,Уголь_коэфф!$A:$B,2,1),(EZ21-0.05))) -> 0.97 | FB21: =MIN(1,MAX(VLOOKUP(($AJ21-$AI21-$AH21-$AG21-$AF21-$AE21*(1+FB$3))/$AJ21,Уголь_коэфф!$A:$B,2,1),(FA21-0.05))) -> 0.97 | FC21: =MIN(1,MAX(VLOOKUP(($AJ21-$AI21-$AH21-$AG21-$AF21-$AE21*(1+FC$3))/$AJ21,Уголь_коэфф!$A:$B,2,1),(FB21-0.05))) -> 0.965 | FD21: =MIN(1,MAX(VLOOKUP(($AJ21-$AI21-$AH21-$AG21-$AF21-$AE21*(1+FD$3))/$AJ21,Уголь_коэфф!$A:$B,2,1),(FC21-0.05))) -> 0.965 | ... IR21: =MIN(1,MAX(VLOOKUP(($AJ21-$AI21-$AH21-$AG21-$AF21-$AE21*(1+IR$3))/$AJ21,Уголь_коэфф!$A:$B,2,1),(IQ21-0.05))) -> 0.872 | IS21: =HLOOKUP($IS$2,$AZ$3:$IR$27,ROW(IR21)-2,FALSE) -> 0.955 | IT21: =IF($IV$2=1,IF(AND($IT$2="индексация",IS21<1,IS21*$IV$1>1),1,IF(AND($IT$2="индексация",IS21=1),1,IF(AND($IT$2="скидка",IS21=1),1,IS21*$IV$1))),IS21*$IV$1) -> 0.955
A22: уголь энергетический (кроме антрацита)ЭкспортСеверо-Западное | B22: 1 | C22: Уголь каменный | D22: 16118 | E22: УГОЛЬ Т | F22: уголь энергетический (кроме антрацита) | G22: ЗСБ | H22: ОКТ | I22: СПИЧЕНКОВО | J22: ЛУЖСКАЯ-ЭКСП | K22: 4233 | L22: полувагон | M22: Экспорт | N22: неконтейнерная | O22: Северо-Западное | P22: 160212 | Q22: АО "ЦЕНТРАЛЬНОЕ" | R22: АО "Стройсервис" | S22: 593128 | T22: 2511003743 | U22: 8372 | W22: 1086193757 | X22: 75 | Y22: маршрутная | Z22: 11 | AA22: 12 | AB22: 4 | AC22: 1894.65 | AD22: 869.42 | AE22: =AC22+AD22 -> 2764.07 | AF22: ='Цены,перевалка,аренда'!$C$26*SUM(Уголь_эластика_экспорт!Z22+Уголь_эластика_экспорт!AA22+Уголь_эластика_экспорт!AB22)/Уголь_эластика_экспорт!X22 -> 360 | AG22: =SUMIF('Цены,перевалка,аренда'!$A$20:$A$22,Уголь_эластика_экспорт!$O22,'Цены,перевалка,аренда'!$D$20:$D$22) -> 610.444 | AI22: 4817 | AJ22: =SUMIF('Цены,перевалка,аренда'!$A$5:$A$17,Уголь_эластика_экспорт!A22,'Цены,перевалка,аренда'!$D$5:$D$17) -> 6485.9675 | AK22: =AJ22/'Цены,перевалка,аренда'!$C$1 -> 85 | AL22: =AE22+AF22+AG22 -> 3734.514 | AM22: =AJ22-AL22 -> 2751.4535 | AN22: =AI22+AH22+AG22+AF22+AE22 -> 8551.514 | AO22: =(AJ22-AN22)/AJ22 -> -0.3184639 | AP22: =AL22/AJ22 -> 0.57578364 | AQ22: =AE22/AJ22 -> 0.42616156 | AR22: =AE22/AL22 -> 0.74014182 | AS22: =IT22 -> 0.801 | AT22: =S22*AS22 -> 475095.53 | AU22: =15/17 -> 0.88235294 | AV22: =(AJ22-(AE22*(1+$IS$2)+AF22+AG22+AH22+AI22))/AJ22 -> -0.36108005 | AW22: =(AE22*(1+$IS$2)+AF22+AG22)/AJ22 -> 0.6183998 | AX22: =(AE22*(1+$IS$2))/AJ22 -> 0.46877771 | AY22: =(AE22*(1+$IS$2))/(AE22*(1+$IS$2)+AF22+AG22) -> 0.75804959 | AZ22: =MIN(IF($AU22=100%,1,1+VLOOKUP(($AJ22-$AI22-$AH22-$AG22-$AF22-$AE22*(1+AZ$3))/$AJ22,Уголь_коэфф!$A:$B,2,1)-VLOOKUP($AO22,Уголь_коэфф!$A:$B,2,1)),1+(1-$AU22)) -> 1.1176471 | BA22: =MIN(IF($AU22=100%,1,1+VLOOKUP(($AJ22-$AI22-$AH22-$AG22-$AF22-$AE22*(1+BA$3))/$AJ22,Уголь_коэфф!$A:$B,2,1)-VLOOKUP($AO22,Уголь_коэфф!$A:$B,2,1)),1+(1-$AU22)) -> 1.1176471 | BB22: =MIN(IF($AU22=100%,1,1+VLOOKUP(($AJ22-$AI22-$AH22-$AG22-$AF22-$AE22*(1+BB$3))/$AJ22,Уголь_коэфф!$A:$B,2,1)-VLOOKUP($AO22,Уголь_коэфф!$A:$B,2,1)),1+(1-$AU22)) -> 1.1176471 | BC22: =MIN(IF($AU22=100%,1,1+VLOOKUP(($AJ22-$AI22-$AH22-$AG22-$AF22-$AE22*(1+BC$3))/$AJ22,Уголь_коэфф!$A:$B,2,1)-VLOOKUP($AO22,Уголь_коэфф!$A:$B,2,1)),1+(1-$AU22)) -> 1.114 | BD22: =MIN(IF($AU22=100%,1,1+VLOOKUP(($AJ22-$AI22-$AH22-$AG22-$AF22-$AE22*(1+BD$3))/$AJ22,Уголь_коэфф!$A:$B,2,1)-VLOOKUP($AO22,Уголь_коэфф!$A:$B,2,1)),1+(1-$AU22)) -> 1.114 | BE22: =MIN(IF($AU22=100%,1,1+VLOOKUP(($AJ22-$AI22-$AH22-$AG22-$AF22-$AE22*(1+BE$3))/$AJ22,Уголь_коэфф!$A:$B,2,1)-VLOOKUP($AO22,Уголь_коэфф!$A:$B,2,1)),1+(1-$AU22)) -> 1.114 | BF22: =MIN(IF($AU22=100%,1,1+VLOOKUP(($AJ22-$AI22-$AH22-$AG22-$AF22-$AE22*(1+BF$3))/$AJ22,Уголь_коэфф!$A:$B,2,1)-VLOOKUP($AO22,Уголь_коэфф!$A:$B,2,1)),1+(1-$AU22)) -> 1.114 | BG22: =MIN(IF($AU22=100%,1,1+VLOOKUP(($AJ22-$AI22-$AH22-$AG22-$AF22-$AE22*(1+BG$3))/$AJ22,Уголь_коэфф!$A:$B,2,1)-VLOOKUP($AO22,Уголь_коэфф!$A:$B,2,1)),1+(1-$AU22)) -> 1.109 | ... EU22: =MIN(IF($AU22=100%,1,1+VLOOKUP(($AJ22-$AI22-$AH22-$AG22-$AF22-$AE22*(1+EU$3))/$AJ22,Уголь_коэфф!$A:$B,2,1)-VLOOKUP($AO22,Уголь_коэфф!$A:$B,2,1)),1+(1-$AU22)) -> 1 | EV22: 1 | EW22: =MIN(1,MAX(VLOOKUP(($AJ22-$AI22-$AH22-$AG22-$AF22-$AE22*(1+EW$3))/$AJ22,Уголь_коэфф!$A:$B,2,1),(EV22-0.05))) -> 0.95 | EX22: =MIN(1,MAX(VLOOKUP(($AJ22-$AI22-$AH22-$AG22-$AF22-$AE22*(1+EX$3))/$AJ22,Уголь_коэфф!$A:$B,2,1),(EW22-0.05))) -> 0.9 | EY22: =MIN(1,MAX(VLOOKUP(($AJ22-$AI22-$AH22-$AG22-$AF22-$AE22*(1+EY$3))/$AJ22,Уголь_коэфф!$A:$B,2,1),(EX22-0.05))) -> 0.85 | EZ22: =MIN(1,MAX(VLOOKUP(($AJ22-$AI22-$AH22-$AG22-$AF22-$AE22*(1+EZ$3))/$AJ22,Уголь_коэфф!$A:$B,2,1),(EY22-0.05))) -> 0.829 | FA22: =MIN(1,MAX(VLOOKUP(($AJ22-$AI22-$AH22-$AG22-$AF22-$AE22*(1+FA$3))/$AJ22,Уголь_коэфф!$A:$B,2,1),(EZ22-0.05))) -> 0.829 | FB22: =MIN(1,MAX(VLOOKUP(($AJ22-$AI22-$AH22-$AG22-$AF22-$AE22*(1+FB$3))/$AJ22,Уголь_коэфф!$A:$B,2,1),(FA22-0.05))) -> 0.822 | FC22: =MIN(1,MAX(VLOOKUP(($AJ22-$AI22-$AH22-$AG22-$AF22-$AE22*(1+FC$3))/$AJ22,Уголь_коэфф!$A:$B,2,1),(FB22-0.05))) -> 0.822 | FD22: =MIN(1,MAX(VLOOKUP(($AJ22-$AI22-$AH22-$AG22-$AF22-$AE22*(1+FD$3))/$AJ22,Уголь_коэфф!$A:$B,2,1),(FC22-0.05))) -> 0.822 | ... IR22: =MIN(1,MAX(VLOOKUP(($AJ22-$AI22-$AH22-$AG22-$AF22-$AE22*(1+IR$3))/$AJ22,Уголь_коэфф!$A:$B,2,1),(IQ22-0.05))) -> 0.671 | IS22: =HLOOKUP($IS$2,$AZ$3:$IR$27,ROW(IR22)-2,FALSE) -> 0.801 | IT22: =IF($IV$2=1,IF(AND($IT$2="индексация",IS22<1,IS22*$IV$1>1),1,IF(AND($IT$2="индексация",IS22=1),1,IF(AND($IT$2="скидка",IS22=1),1,IS22*$IV$1))),IS22*$IV$1) -> 0.801
A23: уголь энергетический (кроме антрацита)ЭкспортЮжное | B23: 1 | C23: Уголь каменный | D23: 16118 | E23: УГОЛЬ Т | F23: уголь энергетический (кроме антрацита) | G23: ЗСБ | H23: СКВ | I23: СПИЧЕНКОВО | J23: КАВКАЗ-ЭКСП | K23: 4645 | L23: полувагон | M23: Экспорт | N23: неконтейнерная | O23: Южное | P23: 160212 | Q23: АО "ЦЕНТРАЛЬНОЕ" | R23: АО "Стройсервис" | S23: 37568 | T23: 174501639 | U23: 543 | W23: 74433738 | X23: 75 | Y23: маршрутная | Z23: 11 | AA23: 12 | AB23: 4 | AC23: 1990.61 | AD23: 928.22 | AE23: =AC23+AD23 -> 2918.83 | AF23: ='Цены,перевалка,аренда'!$C$26*SUM(Уголь_эластика_экспорт!Z23+Уголь_эластика_экспорт!AA23+Уголь_эластика_экспорт!AB23)/Уголь_эластика_экспорт!X23 -> 360 | AG23: =SUMIF('Цены,перевалка,аренда'!$A$20:$A$22,Уголь_эластика_экспорт!$O23,'Цены,перевалка,аренда'!$D$20:$D$22) -> 991.9715 | AI23: 4817 | AJ23: =SUMIF('Цены,перевалка,аренда'!$A$5:$A$17,Уголь_эластика_экспорт!A23,'Цены,перевалка,аренда'!$D$5:$D$17) -> 7249.0225 | AK23: =AJ23/'Цены,перевалка,аренда'!$C$1 -> 95 | AL23: =AE23+AF23+AG23 -> 4270.8015 | AM23: =AJ23-AL23 -> 2978.221 | AN23: =AI23+AH23+AG23+AF23+AE23 -> 9087.8015 | AO23: =(AJ23-AN23)/AJ23 -> -0.25365889 | AP23: =AL23/AJ23 -> 0.5891555 | AQ23: =AE23/AJ23 -> 0.40265153 | AR23: =AE23/AL23 -> 0.68343846 | AS23: =IT23 -> 0.848 | AT23: =S23*AS23 -> 31857.664 | AU23: =15/17 -> 0.88235294 | AV23: =(AJ23-(AE23*(1+$IS$2)+AF23+AG23+AH23+AI23))/AJ23 -> -0.29392404 | AW23: =(AE23*(1+$IS$2)+AF23+AG23)/AJ23 -> 0.62942066 | AX23: =(AE23*(1+$IS$2))/AJ23 -> 0.44291668 | AY23: =(AE23*(1+$IS$2))/(AE23*(1+$IS$2)+AF23+AG23) -> 0.70368946 | AZ23: =MIN(IF($AU23=100%,1,1+VLOOKUP(($AJ23-$AI23-$AH23-$AG23-$AF23-$AE23*(1+AZ$3))/$AJ23,Уголь_коэфф!$A:$B,2,1)-VLOOKUP($AO23,Уголь_коэфф!$A:$B,2,1)),1+(1-$AU23)) -> 1.108 | BA23: =MIN(IF($AU23=100%,1,1+VLOOKUP(($AJ23-$AI23-$AH23-$AG23-$AF23-$AE23*(1+BA$3))/$AJ23,Уголь_коэфф!$A:$B,2,1)-VLOOKUP($AO23,Уголь_коэфф!$A:$B,2,1)),1+(1-$AU23)) -> 1.108 | BB23: =MIN(IF($AU23=100%,1,1+VLOOKUP(($AJ23-$AI23-$AH23-$AG23-$AF23-$AE23*(1+BB$3))/$AJ23,Уголь_коэфф!$A:$B,2,1)-VLOOKUP($AO23,Уголь_коэфф!$A:$B,2,1)),1+(1-$AU23)) -> 1.108 | BC23: =MIN(IF($AU23=100%,1,1+VLOOKUP(($AJ23-$AI23-$AH23-$AG23-$AF23-$AE23*(1+BC$3))/$AJ23,Уголь_коэфф!$A:$B,2,1)-VLOOKUP($AO23,Уголь_коэфф!$A:$B,2,1)),1+(1-$AU23)) -> 1.108 | BD23: =MIN(IF($AU23=100%,1,1+VLOOKUP(($AJ23-$AI23-$AH23-$AG23-$AF23-$AE23*(1+BD$3))/$AJ23,Уголь_коэфф!$A:$B,2,1)-VLOOKUP($AO23,Уголь_коэфф!$A:$B,2,1)),1+(1-$AU23)) -> 1.103 | BE23: =MIN(IF($AU23=100%,1,1+VLOOKUP(($AJ23-$AI23-$AH23-$AG23-$AF23-$AE23*(1+BE$3))/$AJ23,Уголь_коэфф!$A:$B,2,1)-VLOOKUP($AO23,Уголь_коэфф!$A:$B,2,1)),1+(1-$AU23)) -> 1.103 | BF23: =MIN(IF($AU23=100%,1,1+VLOOKUP(($AJ23-$AI23-$AH23-$AG23-$AF23-$AE23*(1+BF$3))/$AJ23,Уголь_коэфф!$A:$B,2,1)-VLOOKUP($AO23,Уголь_коэфф!$A:$B,2,1)),1+(1-$AU23)) -> 1.103 | BG23: =MIN(IF($AU23=100%,1,1+VLOOKUP(($AJ23-$AI23-$AH23-$AG23-$AF23-$AE23*(1+BG$3))/$AJ23,Уголь_коэфф!$A:$B,2,1)-VLOOKUP($AO23,Уголь_коэфф!$A:$B,2,1)),1+(1-$AU23)) -> 1.103 | ... EU23: =MIN(IF($AU23=100%,1,1+VLOOKUP(($AJ23-$AI23-$AH23-$AG23-$AF23-$AE23*(1+EU$3))/$AJ23,Уголь_коэфф!$A:$B,2,1)-VLOOKUP($AO23,Уголь_коэфф!$A:$B,2,1)),1+(1-$AU23)) -> 1 | EV23: 1 | EW23: =MIN(1,MAX(VLOOKUP(($AJ23-$AI23-$AH23-$AG23-$AF23-$AE23*(1+EW$3))/$AJ23,Уголь_коэфф!$A:$B,2,1),(EV23-0.05))) -> 0.95 | EX23: =MIN(1,MAX(VLOOKUP(($AJ23-$AI23-$AH23-$AG23-$AF23-$AE23*(1+EX$3))/$AJ23,Уголь_коэфф!$A:$B,2,1),(EW23-0.05))) -> 0.9 | EY23: =MIN(1,MAX(VLOOKUP(($AJ23-$AI23-$AH23-$AG23-$AF23-$AE23*(1+EY$3))/$AJ23,Уголь_коэфф!$A:$B,2,1),(EX23-0.05))) -> 0.872 | EZ23: =MIN(1,MAX(VLOOKUP(($AJ23-$AI23-$AH23-$AG23-$AF23-$AE23*(1+EZ$3))/$AJ23,Уголь_коэфф!$A:$B,2,1),(EY23-0.05))) -> 0.866 | FA23: =MIN(1,MAX(VLOOKUP(($AJ23-$AI23-$AH23-$AG23-$AF23-$AE23*(1+FA$3))/$AJ23,Уголь_коэфф!$A:$B,2,1),(EZ23-0.05))) -> 0.866 | FB23: =MIN(1,MAX(VLOOKUP(($AJ23-$AI23-$AH23-$AG23-$AF23-$AE23*(1+FB$3))/$AJ23,Уголь_коэфф!$A:$B,2,1),(FA23-0.05))) -> 0.866 | FC23: =MIN(1,MAX(VLOOKUP(($AJ23-$AI23-$AH23-$AG23-$AF23-$AE23*(1+FC$3))/$AJ23,Уголь_коэфф!$A:$B,2,1),(FB23-0.05))) -> 0.866 | FD23: =MIN(1,MAX(VLOOKUP(($AJ23-$AI23-$AH23-$AG23-$AF23-$AE23*(1+FD$3))/$AJ23,Уголь_коэфф!$A:$B,2,1),(FC23-0.05))) -> 0.866 | ... IR23: =MIN(1,MAX(VLOOKUP(($AJ23-$AI23-$AH23-$AG23-$AF23-$AE23*(1+IR$3))/$AJ23,Уголь_коэфф!$A:$B,2,1),(IQ23-0.05))) -> 0.736 | IS23: =HLOOKUP($IS$2,$AZ$3:$IR$27,ROW(IR23)-2,FALSE) -> 0.848 | IT23: =IF($IV$2=1,IF(AND($IT$2="индексация",IS23<1,IS23*$IV$1>1),1,IF(AND($IT$2="индексация",IS23=1),1,IF(AND($IT$2="скидка",IS23=1),1,IS23*$IV$1))),IS23*$IV$1) -> 0.848
A24: уголь энергетический (кроме антрацита)ЭкспортВосточное | B24: 1 | C24: Уголь каменный | D24: 16111 | E24: УГОЛЬ Г | F24: уголь энергетический (кроме антрацита) | G24: ЗСБ | H24: ДВС | I24: ЕРУНАКОВО | J24: НАХОДКА-В-ЭК | K24: 6064 | L24: полувагон | M24: Экспорт | N24: неконтейнерная | O24: Восточное | P24: 54998897 | Q24: ООО "ПРОМУГОЛЬСЕРВИС" | R24: ООО "Промугольсервис" | S24: 756416 | T24: 4586950336 | U24: 10137 | W24: 1667958938 | X24: 75 | Y24: маршрутная | Z24: 13 | AA24: 14 | AB24: 4 | AC24: 2442.47 | AD24: 1120.57 | AE24: =AC24+AD24 -> 3563.04 | AF24: ='Цены,перевалка,аренда'!$C$26*SUM(Уголь_эластика_экспорт!Z24+Уголь_эластика_экспорт!AA24+Уголь_эластика_экспорт!AB24)/Уголь_эластика_экспорт!X24 -> 413.33333 | AG24: =SUMIF('Цены,перевалка,аренда'!$A$20:$A$22,Уголь_эластика_экспорт!$O24,'Цены,перевалка,аренда'!$D$20:$D$22) -> 763.055 | AI24: 2338 | AJ24: =SUMIF('Цены,перевалка,аренда'!$A$5:$A$17,Уголь_эластика_экспорт!A24,'Цены,перевалка,аренда'!$D$5:$D$17) -> 8546.216 | AK24: =AJ24/'Цены,перевалка,аренда'!$C$1 -> 112 | AL24: =AE24+AF24+AG24 -> 4739.4283 | AM24: =AJ24-AL24 -> 3806.7877 | AN24: =AI24+AH24+AG24+AF24+AE24 -> 7077.4283 | AO24: =(AJ24-AN24)/AJ24 -> 0.17186409 | AP24: =AL24/AJ24 -> 0.55456454 | AQ24: =AE24/AJ24 -> 0.41691434 | AR24: =AE24/AL24 -> 0.75178687 | AS24: =IT24 -> 1 | AT24: =S24*AS24 -> 756416 | AU24: 0.8 | AV24: =(AJ24-(AE24*(1+$IS$2)+AF24+AG24+AH24+AI24))/AJ24 -> 0.13017266 | AW24: =(AE24*(1+$IS$2)+AF24+AG24)/AJ24 -> 0.59625597 | AX24: =(AE24*(1+$IS$2))/AJ24 -> 0.45860577 | AY24: =(AE24*(1+$IS$2))/(AE24*(1+$IS$2)+AF24+AG24) -> 0.76914244 | AZ24: =MIN(IF($AU24=100%,1,1+VLOOKUP(($AJ24-$AI24-$AH24-$AG24-$AF24-$AE24*(1+AZ$3))/$AJ24,Уголь_коэфф!$A:$B,2,1)-VLOOKUP($AO24,Уголь_коэфф!$A:$B,2,1)),1+(1-$AU24)) -> 1.131 | BA24: =MIN(IF($AU24=100%,1,1+VLOOKUP(($AJ24-$AI24-$AH24-$AG24-$AF24-$AE24*(1+BA$3))/$AJ24,Уголь_коэфф!$A:$B,2,1)-VLOOKUP($AO24,Уголь_коэфф!$A:$B,2,1)),1+(1-$AU24)) -> 1.124 | BB24: =MIN(IF($AU24=100%,1,1+VLOOKUP(($AJ24-$AI24-$AH24-$AG24-$AF24-$AE24*(1+BB$3))/$AJ24,Уголь_коэфф!$A:$B,2,1)-VLOOKUP($AO24,Уголь_коэфф!$A:$B,2,1)),1+(1-$AU24)) -> 1.124 | BC24: =MIN(IF($AU24=100%,1,1+VLOOKUP(($AJ24-$AI24-$AH24-$AG24-$AF24-$AE24*(1+BC$3))/$AJ24,Уголь_коэфф!$A:$B,2,1)-VLOOKUP($AO24,Уголь_коэфф!$A:$B,2,1)),1+(1-$AU24)) -> 1.124 | BD24: =MIN(IF($AU24=100%,1,1+VLOOKUP(($AJ24-$AI24-$AH24-$AG24-$AF24-$AE24*(1+BD$3))/$AJ24,Уголь_коэфф!$A:$B,2,1)-VLOOKUP($AO24,Уголь_коэфф!$A:$B,2,1)),1+(1-$AU24)) -> 1.124 | BE24: =MIN(IF($AU24=100%,1,1+VLOOKUP(($AJ24-$AI24-$AH24-$AG24-$AF24-$AE24*(1+BE$3))/$AJ24,Уголь_коэфф!$A:$B,2,1)-VLOOKUP($AO24,Уголь_коэфф!$A:$B,2,1)),1+(1-$AU24)) -> 1.117 | BF24: =MIN(IF($AU24=100%,1,1+VLOOKUP(($AJ24-$AI24-$AH24-$AG24-$AF24-$AE24*(1+BF$3))/$AJ24,Уголь_коэфф!$A:$B,2,1)-VLOOKUP($AO24,Уголь_коэфф!$A:$B,2,1)),1+(1-$AU24)) -> 1.117 | BG24: =MIN(IF($AU24=100%,1,1+VLOOKUP(($AJ24-$AI24-$AH24-$AG24-$AF24-$AE24*(1+BG$3))/$AJ24,Уголь_коэфф!$A:$B,2,1)-VLOOKUP($AO24,Уголь_коэфф!$A:$B,2,1)),1+(1-$AU24)) -> 1.117 | ... EU24: =MIN(IF($AU24=100%,1,1+VLOOKUP(($AJ24-$AI24-$AH24-$AG24-$AF24-$AE24*(1+EU$3))/$AJ24,Уголь_коэфф!$A:$B,2,1)-VLOOKUP($AO24,Уголь_коэфф!$A:$B,2,1)),1+(1-$AU24)) -> 1 | EV24: 1 | EW24: =MIN(1,MAX(VLOOKUP(($AJ24-$AI24-$AH24-$AG24-$AF24-$AE24*(1+EW$3))/$AJ24,Уголь_коэфф!$A:$B,2,1),(EV24-0.05))) -> 1 | EX24: =MIN(1,MAX(VLOOKUP(($AJ24-$AI24-$AH24-$AG24-$AF24-$AE24*(1+EX$3))/$AJ24,Уголь_коэфф!$A:$B,2,1),(EW24-0.05))) -> 1 | EY24: =MIN(1,MAX(VLOOKUP(($AJ24-$AI24-$AH24-$AG24-$AF24-$AE24*(1+EY$3))/$AJ24,Уголь_коэфф!$A:$B,2,1),(EX24-0.05))) -> 1 | EZ24: =MIN(1,MAX(VLOOKUP(($AJ24-$AI24-$AH24-$AG24-$AF24-$AE24*(1+EZ$3))/$AJ24,Уголь_коэфф!$A:$B,2,1),(EY24-0.05))) -> 1 | FA24: =MIN(1,MAX(VLOOKUP(($AJ24-$AI24-$AH24-$AG24-$AF24-$AE24*(1+FA$3))/$AJ24,Уголь_коэфф!$A:$B,2,1),(EZ24-0.05))) -> 1 | FB24: =MIN(1,MAX(VLOOKUP(($AJ24-$AI24-$AH24-$AG24-$AF24-$AE24*(1+FB$3))/$AJ24,Уголь_коэфф!$A:$B,2,1),(FA24-0.05))) -> 1 | FC24: =MIN(1,MAX(VLOOKUP(($AJ24-$AI24-$AH24-$AG24-$AF24-$AE24*(1+FC$3))/$AJ24,Уголь_коэфф!$A:$B,2,1),(FB24-0.05))) -> 1 | FD24: =MIN(1,MAX(VLOOKUP(($AJ24-$AI24-$AH24-$AG24-$AF24-$AE24*(1+FD$3))/$AJ24,Уголь_коэфф!$A:$B,2,1),(FC24-0.05))) -> 1 | ... IR24: =MIN(1,MAX(VLOOKUP(($AJ24-$AI24-$AH24-$AG24-$AF24-$AE24*(1+IR$3))/$AJ24,Уголь_коэфф!$A:$B,2,1),(IQ24-0.05))) -> 0.99 | IS24: =HLOOKUP($IS$2,$AZ$3:$IR$27,ROW(IR24)-2,FALSE) -> 1 | IT24: =IF($IV$2=1,IF(AND($IT$2="индексация",IS24<1,IS24*$IV$1>1),1,IF(AND($IT$2="индексация",IS24=1),1,IF(AND($IT$2="скидка",IS24=1),1,IS24*$IV$1))),IS24*$IV$1) -> 1
A25: уголь энергетический (кроме антрацита)ЭкспортСеверо-Западное | B25: 1 | C25: Уголь каменный | D25: 16112 | E25: УГОЛЬ Д | F25: уголь энергетический (кроме антрацита) | G25: ЗСБ | H25: ОКТ | I25: ЕРУНАКОВО | J25: ЛУЖСКАЯ-ЭКСП | K25: 4229 | L25: полувагон | M25: Экспорт | N25: неконтейнерная | O25: Северо-Западное | P25: 87470970 | Q25: ООО "РЕСУРС" | R25: ООО "Промугольсервис" | S25: 3819419 | T25: 16151426937 | U25: 53944 | W25: 6992355439 | X25: 69 | Y25: маршрутная | Z25: 11 | AA25: 12 | AB25: 4 | AC25: 2082.23 | AD25: 928.76 | AE25: =AC25+AD25 -> 3010.99 | AF25: ='Цены,перевалка,аренда'!$C$27*SUM(Уголь_эластика_экспорт!Z25+Уголь_эластика_экспорт!AA25+Уголь_эластика_экспорт!AB25)/Уголь_эластика_экспорт!X25 -> 273.91304 | AG25: =SUMIF('Цены,перевалка,аренда'!$A$20:$A$22,Уголь_эластика_экспорт!$O25,'Цены,перевалка,аренда'!$D$20:$D$22) -> 610.444 | AI25: 2338 | AJ25: =SUMIF('Цены,перевалка,аренда'!$A$5:$A$17,Уголь_эластика_экспорт!A25,'Цены,перевалка,аренда'!$D$5:$D$17) -> 6485.9675 | AK25: =AJ25/'Цены,перевалка,аренда'!$C$1 -> 85 | AL25: =AE25+AF25+AG25 -> 3895.347 | AM25: =AJ25-AL25 -> 2590.6205 | AN25: =AI25+AH25+AG25+AF25+AE25 -> 6233.347 | AO25: =(AJ25-AN25)/AJ25 -> 0.03894877 | AP25: =AL25/AJ25 -> 0.60058072 | AQ25: =AE25/AJ25 -> 0.46423144 | AR25: =AE25/AL25 -> 0.77297092 | AS25: =IT25 -> 1 | AT25: =S25*AS25 -> 3819419 | AU25: 0.8 | AV25: =(AJ25-(AE25*(1+$IS$2)+AF25+AG25+AH25+AI25))/AJ25 -> -0.0074743735 | AW25: =(AE25*(1+$IS$2)+AF25+AG25)/AJ25 -> 0.64700387 | AX25: =(AE25*(1+$IS$2))/AJ25 -> 0.51065458 | AY25: =(AE25*(1+$IS$2))/(AE25*(1+$IS$2)+AF25+AG25) -> 0.78926048 | AZ25: =MIN(IF($AU25=100%,1,1+VLOOKUP(($AJ25-$AI25-$AH25-$AG25-$AF25-$AE25*(1+AZ$3))/$AJ25,Уголь_коэфф!$A:$B,2,1)-VLOOKUP($AO25,Уголь_коэфф!$A:$B,2,1)),1+(1-$AU25)) -> 1.134 | BA25: =MIN(IF($AU25=100%,1,1+VLOOKUP(($AJ25-$AI25-$AH25-$AG25-$AF25-$AE25*(1+BA$3))/$AJ25,Уголь_коэфф!$A:$B,2,1)-VLOOKUP($AO25,Уголь_коэфф!$A:$B,2,1)),1+(1-$AU25)) -> 1.128 | BB25: =MIN(IF($AU25=100%,1,1+VLOOKUP(($AJ25-$AI25-$AH25-$AG25-$AF25-$AE25*(1+BB$3))/$AJ25,Уголь_коэфф!$A:$B,2,1)-VLOOKUP($AO25,Уголь_коэфф!$A:$B,2,1)),1+(1-$AU25)) -> 1.128 | BC25: =MIN(IF($AU25=100%,1,1+VLOOKUP(($AJ25-$AI25-$AH25-$AG25-$AF25-$AE25*(1+BC$3))/$AJ25,Уголь_коэфф!$A:$B,2,1)-VLOOKUP($AO25,Уголь_коэфф!$A:$B,2,1)),1+(1-$AU25)) -> 1.128 | BD25: =MIN(IF($AU25=100%,1,1+VLOOKUP(($AJ25-$AI25-$AH25-$AG25-$AF25-$AE25*(1+BD$3))/$AJ25,Уголь_коэфф!$A:$B,2,1)-VLOOKUP($AO25,Уголь_коэфф!$A:$B,2,1)),1+(1-$AU25)) -> 1.128 | BE25: =MIN(IF($AU25=100%,1,1+VLOOKUP(($AJ25-$AI25-$AH25-$AG25-$AF25-$AE25*(1+BE$3))/$AJ25,Уголь_коэфф!$A:$B,2,1)-VLOOKUP($AO25,Уголь_коэфф!$A:$B,2,1)),1+(1-$AU25)) -> 1.122 | BF25: =MIN(IF($AU25=100%,1,1+VLOOKUP(($AJ25-$AI25-$AH25-$AG25-$AF25-$AE25*(1+BF$3))/$AJ25,Уголь_коэфф!$A:$B,2,1)-VLOOKUP($AO25,Уголь_коэфф!$A:$B,2,1)),1+(1-$AU25)) -> 1.122 | BG25: =MIN(IF($AU25=100%,1,1+VLOOKUP(($AJ25-$AI25-$AH25-$AG25-$AF25-$AE25*(1+BG$3))/$AJ25,Уголь_коэфф!$A:$B,2,1)-VLOOKUP($AO25,Уголь_коэфф!$A:$B,2,1)),1+(1-$AU25)) -> 1.122 | ... EU25: =MIN(IF($AU25=100%,1,1+VLOOKUP(($AJ25-$AI25-$AH25-$AG25-$AF25-$AE25*(1+EU$3))/$AJ25,Уголь_коэфф!$A:$B,2,1)-VLOOKUP($AO25,Уголь_коэфф!$A:$B,2,1)),1+(1-$AU25)) -> 1 | EV25: 1 | EW25: =MIN(1,MAX(VLOOKUP(($AJ25-$AI25-$AH25-$AG25-$AF25-$AE25*(1+EW$3))/$AJ25,Уголь_коэфф!$A:$B,2,1),(EV25-0.05))) -> 1 | EX25: =MIN(1,MAX(VLOOKUP(($AJ25-$AI25-$AH25-$AG25-$AF25-$AE25*(1+EX$3))/$AJ25,Уголь_коэфф!$A:$B,2,1),(EW25-0.05))) -> 1 | EY25: =MIN(1,MAX(VLOOKUP(($AJ25-$AI25-$AH25-$AG25-$AF25-$AE25*(1+EY$3))/$AJ25,Уголь_коэфф!$A:$B,2,1),(EX25-0.05))) -> 1 | EZ25: =MIN(1,MAX(VLOOKUP(($AJ25-$AI25-$AH25-$AG25-$AF25-$AE25*(1+EZ$3))/$AJ25,Уголь_коэфф!$A:$B,2,1),(EY25-0.05))) -> 1 | FA25: =MIN(1,MAX(VLOOKUP(($AJ25-$AI25-$AH25-$AG25-$AF25-$AE25*(1+FA$3))/$AJ25,Уголь_коэфф!$A:$B,2,1),(EZ25-0.05))) -> 1 | FB25: =MIN(1,MAX(VLOOKUP(($AJ25-$AI25-$AH25-$AG25-$AF25-$AE25*(1+FB$3))/$AJ25,Уголь_коэфф!$A:$B,2,1),(FA25-0.05))) -> 1 | FC25: =MIN(1,MAX(VLOOKUP(($AJ25-$AI25-$AH25-$AG25-$AF25-$AE25*(1+FC$3))/$AJ25,Уголь_коэфф!$A:$B,2,1),(FB25-0.05))) -> 1 | FD25: =MIN(1,MAX(VLOOKUP(($AJ25-$AI25-$AH25-$AG25-$AF25-$AE25*(1+FD$3))/$AJ25,Уголь_коэфф!$A:$B,2,1),(FC25-0.05))) -> 1 | ... IR25: =MIN(1,MAX(VLOOKUP(($AJ25-$AI25-$AH25-$AG25-$AF25-$AE25*(1+IR$3))/$AJ25,Уголь_коэфф!$A:$B,2,1),(IQ25-0.05))) -> 0.908 | IS25: =HLOOKUP($IS$2,$AZ$3:$IR$27,ROW(IR25)-2,FALSE) -> 1 | IT25: =IF($IV$2=1,IF(AND($IT$2="индексация",IS25<1,IS25*$IV$1>1),1,IF(AND($IT$2="индексация",IS25=1),1,IF(AND($IT$2="скидка",IS25=1),1,IS25*$IV$1))),IS25*$IV$1) -> 1
A26: уголь энергетический (кроме антрацита)ЭкспортЮжное | B26: 1 | C26: Уголь каменный | D26: 16112 | E26: УГОЛЬ Д | F26: уголь энергетический (кроме антрацита) | G26: ЗСБ | H26: СКВ | I26: ЕРУНАКОВО | J26: ВЫШСТБЛ-ЭКС | K26: 4598 | L26: полувагон | M26: Экспорт | N26: неконтейнерная | O26: Южное | P26: 87470970 | Q26: ООО "РЕСУРС" | R26: ООО "Промугольсервис" | S26: 505459 | T26: 2324319541 | U26: 6990 | W26: 965306586 | X26: 69 | Y26: маршрутная | Z26: 11 | AA26: 12 | AB26: 4 | AC26: 2192.58 | AD26: 993.42 | AE26: =AC26+AD26 -> 3186 | AF26: ='Цены,перевалка,аренда'!$C$27*SUM(Уголь_эластика_экспорт!Z26+Уголь_эластика_экспорт!AA26+Уголь_эластика_экспорт!AB26)/Уголь_эластика_экспорт!X26 -> 273.91304 | AG26: =SUMIF('Цены,перевалка,аренда'!$A$20:$A$22,Уголь_эластика_экспорт!$O26,'Цены,перевалка,аренда'!$D$20:$D$22) -> 991.9715 | AI26: 2338 | AJ26: =SUMIF('Цены,перевалка,аренда'!$A$5:$A$17,Уголь_эластика_экспорт!A26,'Цены,перевалка,аренда'!$D$5:$D$17) -> 7249.0225 | AK26: =AJ26/'Цены,перевалка,аренда'!$C$1 -> 95 | AL26: =AE26+AF26+AG26 -> 4451.8845 | AM26: =AJ26-AL26 -> 2797.138 | AN26: =AI26+AH26+AG26+AF26+AE26 -> 6789.8845 | AO26: =(AJ26-AN26)/AJ26 -> 0.063337913 | AP26: =AL26/AJ26 -> 0.61413584 | AQ26: =AE26/AJ26 -> 0.43950753 | AR26: =AE26/AL26 -> 0.71565198 | AS26: =IT26 -> 1 | AT26: =S26*AS26 -> 505459 | AU26: 0.8 | AV26: =(AJ26-(AE26*(1+$IS$2)+AF26+AG26+AH26+AI26))/AJ26 -> 0.01938716 | AW26: =(AE26*(1+$IS$2)+AF26+AG26)/AJ26 -> 0.6580866 | AX26: =(AE26*(1+$IS$2))/AJ26 -> 0.48345829 | AY26: =(AE26*(1+$IS$2))/(AE26*(1+$IS$2)+AF26+AG26) -> 0.73464236 | AZ26: =MIN(IF($AU26=100%,1,1+VLOOKUP(($AJ26-$AI26-$AH26-$AG26-$AF26-$AE26*(1+AZ$3))/$AJ26,Уголь_коэфф!$A:$B,2,1)-VLOOKUP($AO26,Уголь_коэфф!$A:$B,2,1)),1+(1-$AU26)) -> 1.115 | BA26: =MIN(IF($AU26=100%,1,1+VLOOKUP(($AJ26-$AI26-$AH26-$AG26-$AF26-$AE26*(1+BA$3))/$AJ26,Уголь_коэфф!$A:$B,2,1)-VLOOKUP($AO26,Уголь_коэфф!$A:$B,2,1)),1+(1-$AU26)) -> 1.115 | BB26: =MIN(IF($AU26=100%,1,1+VLOOKUP(($AJ26-$AI26-$AH26-$AG26-$AF26-$AE26*(1+BB$3))/$AJ26,Уголь_коэфф!$A:$B,2,1)-VLOOKUP($AO26,Уголь_коэфф!$A:$B,2,1)),1+(1-$AU26)) -> 1.109 | BC26: =MIN(IF($AU26=100%,1,1+VLOOKUP(($AJ26-$AI26-$AH26-$AG26-$AF26-$AE26*(1+BC$3))/$AJ26,Уголь_коэфф!$A:$B,2,1)-VLOOKUP($AO26,Уголь_коэфф!$A:$B,2,1)),1+(1-$AU26)) -> 1.109 | BD26: =MIN(IF($AU26=100%,1,1+VLOOKUP(($AJ26-$AI26-$AH26-$AG26-$AF26-$AE26*(1+BD$3))/$AJ26,Уголь_коэфф!$A:$B,2,1)-VLOOKUP($AO26,Уголь_коэфф!$A:$B,2,1)),1+(1-$AU26)) -> 1.109 | BE26: =MIN(IF($AU26=100%,1,1+VLOOKUP(($AJ26-$AI26-$AH26-$AG26-$AF26-$AE26*(1+BE$3))/$AJ26,Уголь_коэфф!$A:$B,2,1)-VLOOKUP($AO26,Уголь_коэфф!$A:$B,2,1)),1+(1-$AU26)) -> 1.109 | BF26: =MIN(IF($AU26=100%,1,1+VLOOKUP(($AJ26-$AI26-$AH26-$AG26-$AF26-$AE26*(1+BF$3))/$AJ26,Уголь_коэфф!$A:$B,2,1)-VLOOKUP($AO26,Уголь_коэфф!$A:$B,2,1)),1+(1-$AU26)) -> 1.103 | BG26: =MIN(IF($AU26=100%,1,1+VLOOKUP(($AJ26-$AI26-$AH26-$AG26-$AF26-$AE26*(1+BG$3))/$AJ26,Уголь_коэфф!$A:$B,2,1)-VLOOKUP($AO26,Уголь_коэфф!$A:$B,2,1)),1+(1-$AU26)) -> 1.103 | ... EU26: =MIN(IF($AU26=100%,1,1+VLOOKUP(($AJ26-$AI26-$AH26-$AG26-$AF26-$AE26*(1+EU$3))/$AJ26,Уголь_коэфф!$A:$B,2,1)-VLOOKUP($AO26,Уголь_коэфф!$A:$B,2,1)),1+(1-$AU26)) -> 1 | EV26: 1 | EW26: =MIN(1,MAX(VLOOKUP(($AJ26-$AI26-$AH26-$AG26-$AF26-$AE26*(1+EW$3))/$AJ26,Уголь_коэфф!$A:$B,2,1),(EV26-0.05))) -> 1 | EX26: =MIN(1,MAX(VLOOKUP(($AJ26-$AI26-$AH26-$AG26-$AF26-$AE26*(1+EX$3))/$AJ26,Уголь_коэфф!$A:$B,2,1),(EW26-0.05))) -> 1 | EY26: =MIN(1,MAX(VLOOKUP(($AJ26-$AI26-$AH26-$AG26-$AF26-$AE26*(1+EY$3))/$AJ26,Уголь_коэфф!$A:$B,2,1),(EX26-0.05))) -> 1 | EZ26: =MIN(1,MAX(VLOOKUP(($AJ26-$AI26-$AH26-$AG26-$AF26-$AE26*(1+EZ$3))/$AJ26,Уголь_коэфф!$A:$B,2,1),(EY26-0.05))) -> 1 | FA26: =MIN(1,MAX(VLOOKUP(($AJ26-$AI26-$AH26-$AG26-$AF26-$AE26*(1+FA$3))/$AJ26,Уголь_коэфф!$A:$B,2,1),(EZ26-0.05))) -> 1 | FB26: =MIN(1,MAX(VLOOKUP(($AJ26-$AI26-$AH26-$AG26-$AF26-$AE26*(1+FB$3))/$AJ26,Уголь_коэфф!$A:$B,2,1),(FA26-0.05))) -> 1 | FC26: =MIN(1,MAX(VLOOKUP(($AJ26-$AI26-$AH26-$AG26-$AF26-$AE26*(1+FC$3))/$AJ26,Уголь_коэфф!$A:$B,2,1),(FB26-0.05))) -> 1 | FD26: =MIN(1,MAX(VLOOKUP(($AJ26-$AI26-$AH26-$AG26-$AF26-$AE26*(1+FD$3))/$AJ26,Уголь_коэфф!$A:$B,2,1),(FC26-0.05))) -> 1 | ... IR26: =MIN(1,MAX(VLOOKUP(($AJ26-$AI26-$AH26-$AG26-$AF26-$AE26*(1+IR$3))/$AJ26,Уголь_коэфф!$A:$B,2,1),(IQ26-0.05))) -> 0.93 | IS26: =HLOOKUP($IS$2,$AZ$3:$IR$27,ROW(IR26)-2,FALSE) -> 1 | IT26: =IF($IV$2=1,IF(AND($IT$2="индексация",IS26<1,IS26*$IV$1>1),1,IF(AND($IT$2="индексация",IS26=1),1,IF(AND($IT$2="скидка",IS26=1),1,IS26*$IV$1))),IS26*$IV$1) -> 1
A27: уголь энергетический (кроме антрацита)ЭкспортВосточное | B27: 1 | C27: Уголь каменный | D27: 16122 | E27: ШИХТА УГОЛЬН | F27: уголь энергетический (кроме антрацита) | G27: ДВС | H27: ДВС | I27: НЕРЮНГРИ-ГР | J27: ПОСЬЕТ-ЭКСП | K27: 2546 | L27: полувагон | M27: Экспорт | N27: неконтейнерная | O27: Восточное | P27: 161878 | Q27: АО ХК "ЯКУТУГОЛЬ" | R27: ПАО "Мечел" | S27: 1252273 | T27: 3188538444 | U27: 18092 | W27: 1753178025 | X27: 69 | Y27: маршрутная | Z27: 11 | AA27: 11 | AB27: 4 | AC27: 1537.42 | AD27: 682.23 | AE27: =AC27+AD27 -> 2219.65 | AF27: ='Цены,перевалка,аренда'!$C$27*SUM(Уголь_эластика_экспорт!Z27+Уголь_эластика_экспорт!AA27+Уголь_эластика_экспорт!AB27)/Уголь_эластика_экспорт!X27 -> 263.76812 | AG27: =SUMIF('Цены,перевалка,аренда'!$A$20:$A$22,Уголь_эластика_экспорт!$O27,'Цены,перевалка,аренда'!$D$20:$D$22) -> 763.055 | AI27: 4037 | AJ27: =SUMIF('Цены,перевалка,аренда'!$A$5:$A$17,Уголь_эластика_экспорт!A27,'Цены,перевалка,аренда'!$D$5:$D$17) -> 8546.216 | AK27: =AJ27/'Цены,перевалка,аренда'!$C$1 -> 112 | AL27: =AE27+AF27+AG27 -> 3246.4731 | AM27: =AJ27-AL27 -> 5299.7429 | AN27: =AI27+AH27+AG27+AF27+AE27 -> 7283.4731 | AO27: =(AJ27-AN27)/AJ27 -> 0.14775462 | AP27: =AL27/AJ27 -> 0.37987258 | AQ27: =AE27/AJ27 -> 0.25972313 | AR27: =AE27/AL27 -> 0.68371119 | AS27: =IT27 -> 1 | AT27: =S27*AS27 -> 1252273 | AU27: =7.6/11 -> 0.69090909 | AV27: =(AJ27-(AE27*(1+$IS$2)+AF27+AG27+AH27+AI27))/AJ27 -> 0.12178231 | AW27: =(AE27*(1+$IS$2)+AF27+AG27)/AJ27 -> 0.40584489 | AX27: =(AE27*(1+$IS$2))/AJ27 -> 0.28569545 | AY27: =(AE27*(1+$IS$2))/(AE27*(1+$IS$2)+AF27+AG27) -> 0.7039523 | AZ27: =MIN(IF($AU27=100%,1,1+VLOOKUP(($AJ27-$AI27-$AH27-$AG27-$AF27-$AE27*(1+AZ$3))/$AJ27,Уголь_коэфф!$A:$B,2,1)-VLOOKUP($AO27,Уголь_коэфф!$A:$B,2,1)),1+(1-$AU27)) -> 1.074 | BA27: =MIN(IF($AU27=100%,1,1+VLOOKUP(($AJ27-$AI27-$AH27-$AG27-$AF27-$AE27*(1+BA$3))/$AJ27,Уголь_коэфф!$A:$B,2,1)-VLOOKUP($AO27,Уголь_коэфф!$A:$B,2,1)),1+(1-$AU27)) -> 1.074 | BB27: =MIN(IF($AU27=100%,1,1+VLOOKUP(($AJ27-$AI27-$AH27-$AG27-$AF27-$AE27*(1+BB$3))/$AJ27,Уголь_коэфф!$A:$B,2,1)-VLOOKUP($AO27,Уголь_коэфф!$A:$B,2,1)),1+(1-$AU27)) -> 1.074 | BC27: =MIN(IF($AU27=100%,1,1+VLOOKUP(($AJ27-$AI27-$AH27-$AG27-$AF27-$AE27*(1+BC$3))/$AJ27,Уголь_коэфф!$A:$B,2,1)-VLOOKUP($AO27,Уголь_коэфф!$A:$B,2,1)),1+(1-$AU27)) -> 1.074 | BD27: =MIN(IF($AU27=100%,1,1+VLOOKUP(($AJ27-$AI27-$AH27-$AG27-$AF27-$AE27*(1+BD$3))/$AJ27,Уголь_коэфф!$A:$B,2,1)-VLOOKUP($AO27,Уголь_коэфф!$A:$B,2,1)),1+(1-$AU27)) -> 1.074 | BE27: =MIN(IF($AU27=100%,1,1+VLOOKUP(($AJ27-$AI27-$AH27-$AG27-$AF27-$AE27*(1+BE$3))/$AJ27,Уголь_коэфф!$A:$B,2,1)-VLOOKUP($AO27,Уголь_коэфф!$A:$B,2,1)),1+(1-$AU27)) -> 1.074 | BF27: =MIN(IF($AU27=100%,1,1+VLOOKUP(($AJ27-$AI27-$AH27-$AG27-$AF27-$AE27*(1+BF$3))/$AJ27,Уголь_коэфф!$A:$B,2,1)-VLOOKUP($AO27,Уголь_коэфф!$A:$B,2,1)),1+(1-$AU27)) -> 1.068 | BG27: =MIN(IF($AU27=100%,1,1+VLOOKUP(($AJ27-$AI27-$AH27-$AG27-$AF27-$AE27*(1+BG$3))/$AJ27,Уголь_коэфф!$A:$B,2,1)-VLOOKUP($AO27,Уголь_коэфф!$A:$B,2,1)),1+(1-$AU27)) -> 1.068 | ... EU27: =MIN(IF($AU27=100%,1,1+VLOOKUP(($AJ27-$AI27-$AH27-$AG27-$AF27-$AE27*(1+EU$3))/$AJ27,Уголь_коэфф!$A:$B,2,1)-VLOOKUP($AO27,Уголь_коэфф!$A:$B,2,1)),1+(1-$AU27)) -> 1 | EV27: 1 | EW27: =MIN(1,MAX(VLOOKUP(($AJ27-$AI27-$AH27-$AG27-$AF27-$AE27*(1+EW$3))/$AJ27,Уголь_коэфф!$A:$B,2,1),(EV27-0.05))) -> 1 | EX27: =MIN(1,MAX(VLOOKUP(($AJ27-$AI27-$AH27-$AG27-$AF27-$AE27*(1+EX$3))/$AJ27,Уголь_коэфф!$A:$B,2,1),(EW27-0.05))) -> 1 | EY27: =MIN(1,MAX(VLOOKUP(($AJ27-$AI27-$AH27-$AG27-$AF27-$AE27*(1+EY$3))/$AJ27,Уголь_коэфф!$A:$B,2,1),(EX27-0.05))) -> 1 | EZ27: =MIN(1,MAX(VLOOKUP(($AJ27-$AI27-$AH27-$AG27-$AF27-$AE27*(1+EZ$3))/$AJ27,Уголь_коэфф!$A:$B,2,1),(EY27-0.05))) -> 1 | FA27: =MIN(1,MAX(VLOOKUP(($AJ27-$AI27-$AH27-$AG27-$AF27-$AE27*(1+FA$3))/$AJ27,Уголь_коэфф!$A:$B,2,1),(EZ27-0.05))) -> 1 | FB27: =MIN(1,MAX(VLOOKUP(($AJ27-$AI27-$AH27-$AG27-$AF27-$AE27*(1+FB$3))/$AJ27,Уголь_коэфф!$A:$B,2,1),(FA27-0.05))) -> 1 | FC27: =MIN(1,MAX(VLOOKUP(($AJ27-$AI27-$AH27-$AG27-$AF27-$AE27*(1+FC$3))/$AJ27,Уголь_коэфф!$A:$B,2,1),(FB27-0.05))) -> 1 | FD27: =MIN(1,MAX(VLOOKUP(($AJ27-$AI27-$AH27-$AG27-$AF27-$AE27*(1+FD$3))/$AJ27,Уголь_коэфф!$A:$B,2,1),(FC27-0.05))) -> 1 | ... IR27: =MIN(1,MAX(VLOOKUP(($AJ27-$AI27-$AH27-$AG27-$AF27-$AE27*(1+IR$3))/$AJ27,Уголь_коэфф!$A:$B,2,1),(IQ27-0.05))) -> 1 | IS27: =HLOOKUP($IS$2,$AZ$3:$IR$27,ROW(IR27)-2,FALSE) -> 1 | IT27: =IF($IV$2=1,IF(AND($IT$2="индексация",IS27<1,IS27*$IV$1>1),1,IF(AND($IT$2="индексация",IS27=1),1,IF(AND($IT$2="скидка",IS27=1),1,IS27*$IV$1))),IS27*$IV$1) -> 1

Sheet План погрузки
B1: Погрузка, млн т
B2: Сценарий 270ВП от 28.05.2026 / погрузка 2026 г. 1108,5 млн т (ЦФТО 28.05.2026)
B3: Показатели | C3: факт | G3: прогноз | H3: прогноз | S3: темпы, % | AI3: 2036 - 2025, +/- абс | AJ3: 2036/ 2025, % | AK3: cagr 2025-2036, %
C4: 2021 г | D4: 2022 г | E4: 2023 г | F4: 2024 г | G4: 2025 г | H4: 2026 г | I4: 2027 г | J4: 2028 г | K4: 2029 г | L4: 2030 г | M4: 2031 г | N4: 2032 г | O4: 2033 г | P4: 2034 г | Q4: 2035 г | R4: 2036 г | S4: 2022 г | T4: 2023 г | U4: 2024 г | V4: 2025 г | W4: 2026 г | X4: 2027 г | Y4: 2028 г | Z4: 2029 г | AA4: 2030 г | AB4: 2031 г | AC4: 2032 г | AD4: 2033 г | AE4: 2034 г | AF4: 2035 г | AG4: 2036 г
A5: Всего | B5: ВСЕГО | C5: =SUM(C7:C16) -> 1282.8145 | D5: =SUM(D7:D16) -> 1234.2892 | E5: =SUM(E7:E16) -> 1232.2395 | F5: =SUM(F7:F16) -> 1181.425 | G5: =SUM(G7:G16) -> 1115.7635 | H5: =SUM(H7:H16) -> 1108.5331 | I5: =SUM(I7:I16) -> 1114.7267 | J5: =SUM(J7:J16) -> 1135.001 | ... R5: =SUM(R7:R16) -> 1363.5648 | S5: =D5/C5*100 -> 96.217275 | T5: =E5/D5*100 -> 99.833938 | U5: =F5/E5*100 -> 95.876248 | V5: =G5/F5*100 -> 94.442176 | W5: =H5/G5*100 -> 99.351978 | X5: =I5/H5*100 -> 100.55872 | Y5: =J5/I5*100 -> 101.81877 | Z5: =K5/J5*100 -> 101.92308 | ... AG5: =R5/Q5*100 -> 101.49983 | AI5: =R5-G5 -> 247.8013 | AJ5: =R5/G5*100 -> 122.20912 | AK5: =(R5/G5)^(1/11)*100 -> 101.84003
A6: Всего | B6: в т.ч. без угля | C6: =C5-C7 -> 911.15413 | D6: =D5-D7 -> 879.88858 | E6: =E5-E7 -> 881.95735 | F6: =F5-F7 -> 850.0216 | G6: =G5-G7 -> 791.29713 | H6: =H5-H7 -> 780.29248 | I6: =I5-I7 -> 788.50019 | J6: =J5-J7 -> 808.276 | ... R6: =R5-R7 -> 975.319 | S6: =D6/C6*100 -> 96.568577 | T6: =E6/D6*100 -> 100.23512 | U6: =F6/E6*100 -> 96.378992 | V6: =G6/F6*100 -> 93.091414 | W6: =H6/G6*100 -> 98.609291 | X6: =I6/H6*100 -> 101.05188 | Y6: =J6/I6*100 -> 102.50803 | Z6: =K6/J6*100 -> 102.60319 | ... AG6: =R6/Q6*100 -> 101.97154 | AI6: =R6-G6 -> 184.02187 | AJ6: =R6/G6*100 -> 123.25572 | AK6: =(R6/G6)^(1/11)*100 -> 101.91901
A7: Всего | B7: Уголь | C7: =C20+C33 -> 371.66039 | D7: =D20+D33 -> 354.40059 | E7: =E20+E33 -> 350.28214 | F7: =F20+F33 -> 331.40338 | G7: =G20+G33 -> 324.46634 | H7: =H20+H33 -> 328.24059 | I7: =I20+I33 -> 326.22648 | J7: =J20+J33 -> 326.725 | ... R7: =R20+R33 -> 388.24577 | S7: =D7/C7*100 -> 95.35603 | T7: =E7/D7*100 -> 98.837911 | U7: =F7/E7*100 -> 94.610414 | V7: =G7/F7*100 -> 97.906767 | W7: =H7/G7*100 -> 101.16322 | X7: =I7/H7*100 -> 99.386393 | Y7: =J7/I7*100 -> 100.15281 | Z7: =K7/J7*100 -> 100.24057 | ... AG7: =R7/Q7*100 -> 100.33389 | AI7: =R7-G7 -> 63.779431 | AJ7: =R7/G7*100 -> 119.65672 | AK7: =(R7/G7)^(1/11)*100 -> 101.64481
A8: Всего | B8: Кокс | C8: =C21+C34 -> 12.034458 | D8: =D21+D34 -> 10.144067 | E8: =E21+E34 -> 11.535412 | F8: =F21+F34 -> 11.799099 | G8: =G21+G34 -> 9.987017 | H8: =H21+H34 -> 9.202364 | I8: =I21+I34 -> 9.614428 | J8: =J21+J34 -> 10.093 | ... R8: =R21+R34 -> 11.85 | S8: =D8/C8*100 -> 84.291848 | T8: =E8/D8*100 -> 113.71585 | U8: =F8/E8*100 -> 102.28589 | V8: =G8/F8*100 -> 84.6422 | W8: =H8/G8*100 -> 92.14327 | X8: =I8/H8*100 -> 104.47781 | Y8: =J8/I8*100 -> 104.97764 | Z8: =K8/J8*100 -> 104.90439 | ... AG8: =R8/Q8*100 -> 101.07472 | AI8: =R8-G8 -> 1.862983 | AJ8: =R8/G8*100 -> 118.65405 | AK8: =(R8/G8)^(1/11)*100 -> 101.56708
A9: Всего | B9: Нефтяные грузы | C9: =C22+C35 -> 217.50863 | D9: =D22+D35 -> 215.97843 | E9: =E22+E35 -> 210.05701 | F9: =F22+F35 -> 207.50458 | G9: =G22+G35 -> 197.09127 | H9: =H22+H35 -> 193.91947 | I9: =I22+I35 -> 195.63765 | J9: =J22+J35 -> 196.989 | ... R9: =R22+R35 -> 217.7 | S9: =D9/C9*100 -> 99.296486 | T9: =E9/D9*100 -> 97.258326 | U9: =F9/E9*100 -> 98.784889 | V9: =G9/F9*100 -> 94.981649 | W9: =H9/G9*100 -> 98.390693 | X9: =I9/H9*100 -> 100.88603 | Y9: =J9/I9*100 -> 100.69074 | Z9: =K9/J9*100 -> 101.13255 | ... AG9: =R9/Q9*100 -> 101.00729 | AI9: =R9-G9 -> 20.608729 | AJ9: =R9/G9*100 -> 110.45644 | AK9: =(R9/G9)^(1/11)*100 -> 100.9082
A10: Всего | B10: Руды металлические | C10: =C23+C36 -> 139.65145 | D10: =D23+D36 -> 133.17009 | E10: =E23+E36 -> 128.00871 | F10: =F23+F36 -> 125.29599 | G10: =G23+G36 -> 125.55675 | H10: =H23+H36 -> 125.69446 | I10: =I23+I36 -> 126.53714 | J10: =J23+J36 -> 128.832 | ... R10: =R23+R36 -> 150.8 | S10: =D10/C10*100 -> 95.358896 | T10: =E10/D10*100 -> 96.124221 | U10: =F10/E10*100 -> 97.880837 | V10: =G10/F10*100 -> 100.20811 | W10: =H10/G10*100 -> 100.10968 | X10: =I10/H10*100 -> 100.67042 | Y10: =J10/I10*100 -> 101.81359 | Z10: =K10/J10*100 -> 102.05539 | ... AG10: =R10/Q10*100 -> 101.69057 | AI10: =R10-G10 -> 25.24325 | AJ10: =R10/G10*100 -> 120.10505 | AK10: =(R10/G10)^(1/11)*100 -> 101.67937
A11: Всего | B11: Черные металлы | C11: =C24+C37 -> 69.282991 | D11: =D24+D37 -> 66.285625 | E11: =E24+E37 -> 67.79302 | F11: =F24+F37 -> 61.493635 | G11: =G24+G37 -> 50.634931 | H11: =H24+H37 -> 45.239083 | I11: =I24+I37 -> 46.100852 | J11: =J24+J37 -> 47.345 | ... R11: =R24+R37 -> 61.1 | S11: =D11/C11*100 -> 95.673735 | T11: =E11/D11*100 -> 102.27409 | U11: =F11/E11*100 -> 90.707915 | V11: =G11/F11*100 -> 82.341743 | W11: =H11/G11*100 -> 89.343625 | X11: =I11/H11*100 -> 101.90492 | Y11: =J11/I11*100 -> 102.69875 | Z11: =K11/J11*100 -> 103.43014 | ... AG11: =R11/Q11*100 -> 102.72533 | AI11: =R11-G11 -> 10.465069 | AJ11: =R11/G11*100 -> 120.66769 | AK11: =(R11/G11)^(1/11)*100 -> 101.72258
A12: Всего | B12: Лесные грузы | C12: =C25+C38 -> 41.776198 | D12: =D25+D38 -> 31.415288 | E12: =E25+E38 -> 26.944126 | F12: =F25+F38 -> 26.339061 | G12: =G25+G38 -> 24.786527 | H12: =H25+H38 -> 22.928183 | I12: =I25+I38 -> 23.558 | J12: =J25+J38 -> 24.59 | ... R12: =R25+R38 -> 31.2 | S12: =D12/C12*100 -> 75.199012 | T12: =E12/D12*100 -> 85.76756 | U12: =F12/E12*100 -> 97.754371 | V12: =G12/F12*100 -> 94.105583 | W12: =H12/G12*100 -> 92.502604 | X12: =I12/H12*100 -> 102.74691 | Y12: =J12/I12*100 -> 104.38068 | Z12: =K12/J12*100 -> 104.28223 | ... AG12: =R12/Q12*100 -> 102.02747 | AI12: =R12-G12 -> 6.413473 | AJ12: =R12/G12*100 -> 125.87484 | AK12: =(R12/G12)^(1/11)*100 -> 102.11402
A13: Всего | B13: Минстройматериалы | C13: =C26+C39 -> 196.25282 | D13: =D26+D39 -> 197.30381 | E13: =E26+E39 -> 193.82731 | F13: =F26+F39 -> 172.70009 | G13: =G26+G39 -> 152.53915 | H13: =H26+H39 -> 148.30015 | I13: =I26+I39 -> 148.59473 | J13: =J26+J39 -> 150.862 | ... R13: =R26+R39 -> 177.7 | S13: =D13/C13*100 -> 100.53553 | T13: =E13/D13*100 -> 98.238 | U13: =F13/E13*100 -> 89.099976 | V13: =G13/F13*100 -> 88.32604 | W13: =H13/G13*100 -> 97.221039 | X13: =I13/H13*100 -> 100.19864 | Y13: =J13/I13*100 -> 101.52581 | Z13: =K13/J13*100 -> 101.88119 | ... AG13: =R13/Q13*100 -> 102.07188 | AI13: =R13-G13 -> 25.160849 | AJ13: =R13/G13*100 -> 116.49468 | AK13: =(R13/G13)^(1/11)*100 -> 101.39764
A14: Всего | B14: Удобрения | C14: =C27+C40 -> 64.987162 | D14: =D27+D40 -> 60.504543 | E14: =E27+E40 -> 63.75381 | F14: =F27+F40 -> 67.71774 | G14: =G27+G40 -> 70.26524 | H14: =H27+H40 -> 70.124747 | I14: =I27+I40 -> 70.810646 | J14: =J27+J40 -> 72.906 | ... R14: =R27+R40 -> 92.8 | S14: =D14/C14*100 -> 93.102301 | T14: =E14/D14*100 -> 105.37029 | U14: =F14/E14*100 -> 106.21756 | V14: =G14/F14*100 -> 103.76194 | W14: =H14/G14*100 -> 99.800053 | X14: =I14/H14*100 -> 100.97811 | Y14: =J14/I14*100 -> 102.95909 | Z14: =K14/J14*100 -> 103.05462 | ... AG14: =R14/Q14*100 -> 103.04356 | AI14: =R14-G14 -> 22.53476 | AJ14: =R14/G14*100 -> 132.07099 | AK14: =(R14/G14)^(1/11)*100 -> 102.56106
A15: Всего | B15: Хлебные грузы | C15: =C28+C41 -> 27.655439 | D15: =D28+D41 -> 26.825572 | E15: =E28+E41 -> 35.679511 | F15: =F28+F41 -> 34.154891 | G15: =G28+G41 -> 29.932775 | H15: =H28+H41 -> 33.506471 | I15: =I28+I41 -> 34.3188 | J15: =J28+J41 -> 35.755 | ... R15: =R28+R41 -> 44 | S15: =D15/C15*100 -> 96.999263 | T15: =E15/D15*100 -> 133.00559 | U15: =F15/E15*100 -> 95.726903 | V15: =G15/F15*100 -> 87.638327 | W15: =H15/G15*100 -> 111.93907 | X15: =I15/H15*100 -> 102.42439 | Y15: =J15/I15*100 -> 104.18488 | Z15: =K15/J15*100 -> 103.93791 | ... AG15: =R15/Q15*100 -> 101.91555 | AI15: =R15-G15 -> 14.067225 | AJ15: =R15/G15*100 -> 146.99606 | AK15: =(R15/G15)^(1/11)*100 -> 103.56419
A16: Всего | B16: Прочие грузы | C16: =C29+C42 -> 142.00498 | D16: =D29+D42 -> 138.26116 | E16: =E29+E42 -> 144.35844 | F16: =F29+F42 -> 143.01651 | G16: =G29+G42 -> 130.50347 | H16: =H29+H42 -> 131.37757 | I16: =I29+I42 -> 133.32794 | J16: =J29+J42 -> 140.904 | ... R16: =R29+R42 -> 188.169 | S16: =D16/C16*100 -> 97.363604 | T16: =E16/D16*100 -> 104.40997 | U16: =F16/E16*100 -> 99.070417 | V16: =G16/F16*100 -> 91.250629 | W16: =H16/G16*100 -> 100.66979 | X16: =I16/H16*100 -> 101.48455 | Y16: =J16/I16*100 -> 105.68228 | Z16: =K16/J16*100 -> 104.62513 | ... AG16: =R16/Q16*100 -> 102.52653 | AI16: =R16-G16 -> 57.665533 | AJ16: =R16/G16*100 -> 144.18697 | AK16: =(R16/G16)^(1/11)*100 -> 103.38269
A17: Всего | B17: в т.ч. Грузы в контейнерах | C17: =C30+C43 -> 46.054611 | D17: =D30+D43 -> 44.986289 | E17: =E30+E43 -> 50.746234 | F17: =F30+F43 -> 51.559927 | G17: =G30+G43 -> 50.881789 | H17: =H30+H43 -> 51.020594 | I17: =I30+I43 -> 53.451 | J17: =J30+J43 -> 59.092 | ... R17: =R30+R43 -> 90.08 | S17: =D17/C17*100 -> 97.680315 | T17: =E17/D17*100 -> 112.80378 | U17: =F17/E17*100 -> 101.60345 | V17: =G17/F17*100 -> 98.684758 | W17: =H17/G17*100 -> 100.2728 | X17: =I17/H17*100 -> 104.76358 | Y17: =J17/I17*100 -> 110.55359 | Z17: =K17/J17*100 -> 108.36492 | ... AG17: =R17/Q17*100 -> 102.77943 | AI17: =R17-G17 -> 39.198211 | AJ17: =R17/G17*100 -> 177.0378 | AK17: =(R17/G17)^(1/11)*100 -> 105.32985
A18: Внутр. Перевозки | B18: Внутр. Перевозки | C18: =SUM(C20:C29) -> 792.75903 | D18: =SUM(D20:D29) -> 805.04259 | E18: =SUM(E20:E29) -> 800.57302 | F18: =SUM(F20:F29) -> 767.24542 | G18: =SUM(G20:G29) -> 703.91744 | H18: =SUM(H20:H29) -> 688.20139 | I18: =SUM(I20:I29) -> 690.58316 | J18: =SUM(J20:J29) -> 700.328 | ... R18: =SUM(R20:R29) -> 817.1 | S18: =D18/C18*100 -> 101.54947 | T18: =E18/D18*100 -> 99.444804 | U18: =F18/E18*100 -> 95.837032 | V18: =G18/F18*100 -> 91.74606 | W18: =H18/G18*100 -> 97.767344 | X18: =I18/H18*100 -> 100.34609 | Y18: =J18/I18*100 -> 101.4111 | Z18: =K18/J18*100 -> 101.74147 | ... AG18: =R18/Q18*100 -> 101.97218 | AI18: =R18-G18 -> 113.18256 | AJ18: =R18/G18*100 -> 116.07895 | AK18: =(R18/G18)^(1/11)*100 -> 101.36469
A19: Внутр. Перевозки | B19: в т.ч. без угля | C19: =C18-C20 -> 636.18853 | D19: =D18-D20 -> 647.76156 | E19: =E18-E20 -> 646.04869 | F19: =F18-F20 -> 613.39496 | G19: =G18-G20 -> 556.47905 | H19: =H18-H20 -> 544.77862 | I19: =I18-I20 -> 547.04416 | J19: =J18-J20 -> 556.803 | ... R19: =R18-R20 -> 667.1 | S19: =D19/C19*100 -> 101.81912 | T19: =E19/D19*100 -> 99.735572 | U19: =F19/E19*100 -> 94.945623 | V19: =G19/F19*100 -> 90.721165 | W19: =H19/G19*100 -> 97.897417 | X19: =I19/H19*100 -> 100.41586 | Y19: =J19/I19*100 -> 101.78392 | Z19: =K19/J19*100 -> 102.139 | ... AG19: =R19/Q19*100 -> 102.27736 | AI19: =R19-G19 -> 110.62095 | AJ19: =R19/G19*100 -> 119.87873 | AK19: =(R19/G19)^(1/11)*100 -> 101.66194
A20: Внутр. Перевозки | B20: Уголь | C20: 156.57051 | D20: 157.28103 | E20: 154.52433 | F20: 153.85046 | G20: 147.43839 | H20: 143.42277 | I20: 143.539 | J20: 143.525 | K20: 143.811 | L20: 144.4 | M20: 145.319 | N20: 146.243 | O20: 147.173 | P20: 148.109 | Q20: 149.051 | R20: 150 | S20: =D20/C20*100 -> 100.4538 | T20: =E20/D20*100 -> 98.247277 | U20: =F20/E20*100 -> 99.56391 | V20: =G20/F20*100 -> 95.83227 | W20: =H20/G20*100 -> 97.276407 | X20: =I20/H20*100 -> 100.08104 | Y20: =J20/I20*100 -> 99.990247 | Z20: =K20/J20*100 -> 100.19927 | ... AG20: =R20/Q20*100 -> 100.63669 | AI20: =R20-G20 -> 2.561608 | AJ20: =R20/G20*100 -> 101.73741 | AK20: =(R20/G20)^(1/11)*100 -> 100.15671
A21: Внутр. Перевозки | B21: Кокс | C21: 7.9129 | D21: 7.406707 | E21: 8.890829 | F21: 9.044316 | G21: 8.000834 | H21: 7.518422 | I21: 7.7498 | J21: 8.055 | K21: 8.372 | L21: 8.7 | M21: 8.813 | N21: 8.927 | O21: 9.043 | P21: 9.16 | Q21: 9.279 | R21: 9.4 | S21: =D21/C21*100 -> 93.60294 | T21: =E21/D21*100 -> 120.03754 | U21: =F21/E21*100 -> 101.72635 | V21: =G21/F21*100 -> 88.462566 | W21: =H21/G21*100 -> 93.970479 | X21: =I21/H21*100 -> 103.07748 | Y21: =J21/I21*100 -> 103.93817 | Z21: =K21/J21*100 -> 103.93544 | ... AG21: =R21/Q21*100 -> 101.30402 | AI21: =R21-G21 -> 1.399166 | AJ21: =R21/G21*100 -> 117.48775 | AK21: =(R21/G21)^(1/11)*100 -> 101.47591
A22: Внутр. Перевозки | B22: Нефтяные грузы | C22: 126.07659 | D22: 129.03156 | E22: 126.18907 | F22: 125.68165 | G22: 120.69456 | H22: 119.03292 | I22: 119.40949 | J22: 120.258 | K22: 121.616 | L22: 123.5 | M22: 125.346 | N22: 127.22 | O22: 129.122 | P22: 131.052 | Q22: 133.011 | R22: 135 | S22: =D22/C22*100 -> 102.34378 | T22: =E22/D22*100 -> 97.797058 | U22: =F22/E22*100 -> 99.597892 | V22: =G22/F22*100 -> 96.031962 | W22: =H22/G22*100 -> 98.623273 | X22: =I22/H22*100 -> 100.31636 | Y22: =J22/I22*100 -> 100.71059 | Z22: =K22/J22*100 -> 101.12924 | ... AG22: =R22/Q22*100 -> 101.49537 | AI22: =R22-G22 -> 14.305445 | AJ22: =R22/G22*100 -> 111.8526 | AK22: =(R22/G22)^(1/11)*100 -> 101.02349
A23: Внутр. Перевозки | B23: Руды металлические | C23: 112.11914 | D23: 114.84624 | E23: 112.75108 | F23: 108.86578 | G23: 105.30536 | H23: 102.66741 | I23: 103.22914 | J23: 105.075 | K23: 107.259 | L23: 109.8 | M23: 112.322 | N23: 114.381 | O23: 116.477 | P23: 118.612 | Q23: 120.786 | R23: 123 | S23: =D23/C23*100 -> 102.43233 | T23: =E23/D23*100 -> 98.175678 | U23: =F23/E23*100 -> 96.554094 | V23: =G23/F23*100 -> 96.729529 | W23: =H23/G23*100 -> 97.494951 | X23: =I23/H23*100 -> 100.54714 | Y23: =J23/I23*100 -> 101.78812 | Z23: =K23/J23*100 -> 102.07852 | ... AG23: =R23/Q23*100 -> 101.83299 | AI23: =R23-G23 -> 17.694641 | AJ23: =R23/G23*100 -> 116.80317 | AK23: =(R23/G23)^(1/11)*100 -> 101.42202
A24: Внутр. Перевозки | B24: Черные металлы | C24: 39.636425 | D24: 42.41381 | E24: 45.233942 | F24: 41.038585 | G24: 29.816009 | H24: 25.582209 | I24: 25.63706 | J24: 26.102 | K24: 26.88 | L24: 28 | M24: 29.061 | N24: 30.162 | O24: 31.305 | P24: 32.491 | Q24: 33.722 | R24: 35 | S24: =D24/C24*100 -> 107.00715 | T24: =E24/D24*100 -> 106.64909 | U24: =F24/E24*100 -> 90.725201 | V24: =G24/F24*100 -> 72.653599 | W24: =H24/G24*100 -> 85.800246 | X24: =I24/H24*100 -> 100.21441 | Y24: =J24/I24*100 -> 101.81355 | Z24: =K24/J24*100 -> 102.98061 | ... AG24: =R24/Q24*100 -> 103.78981 | AI24: =R24-G24 -> 5.183991 | AJ24: =R24/G24*100 -> 117.3866 | AK24: =(R24/G24)^(1/11)*100 -> 101.46797
A25: Внутр. Перевозки | B25: Лесные грузы | C25: 22.43515 | D25: 21.468299 | E25: 19.072505 | F25: 19.289507 | G25: 18.687861 | H25: 17.953913 | I25: 18.022 | J25: 18.813 | K25: 19.639 | L25: 20.5 | M25: 20.836 | N25: 21.177 | O25: 21.524 | P25: 21.877 | Q25: 22.235 | R25: 22.6 | S25: =D25/C25*100 -> 95.690463 | T25: =E25/D25*100 -> 88.840318 | U25: =F25/E25*100 -> 101.13777 | V25: =G25/F25*100 -> 96.880967 | W25: =H25/G25*100 -> 96.072595 | X25: =I25/H25*100 -> 100.37923 | Y25: =J25/I25*100 -> 104.38908 | Z25: =K25/J25*100 -> 104.39058 | ... AG25: =R25/Q25*100 -> 101.64156 | AI25: =R25-G25 -> 3.912139 | AJ25: =R25/G25*100 -> 120.93412 | AK25: =(R25/G25)^(1/11)*100 -> 101.74298
A26: Внутр. Перевозки | B26: Минстройматериалы | C26: 191.38905 | D26: 192.96151 | E26: 189.83939 | F26: 168.60355 | G26: 148.64243 | H26: 144.97518 | I26: 145.16073 | J26: 147.067 | K26: 149.505 | L26: 152.5 | M26: 155.68 | N26: 158.926 | O26: 162.24 | P26: 165.623 | Q26: 169.076 | R26: 172.6 | S26: =D26/C26*100 -> 100.8216 | T26: =E26/D26*100 -> 98.382002 | U26: =F26/E26*100 -> 88.813786 | V26: =G26/F26*100 -> 88.160915 | W26: =H26/G26*100 -> 97.532836 | X26: =I26/H26*100 -> 100.12799 | Y26: =J26/I26*100 -> 101.31321 | Z26: =K26/J26*100 -> 101.65775 | ... AG26: =R26/Q26*100 -> 102.08427 | AI26: =R26-G26 -> 23.957565 | AJ26: =R26/G26*100 -> 116.11758 | AK26: =(R26/G26)^(1/11)*100 -> 101.36775
A27: Внутр. Перевозки | B27: Удобрения | C27: 26.306975 | D27: 30.78435 | E27: 33.040373 | F27: 31.475928 | G27: 27.801418 | H27: 28.197012 | I27: 28.359 | J27: 29.07 | K27: 30.106 | L27: 31.5 | M27: 32.915 | N27: 34.393 | O27: 35.938 | P27: 37.552 | Q27: 39.238 | R27: 41 | S27: =D27/C27*100 -> 117.01973 | T27: =E27/D27*100 -> 107.32847 | U27: =F27/E27*100 -> 95.26505 | V27: =G27/F27*100 -> 88.325968 | W27: =H27/G27*100 -> 101.42293 | X27: =I27/H27*100 -> 100.57449 | Y27: =J27/I27*100 -> 102.50714 | Z27: =K27/J27*100 -> 103.56381 | ... AG27: =R27/Q27*100 -> 104.49054 | AI27: =R27-G27 -> 13.198582 | AJ27: =R27/G27*100 -> 147.47449 | AK27: =(R27/G27)^(1/11)*100 -> 103.59479
A28: Внутр. Перевозки | B28: Хлебные грузы | C28: 13.031996 | D28: 12.123923 | E28: 11.058006 | F28: 10.721033 | G28: 12.26973 | H28: 11.254414 | I28: 11.346 | J28: 11.873 | K28: 12.424 | L28: 13 | M28: 13.162 | N28: 13.326 | O28: 13.492 | P28: 13.66 | Q28: 13.83 | R28: 14 | S28: =D28/C28*100 -> 93.031973 | T28: =E28/D28*100 -> 91.208151 | U28: =F28/E28*100 -> 96.952678 | V28: =G28/F28*100 -> 114.44541 | W28: =H28/G28*100 -> 91.725034 | X28: =I28/H28*100 -> 100.81378 | Y28: =J28/I28*100 -> 104.64481 | Z28: =K28/J28*100 -> 104.64078 | ... AG28: =R28/Q28*100 -> 101.22921 | AI28: =R28-G28 -> 1.73027 | AJ28: =R28/G28*100 -> 114.10194 | AK28: =(R28/G28)^(1/11)*100 -> 101.20651
A29: Внутр. Перевозки | B29: Прочие грузы | C29: 97.280294 | D29: 96.725163 | E29: 99.973501 | F29: 98.674603 | G29: 85.260851 | H29: 87.59714 | I29: 88.130936 | J29: 90.49 | K29: 92.912 | L29: 95.4 | M29: 98.346 | N29: 101.383 | O29: 104.514 | P29: 107.742 | Q29: 111.069 | R29: 114.5 | S29: =D29/C29*100 -> 99.429349 | T29: =E29/D29*100 -> 103.35832 | U29: =F29/E29*100 -> 98.700758 | V29: =G29/F29*100 -> 86.406075 | W29: =H29/G29*100 -> 102.74017 | X29: =I29/H29*100 -> 100.60938 | Y29: =J29/I29*100 -> 102.67677 | Z29: =K29/J29*100 -> 102.67654 | ... AG29: =R29/Q29*100 -> 103.08907 | AI29: =R29-G29 -> 29.239149 | AJ29: =R29/G29*100 -> 134.29376 | AK29: =(R29/G29)^(1/11)*100 -> 102.71679
A30: Внутр. Перевозки | B30: в т.ч. Грузы в контейнерах | C30: 21.058302 | D30: 20.773652 | E30: 23.3692 | F30: 23.746445 | G30: 20.925098 | H30: 21.091524 | I30: 21.964 | J30: 23.653 | K30: 25.471 | L30: 27.429 | M30: 28.498 | N30: 29.608 | O30: 30.762 | P30: 31.961 | Q30: 33.206 | R30: 34.5 | S30: =D30/C30*100 -> 98.648277 | T30: =E30/D30*100 -> 112.49442 | U30: =F30/E30*100 -> 101.61428 | V30: =G30/F30*100 -> 88.118866 | W30: =H30/G30*100 -> 100.79534 | X30: =I30/H30*100 -> 104.13662 | Y30: =J30/I30*100 -> 107.68986 | Z30: =K30/J30*100 -> 107.68613 | ... AG30: =R30/Q30*100 -> 103.89689 | AI30: =R30-G30 -> 13.574902 | AJ30: =R30/G30*100 -> 164.87378 | AK30: =(R30/G30)^(1/11)*100 -> 104.65044
A31: Экспорт | B31: Экспорт | C31: =SUM(C33:C42) -> 490.05549 | D31: =SUM(D33:D42) -> 429.24659 | E31: =SUM(E33:E42) -> 431.66647 | F31: =SUM(F33:F42) -> 414.17956 | G31: =SUM(G33:G42) -> 411.84602 | H31: =SUM(H33:H42) -> 420.33168 | I31: =SUM(I33:I42) -> 424.14351 | J31: =SUM(J33:J42) -> 434.673 | ... R31: =SUM(R33:R42) -> 546.46477 | S31: =D31/C31*100 -> 87.591425 | T31: =E31/D31*100 -> 100.56375 | U31: =F31/E31*100 -> 95.948978 | V31: =G31/F31*100 -> 99.436587 | W31: =H31/G31*100 -> 102.0604 | X31: =I31/H31*100 -> 100.90686 | Y31: =J31/I31*100 -> 102.48253 | Z31: =K31/J31*100 -> 102.21569 | ... AG31: =R31/Q31*100 -> 100.80167 | AI31: =R31-G31 -> 134.61875 | AJ31: =R31/G31*100 -> 132.68667 | AK31: =(R31/G31)^(1/11)*100 -> 102.60443
A32: Экспорт | B32: в т.ч. без угля | C32: =C31-C33 -> 274.96561 | D32: =D31-D33 -> 232.12702 | E32: =E31-E33 -> 235.90866 | F32: =F31-F33 -> 236.62664 | G32: =G31-G33 -> 234.81808 | H32: =H31-H33 -> 235.51386 | I32: =I31-I33 -> 241.45603 | J32: =J31-J33 -> 251.473 | ... R32: =R31-R33 -> 308.219 | S32: =D32/C32*100 -> 84.420385 | T32: =E32/D32*100 -> 101.62912 | U32: =F32/E32*100 -> 100.30435 | V32: =G32/F32*100 -> 99.235688 | W32: =H32/G32*100 -> 100.29631 | X32: =I32/H32*100 -> 102.52306 | Y32: =J32/I32*100 -> 104.14857 | Z32: =K32/J32*100 -> 103.63101 | ... AG32: =R32/Q32*100 -> 101.31584 | AI32: =R32-G32 -> 73.400923 | AJ32: =R32/G32*100 -> 131.25863 | AK32: =(R32/G32)^(1/11)*100 -> 102.50355
A33: Экспорт | B33: Уголь | C33: =C46+C59+C72 -> 215.08988 | D33: =D46+D59+D72 -> 197.11956 | E33: =E46+E59+E72 -> 195.75781 | F33: =F46+F59+F72 -> 177.55292 | G33: =G46+G59+G72 -> 177.02795 | H33: =H46+H59+H72 -> 184.81782 | I33: =I46+I59+I72 -> 182.68748 | J33: =J46+J59+J72 -> 183.2 | ... R33: =R46+R59+R72 -> 238.24577 | S33: =D33/C33*100 -> 91.645204 | T33: =E33/D33*100 -> 99.309176 | U33: =F33/E33*100 -> 90.700298 | V33: =G33/F33*100 -> 99.704329 | W33: =H33/G33*100 -> 104.40036 | X33: =I33/H33*100 -> 98.847332 | Y33: =J33/I33*100 -> 100.28054 | Z33: =K33/J33*100 -> 100.27293 | ... AG33: =R33/Q33*100 -> 100.14418 | AI33: =R33-G33 -> 61.217823 | AJ33: =R33/G33*100 -> 134.58088 | AK33: =(R33/G33)^(1/11)*100 -> 102.73674
A34: Экспорт | B34: Кокс | C34: =C47+C60+C73 -> 4.121558 | D34: =D47+D60+D73 -> 2.73736 | E34: =E47+E60+E73 -> 2.644583 | F34: =F47+F60+F73 -> 2.754783 | G34: =G47+G60+G73 -> 1.986183 | H34: =H47+H60+H73 -> 1.683942 | I34: =I47+I60+I73 -> 1.864628 | J34: =J47+J60+J73 -> 2.038 | ... R34: =R47+R60+R73 -> 2.45 | S34: =D34/C34*100 -> 66.415661 | T34: =E34/D34*100 -> 96.610713 | U34: =F34/E34*100 -> 104.16701 | V34: =G34/F34*100 -> 72.099436 | W34: =H34/G34*100 -> 84.782822 | X34: =I34/H34*100 -> 110.72994 | Y34: =J34/I34*100 -> 109.29794 | Z34: =K34/J34*100 -> 108.73405 | ... AG34: =R34/Q34*100 -> 100.2045 | AI34: =R34-G34 -> 0.463817 | AJ34: =R34/G34*100 -> 123.35218 | AK34: =(R34/G34)^(1/11)*100 -> 101.92626
A35: Экспорт | B35: Нефтяные грузы | C35: =C48+C61+C74 -> 91.43204 | D35: =D48+D61+D74 -> 86.946873 | E35: =E48+E61+E74 -> 83.867939 | F35: =F48+F61+F74 -> 81.822929 | G35: =G48+G61+G74 -> 76.396716 | H35: =H48+H61+H74 -> 74.886548 | I35: =I48+I61+I74 -> 76.228163 | J35: =J48+J61+J74 -> 76.731 | ... R35: =R48+R61+R74 -> 82.7 | S35: =D35/C35*100 -> 95.094535 | T35: =E35/D35*100 -> 96.458833 | U35: =F35/E35*100 -> 97.561631 | V35: =G35/F35*100 -> 93.368347 | W35: =H35/G35*100 -> 98.023255 | X35: =I35/H35*100 -> 101.79153 | Y35: =J35/I35*100 -> 100.65965 | Z35: =K35/J35*100 -> 101.13774 | ... AG35: =R35/Q35*100 -> 100.22056 | AI35: =R35-G35 -> 6.303284 | AJ35: =R35/G35*100 -> 108.25073 | AK35: =(R35/G35)^(1/11)*100 -> 100.72333
A36: Экспорт | B36: Руды металлические | C36: =C49+C62+C75 -> 27.532317 | D36: =D49+D62+D75 -> 18.323841 | E36: =E49+E62+E75 -> 15.257628 | F36: =F49+F62+F75 -> 16.430211 | G36: =G49+G62+G75 -> 20.251391 | H36: =H49+H62+H75 -> 23.027048 | I36: =I49+I62+I75 -> 23.308 | J36: =J49+J62+J75 -> 23.757 | ... R36: =R49+R62+R75 -> 27.8 | S36: =D36/C36*100 -> 66.553937 | T36: =E36/D36*100 -> 83.266538 | U36: =F36/E36*100 -> 107.68522 | V36: =G36/F36*100 -> 123.25704 | W36: =H36/G36*100 -> 113.70601 | X36: =I36/H36*100 -> 101.2201 | Y36: =J36/I36*100 -> 101.92638 | Z36: =K36/J36*100 -> 101.95311 | ... AG36: =R36/Q36*100 -> 101.06518 | AI36: =R36-G36 -> 7.548609 | AJ36: =R36/G36*100 -> 137.27452 | AK36: =(R36/G36)^(1/11)*100 -> 102.92199
A37: Экспорт | B37: Черные металлы | C37: =C50+C63+C76 -> 29.646566 | D37: =D50+D63+D76 -> 23.871815 | E37: =E50+E63+E76 -> 22.559078 | F37: =F50+F63+F76 -> 20.45505 | G37: =G50+G63+G76 -> 20.818922 | H37: =H50+H63+H76 -> 19.656874 | I37: =I50+I63+I76 -> 20.463793 | J37: =J50+J63+J76 -> 21.243 | ... R37: =R50+R63+R76 -> 26.1 | S37: =D37/C37*100 -> 80.521349 | T37: =E37/D37*100 -> 94.500892 | U37: =F37/E37*100 -> 90.673254 | V37: =G37/F37*100 -> 101.77889 | W37: =H37/G37*100 -> 94.418308 | X37: =I37/H37*100 -> 104.10502 | Y37: =J37/I37*100 -> 103.80774 | Z37: =K37/J37*100 -> 103.98249 | ... AG37: =R37/Q37*100 -> 101.33168 | AI37: =R37-G37 -> 5.281078 | AJ37: =R37/G37*100 -> 125.36672 | AK37: =(R37/G37)^(1/11)*100 -> 102.07647
A38: Экспорт | B38: Лесные грузы | C38: =C51+C64+C77 -> 19.341048 | D38: =D51+D64+D77 -> 9.946989 | E38: =E51+E64+E77 -> 7.871621 | F38: =F51+F64+F77 -> 7.049554 | G38: =G51+G64+G77 -> 6.098666 | H38: =H51+H64+H77 -> 4.97427 | I38: =I51+I64+I77 -> 5.536 | J38: =J51+J64+J77 -> 5.777 | ... R38: =R51+R64+R77 -> 8.6 | S38: =D38/C38*100 -> 51.429421 | T38: =E38/D38*100 -> 79.135716 | U38: =F38/E38*100 -> 89.556573 | V38: =G38/F38*100 -> 86.511374 | W38: =H38/G38*100 -> 81.563247 | X38: =I38/H38*100 -> 111.29271 | Y38: =J38/I38*100 -> 104.35332 | Z38: =K38/J38*100 -> 103.92938 | ... AG38: =R38/Q38*100 -> 103.05572 | AI38: =R38-G38 -> 2.501334 | AJ38: =R38/G38*100 -> 141.01444 | AK38: =(R38/G38)^(1/11)*100 -> 103.1738
A39: Экспорт | B39: Минстройматериалы | C39: =C52+C65+C78 -> 4.863764 | D39: =D52+D65+D78 -> 4.342303 | E39: =E52+E65+E78 -> 3.987922 | F39: =F52+F65+F78 -> 4.096538 | G39: =G52+G65+G78 -> 3.896716 | H39: =H52+H65+H78 -> 3.324966 | I39: =I52+I65+I78 -> 3.434 | J39: =J52+J65+J78 -> 3.795 | ... R39: =R52+R65+R78 -> 5.1 | S39: =D39/C39*100 -> 89.278653 | T39: =E39/D39*100 -> 91.83887 | U39: =F39/E39*100 -> 102.72362 | V39: =G39/F39*100 -> 95.122174 | W39: =H39/G39*100 -> 85.327388 | X39: =I39/H39*100 -> 103.27925 | Y39: =J39/I39*100 -> 110.51252 | Z39: =K39/J39*100 -> 110.54018 | ... AG39: =R39/Q39*100 -> 101.65438 | AI39: =R39-G39 -> 1.203284 | AJ39: =R39/G39*100 -> 130.87944 | AK39: =(R39/G39)^(1/11)*100 -> 102.47659
A40: Экспорт | B40: Удобрения | C40: =C53+C66+C79 -> 38.680187 | D40: =D53+D66+D79 -> 29.720193 | E40: =E53+E66+E79 -> 30.713437 | F40: =F53+F66+F79 -> 36.241812 | G40: =G53+G66+G79 -> 42.463822 | H40: =H53+H66+H79 -> 41.927735 | I40: =I53+I66+I79 -> 42.451646 | J40: =J53+J66+J79 -> 43.836 | ... R40: =R53+R66+R79 -> 51.8 | S40: =D40/C40*100 -> 76.835701 | T40: =E40/D40*100 -> 103.34198 | U40: =F40/E40*100 -> 117.99986 | V40: =G40/F40*100 -> 117.16804 | W40: =H40/G40*100 -> 98.737544 | X40: =I40/H40*100 -> 101.24956 | Y40: =J40/I40*100 -> 103.26101 | Z40: =K40/J40*100 -> 102.71694 | ... AG40: =R40/Q40*100 -> 101.92637 | AI40: =R40-G40 -> 9.336178 | AJ40: =R40/G40*100 -> 121.98619 | AK40: =(R40/G40)^(1/11)*100 -> 101.82313
A41: Экспорт | B41: Хлебные грузы | C41: =C54+C67+C80 -> 14.623443 | D41: =D54+D67+D80 -> 14.701649 | E41: =E54+E67+E80 -> 24.621505 | F41: =F54+F67+F80 -> 23.433858 | G41: =G54+G67+G80 -> 17.663045 | H41: =H54+H67+H80 -> 22.252057 | I41: =I54+I67+I80 -> 22.9728 | J41: =J54+J67+J80 -> 23.882 | ... R41: =R54+R67+R80 -> 30 | S41: =D41/C41*100 -> 100.5348 | T41: =E41/D41*100 -> 167.47444 | U41: =F41/E41*100 -> 95.176383 | V41: =G41/F41*100 -> 75.374038 | W41: =H41/G41*100 -> 125.98087 | X41: =I41/H41*100 -> 103.23899 | Y41: =J41/I41*100 -> 103.95772 | Z41: =K41/J41*100 -> 103.58848 | ... AG41: =R41/Q41*100 -> 102.23903 | AI41: =R41-G41 -> 12.336955 | AJ41: =R41/G41*100 -> 169.84614 | AK41: =(R41/G41)^(1/11)*100 -> 104.9335
A42: Экспорт | B42: Прочие грузы | C42: =C55+C68+C81 -> 44.724683 | D42: =D55+D68+D81 -> 41.536 | E42: =E55+E68+E81 -> 44.384943 | F42: =F55+F68+F81 -> 44.341909 | G42: =G55+G68+G81 -> 45.242616 | H42: =H55+H68+H81 -> 43.780425 | I42: =I55+I68+I81 -> 45.197 | J42: =J55+J68+J81 -> 50.414 | ... R42: =R55+R68+R81 -> 73.669 | S42: =D42/C42*100 -> 92.870418 | T42: =E42/D42*100 -> 106.85897 | U42: =F42/E42*100 -> 99.903044 | V42: =G42/F42*100 -> 102.03128 | W42: =H42/G42*100 -> 96.768111 | X42: =I42/H42*100 -> 103.23564 | Y42: =J42/I42*100 -> 111.5428 | Z42: =K42/J42*100 -> 108.12274 | ... AG42: =R42/Q42*100 -> 101.6643 | AI42: =R42-G42 -> 28.426384 | AJ42: =R42/G42*100 -> 162.83099 | AK42: =(R42/G42)^(1/11)*100 -> 104.5319
A43: Экспорт | B43: в т.ч. Грузы в контейнерах | C43: =C56+C69+C82 -> 24.996309 | D43: =D56+D69+D82 -> 24.212637 | E43: =E56+E69+E82 -> 27.377034 | F43: =F56+F69+F82 -> 27.813482 | G43: =G56+G69+G82 -> 29.956691 | H43: =H56+H69+H82 -> 29.92907 | I43: =I56+I69+I82 -> 31.487 | J43: =J56+J69+J82 -> 35.439 | ... R43: =R56+R69+R82 -> 55.58 | S43: =D43/C43*100 -> 96.864849 | T43: =E43/D43*100 -> 113.0692 | U43: =F43/E43*100 -> 101.59421 | V43: =G43/F43*100 -> 107.70565 | W43: =H43/G43*100 -> 99.907797 | X43: =I43/H43*100 -> 105.20541 | Y43: =J43/I43*100 -> 112.55121 | Z43: =K43/J43*100 -> 108.81797 | ... AG43: =R43/Q43*100 -> 102.0978 | AI43: =R43-G43 -> 25.623309 | AJ43: =R43/G43*100 -> 185.53451 | AK43: =(R43/G43)^(1/11)*100 -> 105.77968
A44: Экспорт на Северо-Запад | B44: Экспорт на Северо-Запад | C44: =SUM(C46:C55) -> 205.78339 | D44: =SUM(D46:D55) -> 161.36569 | E44: =SUM(E46:E55) -> 152.55368 | F44: =SUM(F46:F55) -> 146.8356 | G44: =SUM(G46:G55) -> 135.58946 | H44: =SUM(H46:H55) -> 124.90257 | I44: =SUM(I46:I55) -> 125.91497 | J44: =SUM(J46:J55) -> 128.89 | ... R44: =SUM(R46:R55) -> 125.619 | S44: =D44/C44*100 -> 78.415315 | T44: =E44/D44*100 -> 94.539103 | U44: =F44/E44*100 -> 96.251761 | V44: =G44/F44*100 -> 92.340997 | W44: =H44/G44*100 -> 92.1182 | X44: =I44/H44*100 -> 100.81055 | Y44: =J44/I44*100 -> 102.36273 | Z44: =K44/J44*100 -> 105.88331 | ... AG44: =R44/Q44*100 -> 101.97341 | AI44: =R44-G44 -> -9.97046 | AJ44: =R44/G44*100 -> 92.646582 | AK44: =(R44/G44)^(1/11)*100 -> 99.308058
A45: Экспорт на Северо-Запад | B45: в т.ч. без угля | C45: =C44-C46 -> 135.15784 | D45: =D44-D46 -> 103.61662 | E45: =E44-E46 -> 96.118973 | F45: =F44-F46 -> 97.8116 | G45: =G44-G46 -> 97.281642 | H45: =H44-H46 -> 87.225269 | I45: =I44-I46 -> 88.237667 | J45: =J44-J46 -> 90.931 | ... R45: =R44-R46 -> 115.619 | S45: =D45/C45*100 -> 76.663417 | T45: =E45/D45*100 -> 92.76405 | U45: =F45/E45*100 -> 101.76097 | V45: =G45/F45*100 -> 99.458185 | W45: =H45/G45*100 -> 89.66262 | X45: =I45/H45*100 -> 101.16067 | Y45: =J45/I45*100 -> 103.05236 | Z45: =K45/J45*100 -> 106.38396 | ... AG45: =R45/Q45*100 -> 102.14775 | AI45: =R45-G45 -> 18.337358 | AJ45: =R45/G45*100 -> 118.84976 | AK45: =(R45/G45)^(1/11)*100 -> 101.5823
A46: Экспорт на Северо-Запад | B46: Уголь | C46: 70.625549 | D46: 57.749074 | E46: 56.434706 | F46: 49.024003 | G46: 38.307818 | H46: 37.677301 | I46: 37.677301 | J46: 37.959 | K46: 39.737 | L46: 41.793 | M46: 25 | N46: 25 | O46: 20 | P46: 15 | Q46: 10 | R46: 10 | S46: =D46/C46*100 -> 81.767965 | T46: =E46/D46*100 -> 97.724002 | U46: =F46/E46*100 -> 86.868536 | V46: =G46/F46*100 -> 78.140943 | W46: =H46/G46*100 -> 98.354077 | X46: =I46/H46*100 -> 100 | Y46: =J46/I46*100 -> 100.74766 | Z46: =K46/J46*100 -> 104.684 | ... AG46: =R46/Q46*100 -> 100 | AI46: =R46-G46 -> -28.307818 | AJ46: =R46/G46*100 -> 26.104332 | AK46: =(R46/G46)^(1/11)*100 -> 88.506236
A47: Экспорт на Северо-Запад | B47: Кокс | C47: 0.758977 | D47: 0.416874 | E47: 1.091164 | F47: 0.895192 | G47: 0.811577 | H47: 0.748713 | I47: 0.868 | J47: 0.972 | K47: 1.102 | L47: 1.25 | M47: 1.25 | N47: 1.25 | O47: 1.25 | P47: 1.25 | Q47: 1.25 | R47: 1.25 | S47: =D47/C47*100 -> 54.925775 | T47: =E47/D47*100 -> 261.74911 | U47: =F47/E47*100 -> 82.040097 | V47: =G47/F47*100 -> 90.659546 | W47: =H47/G47*100 -> 92.254093 | X47: =I47/H47*100 -> 115.93227 | Y47: =J47/I47*100 -> 111.98157 | Z47: =K47/J47*100 -> 113.37449 | ... AG47: =R47/Q47*100 -> 100 | AI47: =R47-G47 -> 0.438423 | AJ47: =R47/G47*100 -> 154.02112 | AK47: =(R47/G47)^(1/11)*100 -> 104.00465
A48: Экспорт на Северо-Запад | B48: Нефтяные грузы | C48: 47.343487 | D48: 45.682756 | E48: 40.199105 | F48: 38.030872 | G48: 36.065201 | H48: 31.369038 | I48: 31.497945 | J48: 31.861 | K48: 32.228 | L48: 32.6 | M48: 33 | N48: 33 | O48: 33 | P48: 33 | Q48: 33 | R48: 33 | S48: =D48/C48*100 -> 96.492166 | T48: =E48/D48*100 -> 87.996234 | U48: =F48/E48*100 -> 94.606265 | V48: =G48/F48*100 -> 94.831381 | W48: =H48/G48*100 -> 86.978686 | X48: =I48/H48*100 -> 100.41094 | Y48: =J48/I48*100 -> 101.15263 | Z48: =K48/J48*100 -> 101.15188 | ... AG48: =R48/Q48*100 -> 100 | AI48: =R48-G48 -> -3.065201 | AJ48: =R48/G48*100 -> 91.500946 | AK48: =(R48/G48)^(1/11)*100 -> 99.195789
A49: Экспорт на Северо-Запад | B49: Руды металлические | C49: 15.124018 | D49: 8.132239 | E49: 4.254609 | F49: 3.665474 | G49: 3.386856 | H49: 2.627066 | I49: 2.639 | J49: 2.799 | K49: 2.969 | L49: 3.15 | M49: 3.318 | N49: 3.495 | O49: 3.681 | P49: 3.877 | Q49: 4.083 | R49: 4.3 | S49: =D49/C49*100 -> 53.77036 | T49: =E49/D49*100 -> 52.317806 | U49: =F49/E49*100 -> 86.153017 | V49: =G49/F49*100 -> 92.398855 | W49: =H49/G49*100 -> 77.56651 | X49: =I49/H49*100 -> 100.45427 | Y49: =J49/I49*100 -> 106.0629 | Z49: =K49/J49*100 -> 106.0736 | ... AG49: =R49/Q49*100 -> 105.31472 | AI49: =R49-G49 -> 0.913144 | AJ49: =R49/G49*100 -> 126.96141 | AK49: =(R49/G49)^(1/11)*100 -> 102.19384
A50: Экспорт на Северо-Запад | B50: Черные металлы | C50: 8.195763 | D50: 5.464453 | E50: 4.829376 | F50: 4.265669 | G50: 4.660287 | H50: 3.332911 | I50: 3.3320752 | J50: 3.683 | K50: 4.071 | L50: 4.5 | M50: 4.653 | N50: 4.811 | O50: 4.975 | P50: 5.144 | Q50: 5.319 | R50: 5.5 | S50: =D50/C50*100 -> 66.674122 | T50: =E50/D50*100 -> 88.378032 | U50: =F50/E50*100 -> 88.32754 | V50: =G50/F50*100 -> 109.25102 | W50: =H50/G50*100 -> 71.517291 | X50: =I50/H50*100 -> 99.974924 | Y50: =J50/I50*100 -> 110.53172 | Z50: =K50/J50*100 -> 110.53489 | ... AG50: =R50/Q50*100 -> 103.4029 | AI50: =R50-G50 -> 0.839713 | AJ50: =R50/G50*100 -> 118.01848 | AK50: =(R50/G50)^(1/11)*100 -> 101.5175
A51: Экспорт на Северо-Запад | B51: Лесные грузы | C51: 5.508845 | D51: 1.131258 | E51: 0.235433 | F51: 0.230556 | G51: 0.140693 | H51: 0.182677 | I51: 0.236 | J51: 0.305 | K51: 0.349 | L51: 0.4 | M51: 0.428 | N51: 0.458 | O51: 0.49 | P51: 0.524 | Q51: 0.561 | R51: 0.6 | S51: =D51/C51*100 -> 20.535303 | T51: =E51/D51*100 -> 20.81161 | U51: =F51/E51*100 -> 97.928498 | V51: =G51/F51*100 -> 61.023352 | W51: =H51/G51*100 -> 129.84086 | X51: =I51/H51*100 -> 129.18977 | Y51: =J51/I51*100 -> 129.23729 | Z51: =K51/J51*100 -> 114.42623 | ... AG51: =R51/Q51*100 -> 106.95187 | AI51: =R51-G51 -> 0.459307 | AJ51: =R51/G51*100 -> 426.46045 | AK51: =(R51/G51)^(1/11)*100 -> 114.09371
A52: Экспорт на Северо-Запад | B52: Минстройматериалы | C52: 1.827101 | D52: 2.254652 | E52: 2.289987 | F52: 2.420945 | G52: 2.339776 | H52: 1.909984 | I52: 1.922 | J52: 2.098 | K52: 2.29 | L52: 2.5 | M52: 2.5 | N52: 2.5 | O52: 2.5 | P52: 2.5 | Q52: 2.5 | R52: 2.5 | S52: =D52/C52*100 -> 123.40051 | T52: =E52/D52*100 -> 101.5672 | U52: =F52/E52*100 -> 105.71872 | V52: =G52/F52*100 -> 96.647218 | W52: =H52/G52*100 -> 81.631062 | X52: =I52/H52*100 -> 100.62912 | Y52: =J52/I52*100 -> 109.15713 | Z52: =K52/J52*100 -> 109.15157 | ... AG52: =R52/Q52*100 -> 100 | AI52: =R52-G52 -> 0.160224 | AJ52: =R52/G52*100 -> 106.84784 | AK52: =(R52/G52)^(1/11)*100 -> 100.60396
A53: Экспорт на Северо-Запад | B53: Удобрения | C53: 31.78296 | D53: 23.323146 | E53: 24.729252 | F53: 29.94673 | G53: 35.276641 | H53: 34.480448 | I53: 34.492646 | J53: 35.149 | K53: 35.818 | L53: 36.5 | M53: 37.061 | N53: 37.631 | O53: 38.21 | P53: 38.798 | Q53: 39.395 | R53: 40 | S53: =D53/C53*100 -> 73.382548 | T53: =E53/D53*100 -> 106.0288 | U53: =F53/E53*100 -> 121.09841 | V53: =G53/F53*100 -> 117.79797 | W53: =H53/G53*100 -> 97.743002 | X53: =I53/H53*100 -> 100.03538 | Y53: =J53/I53*100 -> 101.90288 | Z53: =K53/J53*100 -> 101.90333 | ... AG53: =R53/Q53*100 -> 101.53573 | AI53: =R53-G53 -> 4.723359 | AJ53: =R53/G53*100 -> 113.38948 | AK53: =(R53/G53)^(1/11)*100 -> 101.1489
A54: Экспорт на Северо-Запад | B54: Хлебные грузы | C54: 2.523236 | D54: 2.384305 | E54: 4.34851 | F54: 4.16683 | G54: 3.283839 | H54: 2.724279 | I54: 3.207 | J54: 3.564 | K54: 3.96 | L54: 4.4 | M54: 4.696 | N54: 5.012 | O54: 5.349 | P54: 5.708 | Q54: 6.092 | R54: 6.5 | S54: =D54/C54*100 -> 94.493936 | T54: =E54/D54*100 -> 182.38061 | U54: =F54/E54*100 -> 95.822017 | V54: =G54/F54*100 -> 78.809047 | W54: =H54/G54*100 -> 82.960188 | X54: =I54/H54*100 -> 117.71922 | Y54: =J54/I54*100 -> 111.1319 | Z54: =K54/J54*100 -> 111.11111 | ... AG54: =R54/Q54*100 -> 106.69731 | AI54: =R54-G54 -> 3.216161 | AJ54: =R54/G54*100 -> 197.93906 | AK54: =(R54/G54)^(1/11)*100 -> 106.40387
A55: Экспорт на Северо-Запад | B55: Прочие грузы | C55: 22.093455 | D55: 14.826937 | E55: 14.141537 | F55: 14.189332 | G55: 11.316772 | H55: 9.850153 | I55: 10.043 | J55: 10.5 | K55: 13.949 | L55: 16.7 | M55: 17.481 | N55: 18.298 | O55: 19.154 | P55: 20.05 | Q55: 20.988 | R55: 21.969 | S55: =D55/C55*100 -> 67.110088 | T55: =E55/D55*100 -> 95.377332 | U55: =F55/E55*100 -> 100.33798 | V55: =G55/F55*100 -> 79.755495 | W55: =H55/G55*100 -> 87.040306 | X55: =I55/H55*100 -> 101.95781 | Y55: =J55/I55*100 -> 104.55043 | Z55: =K55/J55*100 -> 132.84762 | ... AG55: =R55/Q55*100 -> 104.6741 | AI55: =R55-G55 -> 10.652228 | AJ55: =R55/G55*100 -> 194.1278 | AK55: =(R55/G55)^(1/11)*100 -> 106.21596
A56: Экспорт на Северо-Запад | B56: в т.ч. Грузы в контейнерах | C56: 10.846075 | D56: 5.564473 | E56: 6.751908 | F56: 7.281423 | G56: 5.942913 | H56: 5.801616 | I56: 6.289 | J56: 6.668 | K56: 9.33 | L56: 12.4 | M56: 13.015 | N56: 13.661 | O56: 14.339 | P56: 15.05 | Q56: 15.797 | R56: 16.58 | S56: =D56/C56*100 -> 51.304025 | T56: =E56/D56*100 -> 121.33958 | U56: =F56/E56*100 -> 107.84245 | V56: =G56/F56*100 -> 81.617467 | W56: =H56/G56*100 -> 97.622429 | X56: =I56/H56*100 -> 108.40083 | Y56: =J56/I56*100 -> 106.0264 | Z56: =K56/J56*100 -> 139.92202 | ... AG56: =R56/Q56*100 -> 104.95664 | AI56: =R56-G56 -> 10.637087 | AJ56: =R56/G56*100 -> 278.98776 | AK56: =(R56/G56)^(1/11)*100 -> 109.77609
A57: Экспорт на Юг-Центр | B57: Экспорт на Юг-Центр | C57: =SUM(C59:C68) -> 139.76361 | D57: =SUM(D59:D68) -> 124.42579 | E57: =SUM(E59:E68) -> 125.27877 | F57: =SUM(F59:F68) -> 113.78896 | G57: =SUM(G59:G68) -> 112.77114 | H57: =SUM(H59:H68) -> 127.01373 | I57: =SUM(I59:I68) -> 129.75292 | J57: =SUM(J59:J68) -> 131.706 | ... R57: =SUM(R59:R68) -> 146.8 | S57: =D57/C57*100 -> 89.025884 | T57: =E57/D57*100 -> 100.68553 | U57: =F57/E57*100 -> 90.82861 | V57: =G57/F57*100 -> 99.105514 | W57: =H57/G57*100 -> 112.62964 | X57: =I57/H57*100 -> 102.1566 | Y57: =J57/I57*100 -> 101.50523 | Z57: =K57/J57*100 -> 101.55498 | ... AG57: =R57/Q57*100 -> 101.32174 | AI57: =R57-G57 -> 34.028861 | AJ57: =R57/G57*100 -> 130.17515 | AK57: =(R57/G57)^(1/11)*100 -> 102.42634
A58: Экспорт на Юг-Центр | B58: в т.ч. без угля | C58: =C57-C59 -> 95.84065 | D58: =D57-D59 -> 86.126961 | E58: =E57-E59 -> 93.699038 | F58: =F57-F59 -> 96.710142 | G58: =G57-G59 -> 92.24778 | H58: =H57-H59 -> 99.839004 | I58: =I57-I59 -> 102.44973 | J58: =J57-J59 -> 104.172 | ... R58: =R57-R59 -> 116.8 | S58: =D58/C58*100 -> 89.86475 | T58: =E58/D58*100 -> 108.79176 | U58: =F58/E58*100 -> 103.21359 | V58: =G58/F58*100 -> 95.385839 | W58: =H58/G58*100 -> 108.22917 | X58: =I58/H58*100 -> 102.61494 | Y58: =J58/I58*100 -> 101.68108 | Z58: =K58/J58*100 -> 101.74327 | ... AG58: =R58/Q58*100 -> 101.36425 | AI58: =R58-G58 -> 24.55222 | AJ58: =R58/G58*100 -> 126.61551 | AK58: =(R58/G58)^(1/11)*100 -> 102.16849
A59: Экспорт на Юг-Центр | B59: Уголь | C59: 43.922965 | D59: 38.298833 | E59: 31.579732 | F59: 17.078823 | G59: 20.523359 | H59: 27.174729 | I59: 27.303182 | J59: 27.534 | K59: 27.766 | L59: 28 | M59: 28.324 | N59: 28.652 | O59: 28.983 | P59: 29.318 | Q59: 29.657 | R59: 30 | S59: =D59/C59*100 -> 87.195464 | T59: =E59/D59*100 -> 82.456121 | U59: =F59/E59*100 -> 54.081596 | V59: =G59/F59*100 -> 120.16846 | W59: =H59/G59*100 -> 132.40878 | X59: =I59/H59*100 -> 100.47269 | Y59: =J59/I59*100 -> 100.84539 | Z59: =K59/J59*100 -> 100.84259 | ... AG59: =R59/Q59*100 -> 101.15656 | AI59: =R59-G59 -> 9.476641 | AJ59: =R59/G59*100 -> 146.1749 | AK59: =(R59/G59)^(1/11)*100 -> 103.51146
A60: Экспорт на Юг-Центр | B60: Кокс | C60: 3.308708 | D60: 2.167081 | E60: 1.485167 | F60: 1.790669 | G60: 1.159675 | H60: 0.858601 | I60: 0.92 | J60: 0.966 | K60: 1.014 | L60: 1.065 | M60: 1.071 | N60: 1.077 | O60: 1.083 | P60: 1.089 | Q60: 1.095 | R60: 1.1 | S60: =D60/C60*100 -> 65.49629 | T60: =E60/D60*100 -> 68.533064 | U60: =F60/E60*100 -> 120.57021 | V60: =G60/F60*100 -> 64.762108 | W60: =H60/G60*100 -> 74.038071 | X60: =I60/H60*100 -> 107.15105 | Y60: =J60/I60*100 -> 105 | Z60: =K60/J60*100 -> 104.96894 | ... AG60: =R60/Q60*100 -> 100.45662 | AI60: =R60-G60 -> -0.059675 | AJ60: =R60/G60*100 -> 94.854162 | AK60: =(R60/G60)^(1/11)*100 -> 99.520882
A61: Экспорт на Юг-Центр | B61: Нефтяные грузы | C61: 34.433592 | D61: 32.308631 | E61: 34.162089 | F61: 34.318222 | G61: 30.454018 | H61: 33.013436 | I61: 34.229217 | J61: 34.293 | K61: 34.357 | L61: 34.42 | M61: 34.598 | N61: 34.777 | O61: 34.957 | P61: 35.137 | Q61: 35.318 | R61: 35.5 | S61: =D61/C61*100 -> 93.828814 | T61: =E61/D61*100 -> 105.73673 | U61: =F61/E61*100 -> 100.45704 | V61: =G61/F61*100 -> 88.740081 | W61: =H61/G61*100 -> 108.4042 | X61: =I61/H61*100 -> 103.68269 | Y61: =J61/I61*100 -> 100.18634 | Z61: =K61/J61*100 -> 100.18663 | ... AG61: =R61/Q61*100 -> 100.51532 | AI61: =R61-G61 -> 5.045982 | AJ61: =R61/G61*100 -> 116.56918 | AK61: =(R61/G61)^(1/11)*100 -> 101.40353
A62: Экспорт на Юг-Центр | B62: Руды металлические | C62: 7.185599 | D62: 4.506545 | E62: 3.096364 | F62: 3.973956 | G62: 6.748244 | H62: 9.154384 | I62: 9.299 | J62: 9.382 | K62: 9.466 | L62: 9.55 | M62: 9.624 | N62: 9.698 | O62: 9.773 | P62: 9.848 | Q62: 9.924 | R62: 10 | S62: =D62/C62*100 -> 62.716344 | T62: =E62/D62*100 -> 68.708157 | U62: =F62/E62*100 -> 128.34266 | V62: =G62/F62*100 -> 169.81174 | W62: =H62/G62*100 -> 135.65579 | X62: =I62/H62*100 -> 101.57975 | Y62: =J62/I62*100 -> 100.89257 | Z62: =K62/J62*100 -> 100.89533 | ... AG62: =R62/Q62*100 -> 100.76582 | AI62: =R62-G62 -> 3.251756 | AJ62: =R62/G62*100 -> 148.1867 | AK62: =(R62/G62)^(1/11)*100 -> 103.64017
A63: Экспорт на Юг-Центр | B63: Черные металлы | C63: 15.974175 | D63: 13.308997 | E63: 14.57964 | F63: 14.157852 | G63: 14.476591 | H63: 14.553363 | I63: 14.830717 | J63: 15.002 | K63: 15.175 | L63: 15.35 | M63: 15.504 | N63: 15.66 | O63: 15.818 | P63: 15.977 | Q63: 16.138 | R63: 16.3 | S63: =D63/C63*100 -> 83.315708 | T63: =E63/D63*100 -> 109.54725 | U63: =F63/E63*100 -> 97.107007 | V63: =G63/F63*100 -> 102.25132 | W63: =H63/G63*100 -> 100.53032 | X63: =I63/H63*100 -> 101.90577 | Y63: =J63/I63*100 -> 101.15492 | Z63: =K63/J63*100 -> 101.15318 | ... AG63: =R63/Q63*100 -> 101.00384 | AI63: =R63-G63 -> 1.823409 | AJ63: =R63/G63*100 -> 112.59557 | AK63: =(R63/G63)^(1/11)*100 -> 101.08431
A64: Экспорт на Юг-Центр | B64: Лесные грузы | C64: 4.945867 | D64: 4.152859 | E64: 3.938803 | F64: 3.843591 | G64: 3.635925 | H64: 2.733359 | I64: 2.8 | J64: 2.972 | K64: 3.155 | L64: 3.35 | M64: 3.519 | N64: 3.696 | O64: 3.882 | P64: 4.078 | Q64: 4.284 | R64: 4.5 | S64: =D64/C64*100 -> 83.966249 | T64: =E64/D64*100 -> 94.845575 | U64: =F64/E64*100 -> 97.582717 | V64: =G64/F64*100 -> 94.597084 | W64: =H64/G64*100 -> 75.176441 | X64: =I64/H64*100 -> 102.43806 | Y64: =J64/I64*100 -> 106.14286 | Z64: =K64/J64*100 -> 106.15747 | ... AG64: =R64/Q64*100 -> 105.04202 | AI64: =R64-G64 -> 0.864075 | AJ64: =R64/G64*100 -> 123.76493 | AK64: =(R64/G64)^(1/11)*100 -> 101.95721
A65: Экспорт на Юг-Центр | B65: Минстройматериалы | C65: 2.850021 | D65: 1.932917 | E65: 1.559152 | F65: 1.532738 | G65: 1.452796 | H65: 1.299182 | I65: 1.345 | J65: 1.52 | K65: 1.717 | L65: 1.94 | M65: 2.01 | N65: 2.083 | O65: 2.158 | P65: 2.236 | Q65: 2.317 | R65: 2.4 | S65: =D65/C65*100 -> 67.821149 | T65: =E65/D65*100 -> 80.663163 | U65: =F65/E65*100 -> 98.305874 | V65: =G65/F65*100 -> 94.784366 | W65: =H65/G65*100 -> 89.42632 | X65: =I65/H65*100 -> 103.52668 | Y65: =J65/I65*100 -> 113.01115 | Z65: =K65/J65*100 -> 112.96053 | ... AG65: =R65/Q65*100 -> 103.58222 | AI65: =R65-G65 -> 0.947204 | AJ65: =R65/G65*100 -> 165.19869 | AK65: =(R65/G65)^(1/11)*100 -> 104.66917
A66: Экспорт на Юг-Центр | B66: Удобрения | C66: 4.766987 | D66: 4.758313 | E66: 4.549313 | F66: 4.86407 | G66: 4.860487 | H66: 4.840865 | I66: 5.209 | J66: 5.687 | K66: 6.209 | L66: 6.78 | M66: 7.081 | N66: 7.396 | O66: 7.725 | P66: 8.068 | Q66: 8.426 | R66: 8.8 | S66: =D66/C66*100 -> 99.81804 | T66: =E66/D66*100 -> 95.607687 | U66: =F66/E66*100 -> 106.91878 | V66: =G66/F66*100 -> 99.926337 | W66: =H66/G66*100 -> 99.596296 | X66: =I66/H66*100 -> 107.60474 | Y66: =J66/I66*100 -> 109.17643 | Z66: =K66/J66*100 -> 109.17883 | ... AG66: =R66/Q66*100 -> 104.43864 | AI66: =R66-G66 -> 3.939513 | AJ66: =R66/G66*100 -> 181.05182 | AK66: =(R66/G66)^(1/11)*100 -> 105.54475
A67: Экспорт на Юг-Центр | B67: Хлебные грузы | C67: 11.225685 | D67: 11.631914 | E67: 18.729252 | F67: 18.190903 | G67: 13.692583 | H67: 18.488778 | I67: 18.6678 | J67: 19.118 | K67: 19.579 | L67: 20.05 | M67: 20.285 | N67: 20.522 | O67: 20.761 | P67: 21.005 | Q67: 21.251 | R67: 21.5 | S67: =D67/C67*100 -> 103.61875 | T67: =E67/D67*100 -> 161.01608 | U67: =F67/E67*100 -> 97.125625 | V67: =G67/F67*100 -> 75.271596 | W67: =H67/G67*100 -> 135.02769 | X67: =I67/H67*100 -> 100.96827 | Y67: =J67/I67*100 -> 102.41164 | Z67: =K67/J67*100 -> 102.41134 | ... AG67: =R67/Q67*100 -> 101.17171 | AI67: =R67-G67 -> 7.807417 | AJ67: =R67/G67*100 -> 157.01931 | AK67: =(R67/G67)^(1/11)*100 -> 104.18709
A68: Экспорт на Юг-Центр | B68: Прочие грузы | C68: 11.150016 | D68: 11.359704 | E68: 11.599258 | F68: 14.038141 | G68: 15.767461 | H68: 14.897036 | I68: 15.149 | J68: 15.232 | K68: 15.316 | L68: 15.4 | M68: 15.609 | N68: 15.821 | O68: 16.036 | P68: 16.254 | Q68: 16.475 | R68: 16.7 | S68: =D68/C68*100 -> 101.88061 | T68: =E68/D68*100 -> 102.1088 | U68: =F68/E68*100 -> 121.0262 | V68: =G68/F68*100 -> 112.31873 | W68: =H68/G68*100 -> 94.479612 | X68: =I68/H68*100 -> 101.69137 | Y68: =J68/I68*100 -> 100.54789 | Z68: =K68/J68*100 -> 100.55147 | ... AG68: =R68/Q68*100 -> 101.36571 | AI68: =R68-G68 -> 0.932539 | AJ68: =R68/G68*100 -> 105.91433 | AK68: =(R68/G68)^(1/11)*100 -> 100.52373
A69: Экспорт на Юг-Центр | B69: в т.ч. Грузы в контейнерах | C69: 4.282215 | D69: 5.435195 | E69: 5.36223 | F69: 7.34074 | G69: 9.105106 | H69: 9.308085 | I69: 9.402 | J69: 9.597 | K69: 9.796 | L69: 10 | M69: 10.309 | N69: 10.627 | O69: 10.955 | P69: 11.293 | Q69: 11.641 | R69: 12 | S69: =D69/C69*100 -> 126.92485 | T69: =E69/D69*100 -> 98.657546 | U69: =F69/E69*100 -> 136.89715 | V69: =G69/F69*100 -> 124.03526 | W69: =H69/G69*100 -> 102.22929 | X69: =I69/H69*100 -> 101.00896 | Y69: =J69/I69*100 -> 102.07403 | Z69: =K69/J69*100 -> 102.07356 | ... AG69: =R69/Q69*100 -> 103.08393 | AI69: =R69-G69 -> 2.894894 | AJ69: =R69/G69*100 -> 131.79418 | AK69: =(R69/G69)^(1/11)*100 -> 102.5415
A70: Экспорт на Восток | B70: Экспорт на Восток | C70: =SUM(C72:C81) -> 144.50848 | D70: =SUM(D72:D81) -> 143.4551 | E70: =SUM(E72:E81) -> 153.83402 | F70: =SUM(F72:F81) -> 153.555 | G70: =SUM(G72:G81) -> 163.48543 | H70: =SUM(H72:H81) -> 168.41538 | I70: =SUM(I72:I81) -> 168.47563 | J70: =SUM(J72:J81) -> 174.077 | ... R70: =SUM(R72:R81) -> 274.04577 | S70: =D70/C70*100 -> 99.271057 | T70: =E70/D70*100 -> 107.23496 | U70: =F70/E70*100 -> 99.81862 | V70: =G70/F70*100 -> 106.46702 | W70: =H70/G70*100 -> 103.01553 | X70: =I70/H70*100 -> 100.03577 | Y70: =J70/I70*100 -> 103.32474 | Z70: =K70/J70*100 -> 100 | ... AG70: =R70/Q70*100 -> 100 | AI70: =R70-G70 -> 110.56035 | AJ70: =R70/G70*100 -> 167.62703 | AK70: =(R70/G70)^(1/11)*100 -> 104.80812
A71: Экспорт на Восток | B71: в т.ч. без угля | C71: =C70-C72 -> 43.967114 | D71: =D70-D72 -> 42.383442 | E71: =E70-E72 -> 46.090645 | F71: =F70-F72 -> 42.104902 | G71: =G70-G72 -> 45.288655 | H71: =H70-H72 -> 48.449592 | I71: =I70-I72 -> 50.768628 | J71: =J70-J72 -> 56.37 | ... R71: =R70-R72 -> 75.8 | S71: =D71/C71*100 -> 96.398053 | T71: =E71/D71*100 -> 108.74682 | U71: =F71/E71*100 -> 91.352382 | V71: =G71/F71*100 -> 107.56148 | W71: =H71/G71*100 -> 106.97953 | X71: =I71/H71*100 -> 104.78649 | Y71: =J71/I71*100 -> 111.03314 | Z71: =K71/J71*100 -> 102.67873 | ... AG71: =R71/Q71*100 -> 100 | AI71: =R71-G71 -> 30.511345 | AJ71: =R71/G71*100 -> 167.37083 | AK71: =(R71/G71)^(1/11)*100 -> 104.79354
A72: Экспорт на Восток | B72: Уголь | C72: 100.54137 | D72: 101.07166 | E72: 107.74338 | F72: 111.4501 | G72: 118.19677 | H72: 119.96579 | I72: 117.707 | J72: 117.707 | K72: 116.197 | L72: 114.707 | M72: 144.89677 | N72: 144.89677 | O72: 160.884 | P72: 178.635 | Q72: 198.24577 | R72: 198.24577 | S72: =D72/C72*100 -> 100.52743 | T72: =E72/D72*100 -> 106.60098 | U72: =F72/E72*100 -> 103.44032 | V72: =G72/F72*100 -> 106.05354 | W72: =H72/G72*100 -> 101.49667 | X72: =I72/H72*100 -> 98.117139 | Y72: =J72/I72*100 -> 100 | Z72: =K72/J72*100 -> 98.717154 | ... AG72: =R72/Q72*100 -> 100 | AI72: =R72-G72 -> 80.049 | AJ72: =R72/G72*100 -> 167.7252 | AK72: =(R72/G72)^(1/11)*100 -> 104.81369
A73: Экспорт на Восток | B73: Кокс | C73: 0.053873 | D73: 0.153405 | E73: 0.068252 | F73: 0.068922 | G73: 0.014931 | H73: 0.076628 | I73: 0.076628 | J73: 0.1 | K73: 0.1 | L73: 0.1 | M73: 0.1 | N73: 0.1 | O73: 0.1 | P73: 0.1 | Q73: 0.1 | R73: 0.1 | S73: =D73/C73*100 -> 284.75303 | T73: =E73/D73*100 -> 44.491379 | U73: =F73/E73*100 -> 100.98166 | V73: =G73/F73*100 -> 21.66362 | W73: =H73/G73*100 -> 513.21412 | AI73: =R73-G73 -> 0.085069 | AJ73: =R73/G73*100 -> 669.74751 | AK73: =(R73/G73)^(1/11)*100 -> 118.87289
A74: Экспорт на Восток | B74: Нефтяные грузы | C74: 9.654961 | D74: 8.955486 | E74: 9.506745 | F74: 9.473835 | G74: 9.877497 | H74: 10.504074 | I74: 10.501 | J74: 10.577 | K74: 11.019 | L74: 11.7 | M74: 12.65 | N74: 12.65 | O74: 13.147 | P74: 13.663 | Q74: 14.2 | R74: 14.2 | S74: =D74/C74*100 -> 92.755279 | T74: =E74/D74*100 -> 106.15555 | U74: =F74/E74*100 -> 99.653825 | V74: =G74/F74*100 -> 104.26081 | W74: =H74/G74*100 -> 106.34348 | X74: =I74/H74*100 -> 99.970735 | Y74: =J74/I74*100 -> 100.72374 | Z74: =K74/J74*100 -> 104.17888 | ... AG74: =R74/Q74*100 -> 100 | AI74: =R74-G74 -> 4.322503 | AJ74: =R74/G74*100 -> 143.76112 | AK74: =(R74/G74)^(1/11)*100 -> 103.35489
A75: Экспорт на Восток | B75: Руды металлические | C75: 5.2227 | D75: 5.685057 | E75: 7.906655 | F75: 8.790781 | G75: 10.116291 | H75: 11.245598 | I75: 11.37 | J75: 11.576 | K75: 11.786 | L75: 12 | M75: 12.36 | N75: 12.36 | O75: 12.729 | P75: 13.109 | Q75: 13.5 | R75: 13.5 | S75: =D75/C75*100 -> 108.85283 | T75: =E75/D75*100 -> 139.07785 | U75: =F75/E75*100 -> 111.18205 | V75: =G75/F75*100 -> 115.07841 | W75: =H75/G75*100 -> 111.16325 | X75: =I75/H75*100 -> 101.10623 | Y75: =J75/I75*100 -> 101.81179 | Z75: =K75/J75*100 -> 101.8141 | ... AG75: =R75/Q75*100 -> 100 | AI75: =R75-G75 -> 3.383709 | AJ75: =R75/G75*100 -> 133.44812 | AK75: =(R75/G75)^(1/11)*100 -> 102.65782
A76: Экспорт на Восток | B76: Черные металлы | C76: 5.476628 | D76: 5.098365 | E76: 3.150062 | F76: 2.031529 | G76: 1.682044 | H76: 1.7706 | I76: 2.301 | J76: 2.558 | K76: 2.843 | L76: 3.16 | M76: 3.86 | N76: 3.86 | O76: 4.001 | P76: 4.148 | Q76: 4.3 | R76: 4.3 | S76: =D76/C76*100 -> 93.093141 | T76: =E76/D76*100 -> 61.785729 | U76: =F76/E76*100 -> 64.491715 | V76: =G76/F76*100 -> 82.796948 | W76: =H76/G76*100 -> 105.26478 | X76: =I76/H76*100 -> 129.95595 | Y76: =J76/I76*100 -> 111.16906 | Z76: =K76/J76*100 -> 111.14152 | ... AG76: =R76/Q76*100 -> 100 | AI76: =R76-G76 -> 2.617956 | AJ76: =R76/G76*100 -> 255.64135 | AK76: =(R76/G76)^(1/11)*100 -> 108.9074
A77: Экспорт на Восток | B77: Лесные грузы | C77: 8.886336 | D77: 4.662872 | E77: 3.697385 | F77: 2.975407 | G77: 2.322048 | H77: 2.058234 | I77: 2.5 | J77: 2.5 | K77: 2.5 | L77: 2.5 | M77: 2.5 | N77: 2.5 | O77: 2.797 | P77: 3.129 | Q77: 3.5 | R77: 3.5 | S77: =D77/C77*100 -> 52.47238 | T77: =E77/D77*100 -> 79.294156 | U77: =F77/E77*100 -> 80.47328 | V77: =G77/F77*100 -> 78.041357 | W77: =H77/G77*100 -> 88.638736 | X77: =I77/H77*100 -> 121.46335 | Y77: =J77/I77*100 -> 100 | Z77: =K77/J77*100 -> 100 | ... AG77: =R77/Q77*100 -> 100 | AI77: =R77-G77 -> 1.177952 | AJ77: =R77/G77*100 -> 150.72901 | AK77: =(R77/G77)^(1/11)*100 -> 103.80056
A78: Экспорт на Восток | B78: Минстройматериалы | C78: 0.186642 | D78: 0.154734 | E78: 0.138783 | F78: 0.142855 | G78: 0.104144 | H78: 0.1158 | I78: 0.167 | J78: 0.177 | K78: 0.188 | L78: 0.2 | M78: 0.2 | N78: 0.2 | O78: 0.2 | P78: 0.2 | Q78: 0.2 | R78: 0.2 | S78: =D78/C78*100 -> 82.904169 | T78: =E78/D78*100 -> 89.691341 | U78: =F78/E78*100 -> 102.93408 | V78: =G78/F78*100 -> 72.901894 | W78: =H78/G78*100 -> 111.1922 | X78: =I78/H78*100 -> 144.21416 | Y78: =J78/I78*100 -> 105.98802 | Z78: =K78/J78*100 -> 106.21469 | ... AG78: =R78/Q78*100 -> 100 | AI78: =R78-G78 -> 0.095856 | AJ78: =R78/G78*100 -> 192.04179 | AK78: =(R78/G78)^(1/11)*100 -> 106.11169
A79: Экспорт на Восток | B79: Удобрения | C79: 2.13024 | D79: 1.638734 | E79: 1.434872 | F79: 1.431012 | G79: 2.326694 | H79: 2.606422 | I79: 2.75 | J79: 3 | K79: 3 | L79: 3 | M79: 3 | N79: 3 | O79: 3 | P79: 3 | Q79: 3 | R79: 3 | S79: =D79/C79*100 -> 76.927201 | T79: =E79/D79*100 -> 87.559787 | U79: =F79/E79*100 -> 99.730986 | V79: =G79/F79*100 -> 162.59081 | W79: =H79/G79*100 -> 112.02255 | X79: =I79/H79*100 -> 105.50862 | Y79: =J79/I79*100 -> 109.09091 | Z79: =K79/J79*100 -> 100 | ... AG79: =R79/Q79*100 -> 100 | AI79: =R79-G79 -> 0.673306 | AJ79: =R79/G79*100 -> 128.93831 | AK79: =(R79/G79)^(1/11)*100 -> 102.33748
A80: Экспорт на Восток | B80: Хлебные грузы | C80: 0.874522 | D80: 0.68543 | E80: 1.543743 | F80: 1.076125 | G80: 0.686623 | H80: 1.039 | I80: 1.098 | J80: 1.2 | K80: 1.2 | L80: 1.2 | M80: 1.2 | N80: 1.2 | O80: 1.423 | P80: 1.687 | Q80: 2 | R80: 2 | S80: =D80/C80*100 -> 78.377674 | T80: =E80/D80*100 -> 225.22256 | U80: =F80/E80*100 -> 69.708818 | V80: =G80/F80*100 -> 63.805134 | W80: =H80/G80*100 -> 151.3203 | X80: =I80/H80*100 -> 105.67854 | Y80: =J80/I80*100 -> 109.28962 | Z80: =K80/J80*100 -> 100 | ... AG80: =R80/Q80*100 -> 100 | AI80: =R80-G80 -> 1.313377 | AJ80: =R80/G80*100 -> 291.28066 | AK80: =(R80/G80)^(1/11)*100 -> 110.20725
A81: Экспорт на Восток | B81: Прочие грузы | C81: 11.481212 | D81: 15.349359 | E81: 18.644148 | F81: 16.114436 | G81: 18.158383 | H81: 19.033236 | I81: 20.005 | J81: 24.682 | K81: 25.244 | L81: 28.22 | M81: 33.23 | N81: 33.23 | O81: 33.72 | P81: 34.27 | Q81: 35 | R81: 35 | S81: =D81/C81*100 -> 133.6911 | T81: =E81/D81*100 -> 121.46532 | U81: =F81/E81*100 -> 86.431603 | V81: =G81/F81*100 -> 112.68395 | W81: =H81/G81*100 -> 104.8179 | X81: =I81/H81*100 -> 105.10562 | Y81: =J81/I81*100 -> 123.37916 | Z81: =K81/J81*100 -> 102.27696 | ... AG81: =R81/Q81*100 -> 100 | AI81: =R81-G81 -> 16.841617 | AJ81: =R81/G81*100 -> 192.74844 | AK81: =(R81/G81)^(1/11)*100 -> 106.14713
A82: Экспорт на Восток | B82: в т.ч. Грузы в контейнерах | C82: 9.868019 | D82: 13.212969 | E82: 15.262896 | F82: 13.191319 | G82: 14.908672 | H82: 14.819369 | I82: 15.796 | J82: 19.174 | K82: 19.438 | L82: 22 | M82: 26.6 | N82: 26.6 | O82: 26.733 | P82: 26.866 | Q82: 27 | R82: 27 | S82: =D82/C82*100 -> 133.89687 | T82: =E82/D82*100 -> 115.51451 | U82: =F82/E82*100 -> 86.427366 | V82: =G82/F82*100 -> 113.01881 | W82: =H82/G82*100 -> 99.401 | X82: =I82/H82*100 -> 106.59023 | Y82: =J82/I82*100 -> 121.38516 | Z82: =K82/J82*100 -> 101.37686 | ... AG82: =R82/Q82*100 -> 100 | AI82: =R82-G82 -> 12.091328 | AJ82: =R82/G82*100 -> 181.10265 | AK82: =(R82/G82)^(1/11)*100 -> 105.54744

Sheet Уголь_эластика_внутр
AO1: 0.363
B2: параметры перевозок | X2: параметры расчета тарифа | AC2: экономика перевозок | AS2: Примечание | AT2: Коэффициент загрузки предприятия | AU2: Изменение тарифа ОАО "РЖД"
A3: сцеп цены | B3: Код группы груза | C3: Группа груза | D3: Код груза | E3: Наим груза | F3: Вид груза | G3: Дор отпр | H3: Дор наз | I3: Станц отпр РФ | J3: Станц назн РФ | K3: Средняя дальность(км) | L3: Род вагона | M3: Вид перевозки | N3: Признак контейнерной отправки | O3: Направление | P3: ОКПО компании | Q3: Компания отправителя | R3: Холдинг отправителя | S3: Объем перевозок (тн) | T3: Грузооборот, ткм | U3: Кол-во вагонов | V3: Кол-во контейнеров | W3: Провозная плата, руб | X3: Загрузка вагона | Y3: Категория отправки | Z3: Груженый рейс, дней | AA3: Порожний рейс, дней | AB3: Погрузка-разгрузка, дней | AC3: Расходы по оплате услуг ОАО 'РЖД', руб. за тонну гружёный рейс | AD3: Расходы по оплате услуг ОАО 'РЖД', руб. за тонну порожний рейс | AE3: Расходы по оплате услуг ОАО 'РЖД', руб. за тонну общая стоимость | AF3: Расходы по оплате услуг операторов, руб. за тонну | AG3: Расходы на перевалку, руб. за тонну | AH3: Акциз/пошлина | AI3: Себестоимость добычи/производства, руб. т. | AJ3: Стоимость 1 тонны на рынке, руб./т. | AK3: Стоимость 1 тонны на рынке, $/т. | AL3: Общие транспортные расходы, руб. за тонну | AM3: Нетбэк, руб. за тонну | AN3: Общие расходы, руб. за тонну | AO3: Маржинальность | AP3: Транспортная составляющая в цене % | AQ3: Инфраструктурная составляющая в цене % | AR3: Инфраструктурная составляющая в транспортных затратах | AU3: -0.25 | AV3: -0.245 | AW3: -0.24 | AX3: -0.235 | AY3: -0.23 | AZ3: -0.225 | BA3: -0.22 | BB3: -0.215 | BC3: -0.21 | BD3: -0.205 | BE3: -0.2 | BF3: -0.195 | BG3: -0.19 | BH3: -0.185 | BI3: -0.18 | BJ3: -0.175 | BK3: -0.17 | BL3: -0.165 | BM3: -0.16 | BN3: -0.155 | BO3: -0.15 | BP3: -0.145 | BQ3: -0.14 | BR3: -0.135 | BS3: -0.13 | BT3: -0.125 | BU3: -0.12 | BV3: -0.115 | BW3: -0.11 | BX3: -0.105 | BY3: -0.1 | BZ3: -0.095 | CA3: -0.09 | CB3: -0.085 | CC3: -0.08 | CD3: -0.075 | CE3: -0.07 | CF3: -0.065 | CG3: -0.06 | CH3: -0.055 | CI3: -0.05 | CJ3: -0.045 | CK3: -0.04 | CL3: -0.035 | CM3: -0.03 | CN3: -0.025 | CO3: -0.02 | CP3: -0.015 | CQ3: -0.01 | CR3: -0.005 | CS3: 0 | CT3: 0.005 | CU3: 0.01 | CV3: 0.015 | CW3: 0.02 | CX3: 0.025 | CY3: 0.03 | CZ3: 0.035 | DA3: 0.04 | DB3: 0.045 | DC3: 0.05 | DD3: 0.055 | DE3: 0.06 | DF3: 0.065 | DG3: 0.07 | DH3: 0.075 | DI3: 0.08 | DJ3: 0.085 | DK3: 0.09 | DL3: 0.095 | DM3: 0.1 | DN3: 0.105 | DO3: 0.11 | DP3: 0.115 | DQ3: 0.12 | DR3: 0.125 | DS3: 0.13 | DT3: 0.135 | DU3: 0.14 | DV3: 0.145 | DW3: 0.15 | DX3: 0.155 | DY3: 0.16 | DZ3: 0.165 | EA3: 0.17 | EB3: 0.175 | EC3: 0.18 | ED3: 0.185 | EE3: 0.19 | EF3: 0.195 | EG3: 0.2 | EH3: 0.205 | EI3: 0.21 | EJ3: 0.215 | EK3: 0.22 | EL3: 0.225 | EM3: 0.23 | EN3: 0.235 | EO3: 0.24 | EP3: 0.245 | EQ3: 0.25 | ER3: 0.255 | ES3: 0.26 | ET3: 0.265 | EU3: 0.27 | EV3: 0.275 | EW3: 0.28 | EX3: 0.285 | EY3: 0.29 | EZ3: 0.295 | FA3: 0.3 | FB3: 0.305 | FC3: 0.31 | FD3: 0.315 | FE3: 0.32 | FF3: 0.325 | FG3: 0.33 | FH3: 0.335 | FI3: 0.34 | FJ3: 0.345 | FK3: 0.35 | FL3: 0.355 | FM3: 0.36 | FN3: 0.365 | FO3: 0.37 | FP3: 0.375 | FQ3: 0.38 | FR3: 0.385 | FS3: 0.39 | FT3: 0.395 | FU3: 0.4 | FV3: 0.405 | FW3: 0.41 | FX3: 0.415 | FY3: 0.42 | FZ3: 0.425 | GA3: 0.43 | GB3: 0.435 | GC3: 0.44 | GD3: 0.445 | GE3: 0.45 | GF3: 0.455 | GG3: 0.46 | GH3: 0.465 | GI3: 0.47 | GJ3: 0.475 | GK3: 0.48 | GL3: 0.485 | GM3: 0.49 | GN3: 0.495 | GO3: 0.5 | GP3: 0.494
B4: 1 | C4: Уголь каменный | D4: 16109 | E4: УГ БУР НЕПОДМОС | F4: уголь энергетический (кроме антрацита) | G4: КРС | H4: КРС | I4: ЗАОЗЕРНАЯ | J4: БАЗАИХА | K4: 146 | L4: полувагон | M4: Внутр. перевозки | N4: неконтейнерная | O4: Восточное | P4: 81213597 | Q4: АО "СУЭК-КРАСНОЯРСК" | R4: АО "СУЭК" | S4: 2221765 | T4: 324379201 | U4: 31173 | W4: 451614471 | X4: 75 | Y4: маршрутная | Z4: 3 | AA4: 3 | AB4: 4 | AC4: 208.05 | AD4: 64.36 | AE4: 281.19 | AF4: ='Цены,перевалка,аренда'!$C$26*SUM(Уголь_эластика_внутр!Z4+Уголь_эластика_внутр!AA4+Уголь_эластика_внутр!AB4)/Уголь_эластика_внутр!X4 -> 133.33333 | AI4: 445.5 | AJ4: ='Цены,перевалка,аренда'!$D$9 -> 1750 | AK4: =AJ4/'Цены,перевалка,аренда'!$C$1 -> 22.934127 | AL4: =AE4+AF4+AG4 -> 414.52333 | AM4: =AJ4-AL4 -> 1335.4767 | AN4: =AI4+AH4+AG4+AF4+AE4 -> 860.02333 | AO4: =(AJ4-AN4)/AJ4 -> 0.5085581 | AP4: =AL4/AJ4 -> 0.23687048 | AQ4: =AE4/AJ4 -> 0.16068 | AR4: =AE4/AL4 -> 0.67834541 | AS4: Красноярская ТЭЦ | AU4: 1 | AV4: 1 | AW4: 1 | AX4: 1 | AY4: 1 | AZ4: 1 | BA4: 1 | BB4: 1 | BC4: 1 | BD4: 1 | BE4: 1 | BF4: 1 | BG4: 1 | BH4: 1 | BI4: 1 | BJ4: 1 | BK4: 1 | BL4: 1 | BM4: 1 | BN4: 1 | BO4: 1 | BP4: 1 | BQ4: 1 | BR4: 1 | BS4: 1 | BT4: 1 | BU4: 1 | BV4: 1 | BW4: 1 | BX4: 1 | BY4: 1 | BZ4: 1 | CA4: 1 | CB4: 1 | CC4: 1 | CD4: 1 | CE4: 1 | CF4: 1 | CG4: 1 | CH4: 1 | CI4: 1 | CJ4: 1 | CK4: 1 | CL4: 1 | CM4: 1 | CN4: 1 | CO4: 1 | CP4: 1 | CQ4: 1 | CR4: 1 | CS4: 1 | CT4: 1 | CU4: 1 | CV4: 1 | CW4: 1 | CX4: 1 | CY4: 1 | CZ4: 1 | DA4: 1 | DB4: 1 | DC4: 1 | DD4: 1 | DE4: 1 | DF4: 1 | DG4: 1 | DH4: 1 | DI4: 1 | DJ4: 1 | DK4: 1 | DL4: 1 | DM4: 1 | DN4: 1 | DO4: 1 | DP4: 1 | DQ4: 1 | DR4: 1 | DS4: 1 | DT4: 1 | DU4: 1 | DV4: 1 | DW4: 1 | DX4: 1 | DY4: 1 | DZ4: 1 | EA4: 1 | EB4: 1 | EC4: 1 | ED4: 1 | EE4: 1 | EF4: 1 | EG4: 1 | EH4: 1 | EI4: 1 | EJ4: 1 | EK4: 1 | EL4: 1 | EM4: 1 | EN4: 1 | EO4: 1 | EP4: 1 | EQ4: 1 | ER4: 1 | ES4: 1 | ET4: 1 | EU4: 1 | EV4: 1 | EW4: 1 | EX4: 1 | EY4: 1 | EZ4: 1 | FA4: 1 | FB4: 1 | FC4: 1 | FD4: 1 | FE4: 1 | FF4: 1 | FG4: 1 | FH4: 1 | FI4: 1 | FJ4: 1 | FK4: 1 | FL4: 1 | FM4: 1 | FN4: 1 | FO4: 1 | FP4: 1 | FQ4: 1 | FR4: 1 | FS4: 1 | FT4: 1 | FU4: 1 | FV4: 1 | FW4: 1 | FX4: 1 | FY4: 1 | FZ4: 1 | GA4: 1 | GB4: 1 | GC4: 1 | GD4: 1 | GE4: 1 | GF4: 1 | GG4: 1 | GH4: 1 | GI4: 1 | GJ4: 1 | GK4: 1 | GL4: 1 | GM4: 1 | GN4: 1 | GO4: 1 | GP4: =HLOOKUP($GP$3,$AU$3:$GO$27,3,TRUE) -> 1
B5: 1 | C5: Уголь каменный | D5: 16112 | E5: УГОЛЬ Д | F5: уголь энергетический (кроме антрацита) | G5: КРС | H5: СЕВ | I5: ЧЕРНОГ.КОПИ | J5: СОЛЬВЫЧЕГОДС | K5: 3616 | L5: полувагон | M5: Внутр. перевозки | N5: неконтейнерная | O5: Северо-Западное | P5: 81195103 | Q5: ООО "СУЭК-ХАКАСИЯ" | R5: АО "СУЭК" | S5: 23435 | T5: 84729325 | U5: 338 | W5: 33346998 | X5: 69 | Y5: группа вагонов | Z5: 12 | AA5: 12 | AB5: 4 | AC5: 1566.84 | AD5: 899 | AE5: 2516.12 | AF5: ='Цены,перевалка,аренда'!$C$27*SUM(Уголь_эластика_внутр!Z5+Уголь_эластика_внутр!AA5+Уголь_эластика_внутр!AB5)/Уголь_эластика_внутр!X5 -> 284.05797 | AI5: 2020 | AJ5: ='Цены,перевалка,аренда'!$D$8 -> 3300 | AK5: =AJ5/'Цены,перевалка,аренда'!$C$1 -> 43.24721 | AL5: =AE5+AF5+AG5 -> 2800.178 | AM5: =AJ5-AL5 -> 499.82203 | AN5: =AI5+AH5+AG5+AF5+AE5 -> 4820.178 | AO5: =(AJ5-AN5)/AJ5 -> -0.46065999 | AP5: =AL5/AJ5 -> 0.84853878 | AQ5: =AE5/AJ5 -> 0.76246061 | AR5: =AE5/AL5 -> 0.89855717 | AS5: Перевозки для нужд ОАО "РЖД" | AU5: 1 | AV5: 1 | AW5: 1 | AX5: 1 | AY5: 1 | AZ5: 1 | BA5: 1 | BB5: 1 | BC5: 1 | BD5: 1 | BE5: 1 | BF5: 1 | BG5: 1 | BH5: 1 | BI5: 1 | BJ5: 1 | BK5: 1 | BL5: 1 | BM5: 1 | BN5: 1 | BO5: 1 | BP5: 1 | BQ5: 1 | BR5: 1 | BS5: 1 | BT5: 1 | BU5: 1 | BV5: 1 | BW5: 1 | BX5: 1 | BY5: 1 | BZ5: 1 | CA5: 1 | CB5: 1 | CC5: 1 | CD5: 1 | CE5: 1 | CF5: 1 | CG5: 1 | CH5: 1 | CI5: 1 | CJ5: 1 | CK5: 1 | CL5: 1 | CM5: 1 | CN5: 1 | CO5: 1 | CP5: 1 | CQ5: 1 | CR5: 1 | CS5: 1 | CT5: 1 | CU5: 1 | CV5: 1 | CW5: 1 | CX5: 1 | CY5: 1 | CZ5: 1 | DA5: 1 | DB5: 1 | DC5: 1 | DD5: 1 | DE5: 1 | DF5: 1 | DG5: 1 | DH5: 1 | DI5: 1 | DJ5: 1 | DK5: 1 | DL5: 1 | DM5: 1 | DN5: 1 | DO5: 1 | DP5: 1 | DQ5: 1 | DR5: 1 | DS5: 1 | DT5: 1 | DU5: 1 | DV5: 1 | DW5: 1 | DX5: 1 | DY5: 1 | DZ5: 1 | EA5: 1 | EB5: 1 | EC5: 1 | ED5: 1 | EE5: 1 | EF5: 1 | EG5: 1 | EH5: 1 | EI5: 1 | EJ5: 1 | EK5: 1 | EL5: 1 | EM5: 1 | EN5: 1 | EO5: 1 | EP5: 1 | EQ5: 1 | ER5: 1 | ES5: 1 | ET5: 1 | EU5: 1 | EV5: 1 | EW5: 1 | EX5: 1 | EY5: 1 | EZ5: 1 | FA5: 1 | FB5: 1 | FC5: 1 | FD5: 1 | FE5: 1 | FF5: 1 | FG5: 1 | FH5: 1 | FI5: 1 | FJ5: 1 | FK5: 1 | FL5: 1 | FM5: 1 | FN5: 1 | FO5: 1 | FP5: 1 | FQ5: 1 | FR5: 1 | FS5: 1 | FT5: 1 | FU5: 1 | FV5: 1 | FW5: 1 | FX5: 1 | FY5: 1 | FZ5: 1 | GA5: 1 | GB5: 1 | GC5: 1 | GD5: 1 | GE5: 1 | GF5: 1 | GG5: 1 | GH5: 1 | GI5: 1 | GJ5: 1 | GK5: 1 | GL5: 1 | GM5: 1 | GN5: 1 | GO5: 1 | GP5: =HLOOKUP($GP$3,$AU$3:$GO$27,3,TRUE) -> 1
B6: 1 | C6: Уголь каменный | D6: 16109 | E6: УГ БУР НЕПОДМОС | F6: уголь энергетический (кроме антрацита) | G6: КРС | H6: ЗСБ | I6: ЗАОЗЕРНАЯ | J6: ЖЕРЕБЦОВО | K6: 910 | L6: полувагон | M6: Внутр. перевозки | N6: неконтейнерная | O6: Южное | P6: 81213597 | Q6: АО "СУЭК-КРАСНОЯРСК" | R6: АО "СУЭК" | S6: 4334533 | T6: 3943795638 | U6: 59894 | W6: 2288495144 | X6: 75 | Y6: маршрутная | Z6: 4 | AA6: 4 | AB6: 4 | AC6: 562.77 | AD6: 335.35 | AE6: 921.88 | AF6: ='Цены,перевалка,аренда'!$C$26*SUM(Уголь_эластика_внутр!Z6+Уголь_эластика_внутр!AA6+Уголь_эластика_внутр!AB6)/Уголь_эластика_внутр!X6 -> 160 | AI6: 445.5 | AJ6: ='Цены,перевалка,аренда'!$D$9 -> 1750 | AK6: =AJ6/'Цены,перевалка,аренда'!$C$1 -> 22.934127 | AL6: =AE6+AF6+AG6 -> 1081.88 | AM6: =AJ6-AL6 -> 668.12 | AN6: =AI6+AH6+AG6+AF6+AE6 -> 1527.38 | AO6: =(AJ6-AN6)/AJ6 -> 0.12721143 | AP6: =AL6/AJ6 -> 0.61821714 | AQ6: =AE6/AJ6 -> 0.52678857 | AR6: =AE6/AL6 -> 0.85210929 | AS6: Сибирская генерирующая компания | AU6: 1 | AV6: 1 | AW6: 1 | AX6: 1 | AY6: 1 | AZ6: 1 | BA6: 1 | BB6: 1 | BC6: 1 | BD6: 1 | BE6: 1 | BF6: 1 | BG6: 1 | BH6: 1 | BI6: 1 | BJ6: 1 | BK6: 1 | BL6: 1 | BM6: 1 | BN6: 1 | BO6: 1 | BP6: 1 | BQ6: 1 | BR6: 1 | BS6: 1 | BT6: 1 | BU6: 1 | BV6: 1 | BW6: 1 | BX6: 1 | BY6: 1 | BZ6: 1 | CA6: 1 | CB6: 1 | CC6: 1 | CD6: 1 | CE6: 1 | CF6: 1 | CG6: 1 | CH6: 1 | CI6: 1 | CJ6: 1 | CK6: 1 | CL6: 1 | CM6: 1 | CN6: 1 | CO6: 1 | CP6: 1 | CQ6: 1 | CR6: 1 | CS6: 1 | CT6: 1 | CU6: 1 | CV6: 1 | CW6: 1 | CX6: 1 | CY6: 1 | CZ6: 1 | DA6: 1 | DB6: 1 | DC6: 1 | DD6: 1 | DE6: 1 | DF6: 1 | DG6: 1 | DH6: 1 | DI6: 1 | DJ6: 1 | DK6: 1 | DL6: 1 | DM6: 1 | DN6: 1 | DO6: 1 | DP6: 1 | DQ6: 1 | DR6: 1 | DS6: 1 | DT6: 1 | DU6: 1 | DV6: 1 | DW6: 1 | DX6: 1 | DY6: 1 | DZ6: 1 | EA6: 1 | EB6: 1 | EC6: 1 | ED6: 1 | EE6: 1 | EF6: 1 | EG6: 1 | EH6: 1 | EI6: 1 | EJ6: 1 | EK6: 1 | EL6: 1 | EM6: 1 | EN6: 1 | EO6: 1 | EP6: 1 | EQ6: 1 | ER6: 1 | ES6: 1 | ET6: 1 | EU6: 1 | EV6: 1 | EW6: 1 | EX6: 1 | EY6: 1 | EZ6: 1 | FA6: 1 | FB6: 1 | FC6: 1 | FD6: 1 | FE6: 1 | FF6: 1 | FG6: 1 | FH6: 1 | FI6: 1 | FJ6: 1 | FK6: 1 | FL6: 1 | FM6: 1 | FN6: 1 | FO6: 1 | FP6: 1 | FQ6: 1 | FR6: 1 | FS6: 1 | FT6: 1 | FU6: 1 | FV6: 1 | FW6: 1 | FX6: 1 | FY6: 1 | FZ6: 1 | GA6: 1 | GB6: 1 | GC6: 1 | GD6: 1 | GE6: 1 | GF6: 1 | GG6: 1 | GH6: 1 | GI6: 1 | GJ6: 1 | GK6: 1 | GL6: 1 | GM6: 1 | GN6: 1 | GO6: 1 | GP6: =HLOOKUP($GP$3,$AU$3:$GO$27,3,TRUE) -> 1
B7: 1 | C7: Уголь каменный | D7: 16109 | E7: УГ БУР НЕПОДМОС | F7: уголь энергетический (кроме антрацита) | G7: ЗАБ | H7: ЗАБ | I7: ЕКАТЕРИНОСЛ. | J7: БЛАГОВЕЩЕНСК | K7: 188 | L7: полувагон | M7: Внутр. перевозки | N7: неконтейнерная | O7: Восточное | P7: 57615980 | Q7: АО "АМУРУГОЛЬ" | R7: АО "Русский уголь" | S7: 1452479 | T7: 273065911 | U7: 20905 | W7: 340188751 | X7: 69 | Y7: маршрутная | Z7: 3 | AA7: 3 | AB7: 4 | AC7: 253.8 | AD7: 85.72 | AE7: 339.52 | AF7: ='Цены,перевалка,аренда'!$C$27*SUM(Уголь_эластика_внутр!Z7+Уголь_эластика_внутр!AA7+Уголь_эластика_внутр!AB7)/Уголь_эластика_внутр!X7 -> 101.44928 | AI7: 1857 | AJ7: ='Цены,перевалка,аренда'!$D$9 -> 1750 | AK7: =AJ7/'Цены,перевалка,аренда'!$C$1 -> 22.934127 | AL7: =AE7+AF7+AG7 -> 440.96928 | AM7: =AJ7-AL7 -> 1309.0307 | AN7: =AI7+AH7+AG7+AF7+AE7 -> 2297.9693 | AO7: =(AJ7-AN7)/AJ7 -> -0.3131253 | AP7: =AL7/AJ7 -> 0.25198244 | AQ7: =AE7/AJ7 -> 0.19401143 | AR7: =AE7/AL7 -> 0.76994026 | AS7: Дальневосточная генерирующая компания | AU7: 1 | AV7: 1 | AW7: 1 | AX7: 1 | AY7: 1 | AZ7: 1 | BA7: 1 | BB7: 1 | BC7: 1 | BD7: 1 | BE7: 1 | BF7: 1 | BG7: 1 | BH7: 1 | BI7: 1 | BJ7: 1 | BK7: 1 | BL7: 1 | BM7: 1 | BN7: 1 | BO7: 1 | BP7: 1 | BQ7: 1 | BR7: 1 | BS7: 1 | BT7: 1 | BU7: 1 | BV7: 1 | BW7: 1 | BX7: 1 | BY7: 1 | BZ7: 1 | CA7: 1 | CB7: 1 | CC7: 1 | CD7: 1 | CE7: 1 | CF7: 1 | CG7: 1 | CH7: 1 | CI7: 1 | CJ7: 1 | CK7: 1 | CL7: 1 | CM7: 1 | CN7: 1 | CO7: 1 | CP7: 1 | CQ7: 1 | CR7: 1 | CS7: 1 | CT7: 1 | CU7: 1 | CV7: 1 | CW7: 1 | CX7: 1 | CY7: 1 | CZ7: 1 | DA7: 1 | DB7: 1 | DC7: 1 | DD7: 1 | DE7: 1 | DF7: 1 | DG7: 1 | DH7: 1 | DI7: 1 | DJ7: 1 | DK7: 1 | DL7: 1 | DM7: 1 | DN7: 1 | DO7: 1 | DP7: 1 | DQ7: 1 | DR7: 1 | DS7: 1 | DT7: 1 | DU7: 1 | DV7: 1 | DW7: 1 | DX7: 1 | DY7: 1 | DZ7: 1 | EA7: 1 | EB7: 1 | EC7: 1 | ED7: 1 | EE7: 1 | EF7: 1 | EG7: 1 | EH7: 1 | EI7: 1 | EJ7: 1 | EK7: 1 | EL7: 1 | EM7: 1 | EN7: 1 | EO7: 1 | EP7: 1 | EQ7: 1 | ER7: 1 | ES7: 1 | ET7: 1 | EU7: 1 | EV7: 1 | EW7: 1 | EX7: 1 | EY7: 1 | EZ7: 1 | FA7: 1 | FB7: 1 | FC7: 1 | FD7: 1 | FE7: 1 | FF7: 1 | FG7: 1 | FH7: 1 | FI7: 1 | FJ7: 1 | FK7: 1 | FL7: 1 | FM7: 1 | FN7: 1 | FO7: 1 | FP7: 1 | FQ7: 1 | FR7: 1 | FS7: 1 | FT7: 1 | FU7: 1 | FV7: 1 | FW7: 1 | FX7: 1 | FY7: 1 | FZ7: 1 | GA7: 1 | GB7: 1 | GC7: 1 | GD7: 1 | GE7: 1 | GF7: 1 | GG7: 1 | GH7: 1 | GI7: 1 | GJ7: 1 | GK7: 1 | GL7: 1 | GM7: 1 | GN7: 1 | GO7: 1 | GP7: =HLOOKUP($GP$3,$AU$3:$GO$27,3,TRUE) -> 1
B8: 1 | C8: Уголь каменный | D8: 16109 | E8: УГ БУР НЕПОДМОС | F8: уголь энергетический (кроме антрацита) | G8: КРС | H8: МСК | I8: КИЛЬЧУГ | J8: ВОСЛЕБОВО | K8: 4326 | L8: полувагон | M8: Внутр. перевозки | N8: неконтейнерная | O8: Северо-Западное | P8: 78465421 | Q8: АО "РУССКИЙ УГОЛЬ" | R8: АО "Русский уголь" | S8: 1635392 | T8: 7074978411 | U8: 23520 | W8: 2299056352 | X8: 69 | Y8: маршрутная | Z8: 10 | AA8: 10 | AB8: 4 | AC8: 1568 | AD8: 961.33 | AE8: 2529.33 | AF8: ='Цены,перевалка,аренда'!$C$27*SUM(Уголь_эластика_внутр!Z8+Уголь_эластика_внутр!AA8+Уголь_эластика_внутр!AB8)/Уголь_эластика_внутр!X8 -> 243.47826 | AI8: 586 | AJ8: ='Цены,перевалка,аренда'!$D$9 -> 1750 | AK8: =AJ8/'Цены,перевалка,аренда'!$C$1 -> 22.934127 | AL8: =AE8+AF8+AG8 -> 2772.8083 | AM8: =AJ8-AL8 -> -1022.8083 | AN8: =AI8+AH8+AG8+AF8+AE8 -> 3358.8083 | AO8: =(AJ8-AN8)/AJ8 -> -0.91931901 | AP8: =AL8/AJ8 -> 1.5844619 | AQ8: =AE8/AJ8 -> 1.4453314 | AR8: =AE8/AL8 -> 0.91219073 | AS8: Рязанская ГРЭС | AU8: 1 | AV8: 1 | AW8: 1 | AX8: 1 | AY8: 1 | AZ8: 1 | BA8: 1 | BB8: 1 | BC8: 1 | BD8: 1 | BE8: 1 | BF8: 1 | BG8: 1 | BH8: 1 | BI8: 1 | BJ8: 1 | BK8: 1 | BL8: 1 | BM8: 1 | BN8: 1 | BO8: 1 | BP8: 1 | BQ8: 1 | BR8: 1 | BS8: 1 | BT8: 1 | BU8: 1 | BV8: 1 | BW8: 1 | BX8: 1 | BY8: 1 | BZ8: 1 | CA8: 1 | CB8: 1 | CC8: 1 | CD8: 1 | CE8: 1 | CF8: 1 | CG8: 1 | CH8: 1 | CI8: 1 | CJ8: 1 | CK8: 1 | CL8: 1 | CM8: 1 | CN8: 1 | CO8: 1 | CP8: 1 | CQ8: 1 | CR8: 1 | CS8: 1 | CT8: 1 | CU8: 1 | CV8: 1 | CW8: 1 | CX8: 1 | CY8: 1 | CZ8: 1 | DA8: 1 | DB8: 1 | DC8: 1 | DD8: 1 | DE8: 1 | DF8: 1 | DG8: 1 | DH8: 1 | DI8: 1 | DJ8: 1 | DK8: 1 | DL8: 1 | DM8: 1 | DN8: 1 | DO8: 1 | DP8: 1 | DQ8: 1 | DR8: 1 | DS8: 1 | DT8: 1 | DU8: 1 | DV8: 1 | DW8: 1 | DX8: 1 | DY8: 1 | DZ8: 1 | EA8: 1 | EB8: 1 | EC8: 1 | ED8: 1 | EE8: 1 | EF8: 1 | EG8: 1 | EH8: 1 | EI8: 1 | EJ8: 1 | EK8: 1 | EL8: 1 | EM8: 1 | EN8: 1 | EO8: 1 | EP8: 1 | EQ8: 1 | ER8: 1 | ES8: 1 | ET8: 1 | EU8: 1 | EV8: 1 | EW8: 1 | EX8: 1 | EY8: 1 | EZ8: 1 | FA8: 1 | FB8: 1 | FC8: 1 | FD8: 1 | FE8: 1 | FF8: 1 | FG8: 1 | FH8: 1 | FI8: 1 | FJ8: 1 | FK8: 1 | FL8: 1 | FM8: 1 | FN8: 1 | FO8: 1 | FP8: 1 | FQ8: 1 | FR8: 1 | FS8: 1 | FT8: 1 | FU8: 1 | FV8: 1 | FW8: 1 | FX8: 1 | FY8: 1 | FZ8: 1 | GA8: 1 | GB8: 1 | GC8: 1 | GD8: 1 | GE8: 1 | GF8: 1 | GG8: 1 | GH8: 1 | GI8: 1 | GJ8: 1 | GK8: 1 | GL8: 1 | GM8: 1 | GN8: 1 | GO8: 1 | GP8: =HLOOKUP($GP$3,$AU$3:$GO$27,3,TRUE) -> 1
B9: 1 | C9: Уголь каменный | D9: 16112 | E9: УГОЛЬ Д | F9: уголь энергетический (кроме антрацита) | G9: КРС | H9: ЗСБ | I9: КАМЫШТА | J9: БАРДИНО | K9: 319 | L9: полувагон | M9: Внутр. перевозки | N9: неконтейнерная | O9: Южное | P9: 26649063 | Q9: ООО "РАЗРЕЗ КИРБИНСКИЙ" | R9: АО "Русский уголь" | S9: 53637 | T9: 17110140 | U9: 764 | W9: 17354701 | X9: 69 | Y9: группа вагонов | Z9: 4 | AA9: 4 | AB9: 4 | AC9: 372.39 | AD9: 157.39 | AE9: 513.88 | AF9: ='Цены,перевалка,аренда'!$C$27*SUM(Уголь_эластика_внутр!Z9+Уголь_эластика_внутр!AA9+Уголь_эластика_внутр!AB9)/Уголь_эластика_внутр!X9 -> 121.73913 | AI9: 586 | AJ9: ='Цены,перевалка,аренда'!$D$8 -> 3300 | AK9: =AJ9/'Цены,перевалка,аренда'!$C$1 -> 43.24721 | AL9: =AE9+AF9+AG9 -> 635.61913 | AM9: =AJ9-AL9 -> 2664.3809 | AN9: =AI9+AH9+AG9+AF9+AE9 -> 1221.6191 | AO9: =(AJ9-AN9)/AJ9 -> 0.62981238 | AP9: =AL9/AJ9 -> 0.19261186 | AQ9: =AE9/AJ9 -> 0.15572121 | AR9: =AE9/AL9 -> 0.80847158 | AS9: Аграрный холдинг | AU9: 1 | AV9: 1 | AW9: 1 | AX9: 1 | AY9: 1 | AZ9: 1 | BA9: 1 | BB9: 1 | BC9: 1 | BD9: 1 | BE9: 1 | BF9: 1 | BG9: 1 | BH9: 1 | BI9: 1 | BJ9: 1 | BK9: 1 | BL9: 1 | BM9: 1 | BN9: 1 | BO9: 1 | BP9: 1 | BQ9: 1 | BR9: 1 | BS9: 1 | BT9: 1 | BU9: 1 | BV9: 1 | BW9: 1 | BX9: 1 | BY9: 1 | BZ9: 1 | CA9: 1 | CB9: 1 | CC9: 1 | CD9: 1 | CE9: 1 | CF9: 1 | CG9: 1 | CH9: 1 | CI9: 1 | CJ9: 1 | CK9: 1 | CL9: 1 | CM9: 1 | CN9: 1 | CO9: 1 | CP9: 1 | CQ9: 1 | CR9: 1 | CS9: 1 | CT9: 1 | CU9: 1 | CV9: 1 | CW9: 1 | CX9: 1 | CY9: 1 | CZ9: 1 | DA9: 1 | DB9: 1 | DC9: 1 | DD9: 1 | DE9: 1 | DF9: 1 | DG9: 1 | DH9: 1 | DI9: 1 | DJ9: 1 | DK9: 1 | DL9: 1 | DM9: 1 | DN9: 1 | DO9: 1 | DP9: 1 | DQ9: 1 | DR9: 1 | DS9: 1 | DT9: 1 | DU9: 1 | DV9: 1 | DW9: 1 | DX9: 1 | DY9: 1 | DZ9: 1 | EA9: 1 | EB9: 1 | EC9: 1 | ED9: 1 | EE9: 1 | EF9: 1 | EG9: 1 | EH9: 1 | EI9: 1 | EJ9: 1 | EK9: 1 | EL9: 1 | EM9: 1 | EN9: 1 | EO9: 1 | EP9: 1 | EQ9: 1 | ER9: 1 | ES9: 1 | ET9: 1 | EU9: 1 | EV9: 1 | EW9: 1 | EX9: 1 | EY9: 1 | EZ9: 1 | FA9: 1 | FB9: 1 | FC9: 1 | FD9: 1 | FE9: 1 | FF9: 1 | FG9: 1 | FH9: 1 | FI9: 1 | FJ9: 1 | FK9: 1 | FL9: 1 | FM9: 1 | FN9: 1 | FO9: 1 | FP9: 1 | FQ9: 1 | FR9: 1 | FS9: 1 | FT9: 1 | FU9: 1 | FV9: 1 | FW9: 1 | FX9: 1 | FY9: 1 | FZ9: 1 | GA9: 1 | GB9: 1 | GC9: 1 | GD9: 1 | GE9: 1 | GF9: 1 | GG9: 1 | GH9: 1 | GI9: 1 | GJ9: 1 | GK9: 1 | GL9: 1 | GM9: 1 | GN9: 1 | GO9: 1 | GP9: =HLOOKUP($GP$3,$AU$3:$GO$27,3,TRUE) -> 1
